package com.example.lw.appweb;

import java.io.DataInputStream;
import java.util.Enumeration;
import java.util.Hashtable;
import java.util.Vector;

public class ab
  implements Runnable
{
  private static int h;
  private static int i;
  private static aq t = new aq();
  private int A;
  String B = null;
  int C = -1;
  final g Code;
  private bi D;
  private int E;
  Hashtable I = new Hashtable();
  y J;
  bf Z;
  Hashtable a;
  String b;
  int c;
  public int d;
  private k e;
  private Vector f = new Vector();
  private boolean g;
  private int j;
  private bc k;
  private boolean l;
  private boolean m;
  private boolean n;
  private final Object[] o;
  private final int[] p;
  private final int q;
  private final int r;
  private boolean s = true;
  private int u;
  private int v;
  private int w;
  private int x;
  private int y;
  private bc z;
  
  ab(g paramg, Object[] paramArrayOfObject, int[] paramArrayOfInt, k paramk, Hashtable paramHashtable, boolean paramBoolean)
  {
    this.Code = paramg;
    this.o = paramArrayOfObject;
    this.p = paramArrayOfInt;
    if (paramHashtable != null) {
      this.I = paramHashtable;
    }
    this.g = paramBoolean;
    this.q = paramArrayOfInt[19];
    this.r = paramArrayOfInt[14];
    Code(paramk);
  }
  
  private boolean A()
  {
    return (this.Z.J()) && (!this.Z.Z().Code());
  }
  
  public static void Code()
  {
    t.Code(1000);
  }
  
  private void Code(k paramk)
  {
    this.e = new k(this, paramk, true, this.g);
    this.Z = new bf(this.e);
    this.J = new y(this.e);
  }
  
  private native void Code(boolean paramBoolean, String paramString);
  
  private int D()
  {
    return this.Z.Z().b();
  }
  
  private int E()
  {
    return this.Z.Z().c();
  }
  
  /* Error */
  static void J(int paramInt)
  {
    // Byte code:
    //   0: ldc 2
    //   2: monitorenter
    //   3: getstatic 134	ab:h	I
    //   6: ifeq +30 -> 36
    //   9: ldc2_w 135
    //   12: getstatic 134	ab:h	I
    //   15: i2l
    //   16: lmul
    //   17: ldc2_w 137
    //   20: iload_0
    //   21: i2l
    //   22: lmul
    //   23: ladd
    //   24: ldc2_w 139
    //   27: ldiv
    //   28: l2i
    //   29: putstatic 134	ab:h	I
    //   32: ldc 2
    //   34: monitorexit
    //   35: return
    //   36: iload_0
    //   37: putstatic 134	ab:h	I
    //   40: goto -8 -> 32
    //   43: astore_1
    //   44: ldc 2
    //   46: monitorexit
    //   47: aload_1
    //   48: athrow
    // Local variable table:
    //   start	length	slot	name	signature
    //   0	49	0	paramInt	int
    //   43	5	1	localObject	Object
    // Exception table:
    //   from	to	target	type
    //   3	32	43	finally
    //   36	40	43	finally
  }
  
  private void Z(int paramInt1, int paramInt2)
  {
    g.I.B();
    if (this.c != 0)
    {
      int i1 = C();
      if (i1 != 0)
      {
        g.Z.c(paramInt1);
        g.I.Code(i1, paramInt2);
        return;
      }
      g.I.C();
      return;
    }
    g.I.C();
  }
  
  private void u()
  {
    k localk = this.e;
    int i1 = 1;
    Object localObject = new DataInputStream(this.k);
    int i3 = this.k.n();
    int i2 = 0;
    int i4;
    for (;;)
    {
      i4 = ((DataInputStream)localObject).readUnsignedByte();
      if (i4 != 255) {
        break;
      }
      i2 = ((DataInputStream)localObject).readUnsignedByte();
      if (i1 == 1) {
        Z(2);
      }
      this.v = i2;
    }
    if (i1 > 1) {
      localk = new k(this, this.e, false, this.g);
    }
    localk.Code(this.k, (DataInputStream)localObject, i3, i4);
    if (i1 > 1)
    {
      g.I.B();
      this.e.Z = null;
      i3 = g.Z.B(this.c, 2);
      if ((this.B != null) && (i3 != 0)) {
        localk.Code(this.B, null, i3);
      }
      localObject = new bf(localk);
      if ((this.Z.J()) && (localk.Code((bf)localObject, i3, this.Z))) {
        ((bf)localObject).Code(true);
      }
      this.Z = ((bf)localObject);
      localObject = new y(localk);
      if ((this.J.Z()) && (localk.Code((y)localObject, i3, this.J))) {
        ((y)localObject).Code(true);
      }
      this.J = ((y)localObject);
      this.e = localk;
      this.e.Code(false);
      J();
    }
    for (;;)
    {
      if (i2 == 100) {
        Z(4);
      }
      i1 += 1;
      break;
      Thread.currentThread().setPriority(1);
    }
  }
  
  private boolean v()
  {
    return (this.J.Z()) && (!this.J.Code().Code()) && (!this.J.I().Code());
  }
  
  private int w()
  {
    return this.J.Code().b();
  }
  
  private int x()
  {
    return this.J.Code().c();
  }
  
  private int y()
  {
    return this.J.I().b();
  }
  
  private int z()
  {
    return this.J.I().c();
  }
  
  final void B(int paramInt)
  {
    i = this.j - paramInt;
  }
  
  public final boolean B()
  {
    return (this.k == null) || (this.k.o());
  }
  
  final int C()
  {
    return g.Z.B(g.Z.B(this.c, 1), 0);
  }
  
  String Code(char paramChar, String paramString, int paramInt)
  {
    switch (paramChar)
    {
    }
    do
    {
      return null;
      paramString = (String)this.I.get(paramString);
      if (paramString == null) {
        return null;
      }
      paramString = paramString.split("");
      if (paramInt < paramString.length) {
        return paramString[paramInt];
      }
      return null;
    } while (this.a == null);
    paramString = (Object[])this.a.get(paramString);
    if ((paramString != null) && (paramString[0] != null)) {
      return (String)paramString[0];
    }
    return null;
  }
  
  final void Code(int paramInt)
  {
    this.x += paramInt;
  }
  
  final void Code(int paramInt1, int paramInt2)
  {
    try
    {
      this.e.Code(this.J.Code(), paramInt1, paramInt2);
      return;
    }
    finally
    {
      localObject = finally;
      throw localObject;
    }
  }
  
  final void Code(int paramInt1, int paramInt2, int paramInt3)
  {
    try
    {
      this.J.I(paramInt3, paramInt1, paramInt2);
      this.J.J(paramInt3, paramInt1, paramInt2);
      this.Z.Code(this.J.I());
      return;
    }
    finally
    {
      localObject = finally;
      throw localObject;
    }
  }
  
  final void Code(int paramInt, boolean paramBoolean)
  {
    try
    {
      this.Z.Code(paramInt);
      if (this.J.Z())
      {
        if (!paramBoolean) {
          this.J.Code(this.Z.Z());
        }
        this.J.I(this.Z.Z());
      }
      return;
    }
    finally {}
  }
  
  final void Code(bi parambi)
  {
    if (this.D == parambi) {
      parambi.I(this.E);
    }
  }
  
  final void Code(bi parambi, int paramInt)
  {
    parambi.Code(paramInt, this);
  }
  
  public final void Code(String paramString)
  {
    if ((!this.I.isEmpty()) || ((this.a != null) && (!this.a.isEmpty()))) {}
    for (boolean bool = true;; bool = false)
    {
      Code(bool, paramString);
      return;
    }
  }
  
  final void Code(String paramString1, int paramInt, String paramString2)
  {
    switch (paramInt)
    {
    }
    for (;;)
    {
      try
      {
        Code(paramString2);
        return;
      }
      finally {}
      if (!this.I.containsKey(paramString2)) {
        this.f.addElement(paramString2);
      }
      this.I.put(paramString2, paramString1);
      continue;
      if (this.I.get(paramString2) == null)
      {
        this.I.put(paramString2, paramString1);
      }
      else
      {
        this.I.remove(paramString2);
        continue;
        this.I.put(paramString2, paramString1.replace(' ', '\000'));
      }
    }
  }
  
  final void Code(boolean paramBoolean)
  {
    try
    {
      this.Z.Code(paramBoolean);
      return;
    }
    finally
    {
      localObject = finally;
      throw localObject;
    }
  }
  
  final void Code(boolean paramBoolean, int paramInt1, int paramInt2, int paramInt3)
  {
    try
    {
      this.J.Code(paramBoolean);
      if (paramBoolean)
      {
        this.Z.Code(paramInt3, paramInt1, paramInt2);
        this.J.Code(this.Z.Z());
        this.J.I(this.Z.Z());
      }
      return;
    }
    finally {}
  }
  
  /* Error */
  final void Code(int[] paramArrayOfInt)
  {
    // Byte code:
    //   0: iconst_0
    //   1: istore_2
    //   2: aload_0
    //   3: monitorenter
    //   4: aload_0
    //   5: getfield 100	ab:Z	Lbf;
    //   8: invokevirtual 107	bf:Z	()Lbk;
    //   11: astore_3
    //   12: aload_1
    //   13: iconst_0
    //   14: aload_3
    //   15: invokevirtual 306	bk:B	()I
    //   18: iastore
    //   19: aload_1
    //   20: iconst_1
    //   21: aload_3
    //   22: invokevirtual 307	bk:C	()I
    //   25: iastore
    //   26: aload_3
    //   27: invokevirtual 111	bk:Code	()Z
    //   30: ifeq +17 -> 47
    //   33: aload_1
    //   34: iconst_2
    //   35: iload_2
    //   36: iastore
    //   37: aload_1
    //   38: iconst_3
    //   39: aload_3
    //   40: invokevirtual 309	bk:a	()I
    //   43: iastore
    //   44: aload_0
    //   45: monitorexit
    //   46: return
    //   47: iconst_1
    //   48: istore_2
    //   49: goto -16 -> 33
    //   52: astore_1
    //   53: aload_0
    //   54: monitorexit
    //   55: aload_1
    //   56: athrow
    // Local variable table:
    //   start	length	slot	name	signature
    //   0	57	0	this	ab
    //   0	57	1	paramArrayOfInt	int[]
    //   1	48	2	i1	int
    //   11	29	3	localbk	bk
    // Exception table:
    //   from	to	target	type
    //   4	33	52	finally
    //   37	44	52	finally
  }
  
  boolean Code(char paramChar, String paramString)
  {
    switch (paramChar)
    {
    default: 
      return false;
    case 'S': 
    case 'U': 
    case 'a': 
    case 'c': 
    case 'p': 
    case 'r': 
    case 's': 
    case 'x': 
      return this.I.containsKey(paramString);
    }
    return this.a.containsKey(paramString);
  }
  
  native void I();
  
  final void I(int paramInt)
  {
    this.y = paramInt;
  }
  
  final void I(int paramInt1, int paramInt2)
  {
    try
    {
      this.e.Code(this.J.I(), paramInt1, paramInt2);
      return;
    }
    finally
    {
      localObject = finally;
      throw localObject;
    }
  }
  
  final void I(int paramInt1, int paramInt2, int paramInt3)
  {
    try
    {
      this.J.Code(paramInt3, paramInt1, paramInt2);
      this.Z.Code(this.J.Code());
      return;
    }
    finally
    {
      localObject = finally;
      throw localObject;
    }
  }
  
  native void I(bi parambi);
  
  final void I(bi parambi, int paramInt)
  {
    if ((parambi != null) && (this.D != null) && (parambi != this.D))
    {
      Code(this.D);
      I(this.D);
    }
    this.D = parambi;
    this.E = paramInt;
    if (parambi != null) {
      I(parambi);
    }
  }
  
  native void J();
  
  native void Z();
  
  final void Z(int paramInt)
  {
    if (this.u != paramInt)
    {
      if ((paramInt == 3) && (this.j == 0)) {
        this.j = this.k.q();
      }
      this.u = paramInt;
      Z(paramInt, 21);
    }
    if (paramInt >= 4)
    {
      b.Code(0L, this.d, 0L);
      this.d = 0;
    }
    b.J();
  }
  
  final void Z(int paramInt1, int paramInt2, int paramInt3)
  {
    try
    {
      this.J.Z(paramInt3, paramInt1, paramInt2);
      this.Z.Code(this.J.I());
      return;
    }
    finally
    {
      localObject = finally;
      throw localObject;
    }
  }
  
  final void a()
  {
    g.I.B();
    try
    {
      if (this.c == 0)
      {
        g.I.C();
        throw new RuntimeException();
      }
    }
    finally {}
  }
  
  public final k b()
  {
    return this.e;
  }
  
  final int c()
  {
    return this.q;
  }
  
  int d()
  {
    return this.r;
  }
  
  final void e()
  {
    try
    {
      if (this.c != 0)
      {
        m();
        this.c = 0;
        this.e.c();
      }
      return;
    }
    finally
    {
      localObject = finally;
      throw localObject;
    }
  }
  
  final k f()
  {
    if (this.e.I()) {
      return this.e;
    }
    return null;
  }
  
  final void g()
  {
    try
    {
      if (this.k != null)
      {
        bc localbc = this.k;
        if (localbc != this.z) {
          this.A = 0;
        }
        this.w += this.k.n() - this.A;
        this.A = this.k.n();
        this.z = localbc;
      }
      if (this.e != null)
      {
        g.Z.C(this.c, 3, this.v);
        g.Z.C(this.c, 4, this.w);
        g.Z.C(this.c, 5, this.x);
        g.Z.C(this.c, 6, this.y);
      }
      return;
    }
    finally {}
  }
  
  final boolean h()
  {
    return this.p[56] == 1;
  }
  
  final String i()
  {
    return (String)this.o[42];
  }
  
  final String j()
  {
    return (String)this.o[53];
  }
  
  final int k()
  {
    return this.p[80];
  }
  
  final void l()
  {
    b.Code(this.k);
    this.m = true;
  }
  
  final void m()
  {
    this.l = true;
    b.Code(this.k);
    b.Code(new Runnable()
    {
      public final void run()
      {
        try
        {
          b.J();
          return;
        }
        catch (Throwable localThrowable) {}
      }
    });
  }
  
  final void n()
  {
    Enumeration localEnumeration = this.f.elements();
    while (localEnumeration.hasMoreElements()) {
      this.I.remove(localEnumeration.nextElement());
    }
    this.f.removeAllElements();
  }
  
  final Hashtable o()
  {
    return this.I;
  }
  
  final void p()
  {
    try
    {
      this.J.J();
      return;
    }
    finally
    {
      localObject = finally;
      throw localObject;
    }
  }
  
  final void q()
  {
    try
    {
      this.J.B();
      return;
    }
    finally
    {
      localObject = finally;
      throw localObject;
    }
  }
  
  final String r()
  {
    try
    {
      String str = this.J.C();
      return str;
    }
    finally
    {
      localObject = finally;
      throw localObject;
    }
  }
  
  /* Error */
  public void run()
  {
    // Byte code:
    //   0: getstatic 64	ab:t	Laq;
    //   3: invokevirtual 391	aq:I	()V
    //   6: aload_0
    //   7: getfield 86	ab:o	[Ljava/lang/Object;
    //   10: bipush 53
    //   12: aaload
    //   13: invokevirtual 394	java/lang/Object:toString	()Ljava/lang/String;
    //   16: ldc_w 396
    //   19: invokevirtual 400	java/lang/String:startsWith	(Ljava/lang/String;)Z
    //   22: ifeq +46 -> 68
    //   25: aload_0
    //   26: getfield 86	ab:o	[Ljava/lang/Object;
    //   29: bipush 53
    //   31: aaload
    //   32: invokevirtual 394	java/lang/Object:toString	()Ljava/lang/String;
    //   35: bipush 7
    //   37: invokevirtual 404	java/lang/String:substring	(I)Ljava/lang/String;
    //   40: astore 8
    //   42: aload 8
    //   44: invokestatic 409	ad:c	(Ljava/lang/String;)I
    //   47: bipush 16
    //   49: if_icmpne +19 -> 68
    //   52: aload_0
    //   53: getfield 120	ab:e	Lk;
    //   56: aload 8
    //   58: invokevirtual 410	k:Code	(Ljava/lang/String;)V
    //   61: getstatic 64	ab:t	Laq;
    //   64: invokevirtual 412	aq:Z	()V
    //   67: return
    //   68: getstatic 415	b:P	Z
    //   71: ifeq +58 -> 129
    //   74: aload_0
    //   75: getfield 90	ab:g	Z
    //   78: ifeq +51 -> 129
    //   81: aload_0
    //   82: getfield 86	ab:o	[Ljava/lang/Object;
    //   85: bipush 53
    //   87: aaload
    //   88: checkcast 232	java/lang/String
    //   91: ldc_w 417
    //   94: invokevirtual 400	java/lang/String:startsWith	(Ljava/lang/String;)Z
    //   97: ifeq +32 -> 129
    //   100: aload_0
    //   101: getfield 120	ab:e	Lk;
    //   104: aload_0
    //   105: getfield 86	ab:o	[Ljava/lang/Object;
    //   108: bipush 53
    //   110: aaload
    //   111: checkcast 232	java/lang/String
    //   114: invokevirtual 410	k:Code	(Ljava/lang/String;)V
    //   117: goto -56 -> 61
    //   120: astore 8
    //   122: getstatic 64	ab:t	Laq;
    //   125: invokevirtual 412	aq:Z	()V
    //   128: return
    //   129: aload_0
    //   130: getfield 165	ab:k	Lbc;
    //   133: ifnonnull +278 -> 411
    //   136: aload_0
    //   137: iconst_1
    //   138: invokevirtual 177	ab:Z	(I)V
    //   141: getstatic 420	b:O	Z
    //   144: ifeq +57 -> 201
    //   147: getstatic 415	b:P	Z
    //   150: ifeq +51 -> 201
    //   153: getstatic 424	b:K	[Ljava/lang/String;
    //   156: iconst_1
    //   157: aaload
    //   158: ifnonnull +43 -> 201
    //   161: aload_0
    //   162: getfield 86	ab:o	[Ljava/lang/Object;
    //   165: bipush 94
    //   167: aaload
    //   168: ifnull +17 -> 185
    //   171: aload_0
    //   172: getfield 86	ab:o	[Ljava/lang/Object;
    //   175: bipush 94
    //   177: aaload
    //   178: checkcast 426	[B
    //   181: arraylength
    //   182: ifgt +19 -> 201
    //   185: aload_0
    //   186: getfield 86	ab:o	[Ljava/lang/Object;
    //   189: bipush 53
    //   191: aaload
    //   192: ldc_w 428
    //   195: invokevirtual 431	java/lang/Object:equals	(Ljava/lang/Object;)Z
    //   198: ifne +234 -> 432
    //   201: invokestatic 432	b:B	()V
    //   204: aload_0
    //   205: getfield 86	ab:o	[Ljava/lang/Object;
    //   208: iconst_1
    //   209: ldc_w 434
    //   212: invokestatic 437	b:B	(Ljava/lang/String;)Ljava/lang/String;
    //   215: aastore
    //   216: aload_0
    //   217: getfield 86	ab:o	[Ljava/lang/Object;
    //   220: iconst_2
    //   221: ldc_w 439
    //   224: invokestatic 437	b:B	(Ljava/lang/String;)Ljava/lang/String;
    //   227: aastore
    //   228: aload_0
    //   229: getfield 86	ab:o	[Ljava/lang/Object;
    //   232: iconst_3
    //   233: ldc_w 441
    //   236: invokestatic 437	b:B	(Ljava/lang/String;)Ljava/lang/String;
    //   239: aastore
    //   240: aload_0
    //   241: getfield 86	ab:o	[Ljava/lang/Object;
    //   244: iconst_4
    //   245: ldc_w 443
    //   248: invokestatic 437	b:B	(Ljava/lang/String;)Ljava/lang/String;
    //   251: aastore
    //   252: new 445	java/lang/StringBuilder
    //   255: dup
    //   256: invokespecial 446	java/lang/StringBuilder:<init>	()V
    //   259: ldc_w 448
    //   262: invokevirtual 452	java/lang/StringBuilder:append	(Ljava/lang/String;)Ljava/lang/StringBuilder;
    //   265: getstatic 455	g:Code	Le;
    //   268: invokeinterface 459 1 0
    //   273: invokevirtual 452	java/lang/StringBuilder:append	(Ljava/lang/String;)Ljava/lang/StringBuilder;
    //   276: ldc_w 461
    //   279: invokevirtual 452	java/lang/StringBuilder:append	(Ljava/lang/String;)Ljava/lang/StringBuilder;
    //   282: invokestatic 464	o:Code	()Ljava/lang/String;
    //   285: invokevirtual 452	java/lang/StringBuilder:append	(Ljava/lang/String;)Ljava/lang/StringBuilder;
    //   288: invokevirtual 465	java/lang/StringBuilder:toString	()Ljava/lang/String;
    //   291: astore 8
    //   293: aload_0
    //   294: getfield 86	ab:o	[Ljava/lang/Object;
    //   297: bipush 54
    //   299: aload 8
    //   301: aastore
    //   302: aload_0
    //   303: getfield 86	ab:o	[Ljava/lang/Object;
    //   306: bipush 97
    //   308: getstatic 455	g:Code	Le;
    //   311: invokeinterface 467 1 0
    //   316: aastore
    //   317: aload_0
    //   318: getfield 86	ab:o	[Ljava/lang/Object;
    //   321: bipush 34
    //   323: getstatic 455	g:Code	Le;
    //   326: invokeinterface 459 1 0
    //   331: aastore
    //   332: aload_0
    //   333: getfield 86	ab:o	[Ljava/lang/Object;
    //   336: bipush 49
    //   338: invokestatic 469	o:I	()Ljava/lang/String;
    //   341: aastore
    //   342: aload_0
    //   343: getfield 86	ab:o	[Ljava/lang/Object;
    //   346: bipush 57
    //   348: invokestatic 471	o:Z	()Ljava/lang/String;
    //   351: aastore
    //   352: invokestatic 473	b:g	()I
    //   355: istore_1
    //   356: invokestatic 475	b:h	()I
    //   359: istore_2
    //   360: iload_1
    //   361: iconst_m1
    //   362: if_icmpeq +129 -> 491
    //   365: iload_2
    //   366: iconst_m1
    //   367: if_icmpeq +124 -> 491
    //   370: iload_2
    //   371: invokestatic 479	java/lang/Integer:toString	(I)Ljava/lang/String;
    //   374: astore 8
    //   376: aload 8
    //   378: invokevirtual 482	java/lang/String:length	()I
    //   381: iconst_3
    //   382: if_icmpge +74 -> 456
    //   385: new 445	java/lang/StringBuilder
    //   388: dup
    //   389: invokespecial 446	java/lang/StringBuilder:<init>	()V
    //   392: ldc_w 484
    //   395: invokevirtual 452	java/lang/StringBuilder:append	(Ljava/lang/String;)Ljava/lang/StringBuilder;
    //   398: aload 8
    //   400: invokevirtual 452	java/lang/StringBuilder:append	(Ljava/lang/String;)Ljava/lang/StringBuilder;
    //   403: invokevirtual 465	java/lang/StringBuilder:toString	()Ljava/lang/String;
    //   406: astore 8
    //   408: goto -32 -> 376
    //   411: aload_0
    //   412: getfield 165	ab:k	Lbc;
    //   415: invokestatic 353	b:Code	(Ljava/io/InputStream;)V
    //   418: goto -277 -> 141
    //   421: astore 8
    //   423: getstatic 64	ab:t	Laq;
    //   426: invokevirtual 412	aq:Z	()V
    //   429: aload 8
    //   431: athrow
    //   432: getstatic 486	b:D	Z
    //   435: ifeq -231 -> 204
    //   438: aload_0
    //   439: iconst_0
    //   440: putfield 82	ab:s	Z
    //   443: goto -239 -> 204
    //   446: astore 8
    //   448: aload_0
    //   449: iconst_5
    //   450: invokevirtual 177	ab:Z	(I)V
    //   453: goto -392 -> 61
    //   456: aload_0
    //   457: getfield 86	ab:o	[Ljava/lang/Object;
    //   460: bipush 92
    //   462: new 445	java/lang/StringBuilder
    //   465: dup
    //   466: invokespecial 446	java/lang/StringBuilder:<init>	()V
    //   469: iload_1
    //   470: invokestatic 479	java/lang/Integer:toString	(I)Ljava/lang/String;
    //   473: invokevirtual 452	java/lang/StringBuilder:append	(Ljava/lang/String;)Ljava/lang/StringBuilder;
    //   476: ldc_w 488
    //   479: invokevirtual 452	java/lang/StringBuilder:append	(Ljava/lang/String;)Ljava/lang/StringBuilder;
    //   482: aload 8
    //   484: invokevirtual 452	java/lang/StringBuilder:append	(Ljava/lang/String;)Ljava/lang/StringBuilder;
    //   487: invokevirtual 465	java/lang/StringBuilder:toString	()Ljava/lang/String;
    //   490: aastore
    //   491: aload_0
    //   492: getfield 86	ab:o	[Ljava/lang/Object;
    //   495: bipush 41
    //   497: getstatic 490	b:h	Ljava/lang/String;
    //   500: aastore
    //   501: aload_0
    //   502: getfield 88	ab:p	[I
    //   505: bipush 74
    //   507: bipush 109
    //   509: iastore
    //   510: aload_0
    //   511: getfield 88	ab:p	[I
    //   514: bipush 75
    //   516: ldc_w 492
    //   519: iconst_0
    //   520: invokevirtual 496	java/lang/String:charAt	(I)C
    //   523: iastore
    //   524: getstatic 455	g:Code	Le;
    //   527: invokeinterface 498 1 0
    //   532: ifeq +548 -> 1080
    //   535: iconst_1
    //   536: istore_2
    //   537: aload_0
    //   538: getfield 88	ab:p	[I
    //   541: astore 8
    //   543: aload 8
    //   545: bipush 24
    //   547: iaload
    //   548: istore 4
    //   550: getstatic 499	b:g	Z
    //   553: ifeq +532 -> 1085
    //   556: iconst_1
    //   557: istore_1
    //   558: goto +784 -> 1342
    //   561: getstatic 455	g:Code	Le;
    //   564: invokeinterface 498 1 0
    //   569: ifeq +526 -> 1095
    //   572: ldc_w 500
    //   575: istore_3
    //   576: aload 8
    //   578: bipush 24
    //   580: iload_3
    //   581: ldc_w 501
    //   584: iload_2
    //   585: iload_1
    //   586: iconst_4
    //   587: ior
    //   588: ior
    //   589: ldc_w 502
    //   592: ior
    //   593: ldc_w 503
    //   596: ior
    //   597: sipush 4096
    //   600: ior
    //   601: ior
    //   602: ior
    //   603: ldc_w 504
    //   606: ior
    //   607: ldc_w 505
    //   610: ior
    //   611: ldc_w 506
    //   614: ior
    //   615: ldc_w 507
    //   618: ior
    //   619: iload 4
    //   621: ior
    //   622: iastore
    //   623: aload_0
    //   624: getfield 88	ab:p	[I
    //   627: astore 8
    //   629: aload 8
    //   631: bipush 43
    //   633: iaload
    //   634: istore 7
    //   636: getstatic 509	b:n	Z
    //   639: ifeq +461 -> 1100
    //   642: sipush 512
    //   645: istore_1
    //   646: getstatic 511	b:o	Z
    //   649: ifeq +456 -> 1105
    //   652: sipush 2048
    //   655: istore_2
    //   656: getstatic 513	b:p	Z
    //   659: ifeq +451 -> 1110
    //   662: ldc_w 501
    //   665: istore_3
    //   666: aload_0
    //   667: getfield 120	ab:e	Lk;
    //   670: getfield 515	k:I	Lk;
    //   673: ifnonnull +442 -> 1115
    //   676: sipush 4096
    //   679: istore 4
    //   681: getstatic 517	b:v	Z
    //   684: ifeq +437 -> 1121
    //   687: ldc_w 505
    //   690: istore 5
    //   692: getstatic 455	g:Code	Le;
    //   695: invokeinterface 519 1 0
    //   700: ifne +427 -> 1127
    //   703: ldc_w 504
    //   706: istore 6
    //   708: aload 8
    //   710: bipush 43
    //   712: iload 6
    //   714: ldc_w 520
    //   717: iload 4
    //   719: iload_3
    //   720: ldc_w 521
    //   723: iload_2
    //   724: iload_1
    //   725: sipush 16432
    //   728: ior
    //   729: iconst_0
    //   730: ior
    //   731: ior
    //   732: ldc_w 500
    //   735: ior
    //   736: ior
    //   737: ior
    //   738: ldc_w 502
    //   741: ior
    //   742: ior
    //   743: ldc_w 506
    //   746: ior
    //   747: ior
    //   748: iload 5
    //   750: ior
    //   751: ior
    //   752: iload 7
    //   754: ior
    //   755: iastore
    //   756: aload_0
    //   757: getfield 88	ab:p	[I
    //   760: bipush 25
    //   762: getstatic 455	g:Code	Le;
    //   765: invokeinterface 522 1 0
    //   770: iastore
    //   771: aload_0
    //   772: getfield 88	ab:p	[I
    //   775: bipush 26
    //   777: getstatic 455	g:Code	Le;
    //   780: invokeinterface 523 1 0
    //   785: iastore
    //   786: aload_0
    //   787: getfield 88	ab:p	[I
    //   790: bipush 47
    //   792: getstatic 455	g:Code	Le;
    //   795: invokeinterface 524 1 0
    //   800: iastore
    //   801: aload_0
    //   802: getfield 88	ab:p	[I
    //   805: bipush 48
    //   807: getstatic 455	g:Code	Le;
    //   810: invokeinterface 525 1 0
    //   815: iastore
    //   816: aload_0
    //   817: getfield 86	ab:o	[Ljava/lang/Object;
    //   820: bipush 22
    //   822: getstatic 527	b:J	J
    //   825: getstatic 529	b:B	J
    //   828: lsub
    //   829: invokestatic 533	java/lang/String:valueOf	(J)Ljava/lang/String;
    //   832: aastore
    //   833: aload_0
    //   834: getfield 88	ab:p	[I
    //   837: bipush 58
    //   839: invokestatic 539	java/lang/System:currentTimeMillis	()J
    //   842: ldc2_w 540
    //   845: ldiv
    //   846: l2i
    //   847: iastore
    //   848: aload_0
    //   849: getfield 86	ab:o	[Ljava/lang/Object;
    //   852: bipush 59
    //   854: invokestatic 547	java/util/TimeZone:getDefault	()Ljava/util/TimeZone;
    //   857: invokestatic 553	java/util/Calendar:getInstance	(Ljava/util/TimeZone;)Ljava/util/Calendar;
    //   860: invokevirtual 556	java/util/Calendar:getTimeZone	()Ljava/util/TimeZone;
    //   863: invokevirtual 559	java/util/TimeZone:getID	()Ljava/lang/String;
    //   866: aastore
    //   867: aload_0
    //   868: getfield 88	ab:p	[I
    //   871: astore 8
    //   873: getstatic 562	b:H	Z
    //   876: ifeq +257 -> 1133
    //   879: iconst_1
    //   880: istore_1
    //   881: aload 8
    //   883: bipush 61
    //   885: iload_1
    //   886: iastore
    //   887: aload_0
    //   888: getfield 88	ab:p	[I
    //   891: bipush 68
    //   893: getstatic 223	ab:i	I
    //   896: iastore
    //   897: aload_0
    //   898: getfield 88	ab:p	[I
    //   901: bipush 69
    //   903: getstatic 134	ab:h	I
    //   906: iastore
    //   907: aload_0
    //   908: getfield 88	ab:p	[I
    //   911: bipush 82
    //   913: getstatic 563	b:r	I
    //   916: iastore
    //   917: getstatic 424	b:K	[Ljava/lang/String;
    //   920: iconst_1
    //   921: aaload
    //   922: ifnull +15 -> 937
    //   925: aload_0
    //   926: getfield 86	ab:o	[Ljava/lang/Object;
    //   929: bipush 91
    //   931: getstatic 424	b:K	[Ljava/lang/String;
    //   934: iconst_3
    //   935: aaload
    //   936: aastore
    //   937: aload_0
    //   938: aload_0
    //   939: getfield 86	ab:o	[Ljava/lang/Object;
    //   942: aload_0
    //   943: getfield 88	ab:p	[I
    //   946: aload_0
    //   947: getfield 86	ab:o	[Ljava/lang/Object;
    //   950: bipush 53
    //   952: aaload
    //   953: checkcast 232	java/lang/String
    //   956: aload_0
    //   957: getfield 86	ab:o	[Ljava/lang/Object;
    //   960: bipush 38
    //   962: aaload
    //   963: checkcast 232	java/lang/String
    //   966: invokestatic 568	ba:Code	(Ljava/lang/String;Ljava/lang/String;)I
    //   969: aload_0
    //   970: getfield 82	ab:s	Z
    //   973: invokestatic 573	ap:Code	([Ljava/lang/Object;[IIZ)Lbc;
    //   976: putfield 165	ab:k	Lbc;
    //   979: aload_0
    //   980: getfield 357	ab:l	Z
    //   983: ifne +155 -> 1138
    //   986: aload_0
    //   987: invokespecial 575	ab:u	()V
    //   990: aload_0
    //   991: getfield 165	ab:k	Lbc;
    //   994: invokestatic 353	b:Code	(Ljava/io/InputStream;)V
    //   997: goto -936 -> 61
    //   1000: astore 8
    //   1002: aload_0
    //   1003: getfield 319	ab:u	I
    //   1006: iconst_5
    //   1007: if_icmpge +215 -> 1222
    //   1010: aload_0
    //   1011: getfield 120	ab:e	Lk;
    //   1014: getfield 515	k:I	Lk;
    //   1017: ifnull +13 -> 1030
    //   1020: aload_0
    //   1021: getfield 88	ab:p	[I
    //   1024: bipush 62
    //   1026: iaload
    //   1027: ifne +17 -> 1044
    //   1030: aload_0
    //   1031: getfield 88	ab:p	[I
    //   1034: bipush 24
    //   1036: iaload
    //   1037: ldc_w 502
    //   1040: iand
    //   1041: ifeq +181 -> 1222
    //   1044: aload_0
    //   1045: aconst_null
    //   1046: invokespecial 97	ab:Code	(Lk;)V
    //   1049: aload_0
    //   1050: getfield 88	ab:p	[I
    //   1053: bipush 62
    //   1055: iconst_0
    //   1056: iastore
    //   1057: aload_0
    //   1058: getfield 88	ab:p	[I
    //   1061: astore 8
    //   1063: aload 8
    //   1065: bipush 43
    //   1067: aload 8
    //   1069: bipush 43
    //   1071: iaload
    //   1072: sipush 4096
    //   1075: ior
    //   1076: iastore
    //   1077: goto -1071 -> 6
    //   1080: iconst_0
    //   1081: istore_2
    //   1082: goto -545 -> 537
    //   1085: iconst_2
    //   1086: istore_1
    //   1087: goto +255 -> 1342
    //   1090: iconst_0
    //   1091: istore_2
    //   1092: goto -531 -> 561
    //   1095: iconst_0
    //   1096: istore_3
    //   1097: goto -521 -> 576
    //   1100: iconst_0
    //   1101: istore_1
    //   1102: goto -456 -> 646
    //   1105: iconst_0
    //   1106: istore_2
    //   1107: goto -451 -> 656
    //   1110: iconst_0
    //   1111: istore_3
    //   1112: goto -446 -> 666
    //   1115: iconst_0
    //   1116: istore 4
    //   1118: goto -437 -> 681
    //   1121: iconst_0
    //   1122: istore 5
    //   1124: goto -432 -> 692
    //   1127: iconst_0
    //   1128: istore 6
    //   1130: goto -422 -> 708
    //   1133: iconst_0
    //   1134: istore_1
    //   1135: goto -254 -> 881
    //   1138: aload_0
    //   1139: bipush 7
    //   1141: invokevirtual 177	ab:Z	(I)V
    //   1144: goto -154 -> 990
    //   1147: astore 8
    //   1149: aload_0
    //   1150: getfield 577	ab:b	Ljava/lang/String;
    //   1153: ifnull +131 -> 1284
    //   1156: aload_0
    //   1157: getfield 577	ab:b	Ljava/lang/String;
    //   1160: astore 8
    //   1162: aload_0
    //   1163: aconst_null
    //   1164: putfield 577	ab:b	Ljava/lang/String;
    //   1167: aload_0
    //   1168: aload_0
    //   1169: getfield 120	ab:e	Lk;
    //   1172: getfield 515	k:I	Lk;
    //   1175: invokespecial 97	ab:Code	(Lk;)V
    //   1178: aload_0
    //   1179: getfield 86	ab:o	[Ljava/lang/Object;
    //   1182: bipush 38
    //   1184: aload_0
    //   1185: getfield 86	ab:o	[Ljava/lang/Object;
    //   1188: bipush 53
    //   1190: aaload
    //   1191: aastore
    //   1192: aload_0
    //   1193: getfield 86	ab:o	[Ljava/lang/Object;
    //   1196: bipush 53
    //   1198: aload 8
    //   1200: aastore
    //   1201: aload_0
    //   1202: getfield 86	ab:o	[Ljava/lang/Object;
    //   1205: bipush 42
    //   1207: aconst_null
    //   1208: aastore
    //   1209: aload_0
    //   1210: getfield 86	ab:o	[Ljava/lang/Object;
    //   1213: bipush 77
    //   1215: getstatic 579	g:d	[B
    //   1218: aastore
    //   1219: goto -1213 -> 6
    //   1222: aload_0
    //   1223: getfield 580	ab:n	Z
    //   1226: ifne +42 -> 1268
    //   1229: aload_0
    //   1230: iconst_1
    //   1231: putfield 580	ab:n	Z
    //   1234: aload_0
    //   1235: getfield 84	ab:Code	Lg;
    //   1238: invokevirtual 146	g:B	()V
    //   1241: aload_0
    //   1242: getfield 84	ab:Code	Lg;
    //   1245: iconst_1
    //   1246: invokevirtual 581	g:Code	(Z)V
    //   1249: getstatic 153	g:Z	Law;
    //   1252: iconst_3
    //   1253: invokevirtual 157	aw:c	(I)V
    //   1256: aload_0
    //   1257: getfield 84	ab:Code	Lg;
    //   1260: bipush 66
    //   1262: invokevirtual 582	g:Code	(I)V
    //   1265: goto -1259 -> 6
    //   1268: aload_0
    //   1269: iconst_0
    //   1270: bipush 28
    //   1272: invokespecial 323	ab:Z	(II)V
    //   1275: aload_0
    //   1276: bipush 6
    //   1278: invokevirtual 177	ab:Z	(I)V
    //   1281: goto -1220 -> 61
    //   1284: aload_0
    //   1285: getfield 357	ab:l	Z
    //   1288: ifne -1227 -> 61
    //   1291: aload_0
    //   1292: getfield 355	ab:m	Z
    //   1295: ifeq +11 -> 1306
    //   1298: aload_0
    //   1299: iconst_0
    //   1300: putfield 355	ab:m	Z
    //   1303: goto -1297 -> 6
    //   1306: aload_0
    //   1307: getfield 165	ab:k	Lbc;
    //   1310: ifnull +27 -> 1337
    //   1313: aload_0
    //   1314: getfield 165	ab:k	Lbc;
    //   1317: invokevirtual 584	bc:m	()I
    //   1320: istore_1
    //   1321: aload_0
    //   1322: iload_1
    //   1323: bipush 28
    //   1325: invokespecial 323	ab:Z	(II)V
    //   1328: aload_0
    //   1329: bipush 6
    //   1331: invokevirtual 177	ab:Z	(I)V
    //   1334: goto -1273 -> 61
    //   1337: iconst_0
    //   1338: istore_1
    //   1339: goto -18 -> 1321
    //   1342: iload_2
    //   1343: ifeq -253 -> 1090
    //   1346: bipush 8
    //   1348: istore_2
    //   1349: goto -788 -> 561
    // Local variable table:
    //   start	length	slot	name	signature
    //   0	1352	0	this	ab
    //   355	984	1	i1	int
    //   359	990	2	i2	int
    //   575	537	3	i3	int
    //   548	569	4	i4	int
    //   690	433	5	i5	int
    //   706	423	6	i6	int
    //   634	121	7	i7	int
    //   40	17	8	str1	String
    //   120	1	8	localThrowable1	Throwable
    //   291	116	8	str2	String
    //   421	9	8	localObject	Object
    //   446	37	8	localEOFException	java.io.EOFException
    //   541	341	8	arrayOfInt1	int[]
    //   1000	1	8	localOutOfMemoryError	java.lang.OutOfMemoryError
    //   1061	7	8	arrayOfInt2	int[]
    //   1147	1	8	localThrowable2	Throwable
    //   1160	39	8	str3	String
    // Exception table:
    //   from	to	target	type
    //   0	6	120	java/lang/Throwable
    //   6	61	120	java/lang/Throwable
    //   68	117	120	java/lang/Throwable
    //   129	141	120	java/lang/Throwable
    //   411	418	120	java/lang/Throwable
    //   448	453	120	java/lang/Throwable
    //   1002	1030	120	java/lang/Throwable
    //   1030	1044	120	java/lang/Throwable
    //   1044	1063	120	java/lang/Throwable
    //   1149	1219	120	java/lang/Throwable
    //   1222	1265	120	java/lang/Throwable
    //   1268	1281	120	java/lang/Throwable
    //   1284	1303	120	java/lang/Throwable
    //   1306	1321	120	java/lang/Throwable
    //   1321	1334	120	java/lang/Throwable
    //   0	6	421	finally
    //   6	61	421	finally
    //   68	117	421	finally
    //   129	141	421	finally
    //   141	185	421	finally
    //   185	201	421	finally
    //   201	204	421	finally
    //   204	360	421	finally
    //   370	376	421	finally
    //   376	408	421	finally
    //   411	418	421	finally
    //   432	443	421	finally
    //   448	453	421	finally
    //   456	491	421	finally
    //   491	535	421	finally
    //   537	543	421	finally
    //   550	556	421	finally
    //   561	572	421	finally
    //   623	629	421	finally
    //   636	642	421	finally
    //   646	652	421	finally
    //   656	662	421	finally
    //   666	676	421	finally
    //   681	687	421	finally
    //   692	703	421	finally
    //   756	879	421	finally
    //   887	937	421	finally
    //   937	990	421	finally
    //   990	997	421	finally
    //   1002	1030	421	finally
    //   1030	1044	421	finally
    //   1044	1063	421	finally
    //   1138	1144	421	finally
    //   1149	1219	421	finally
    //   1222	1265	421	finally
    //   1268	1281	421	finally
    //   1284	1303	421	finally
    //   1306	1321	421	finally
    //   1321	1334	421	finally
    //   141	185	446	java/io/EOFException
    //   185	201	446	java/io/EOFException
    //   201	204	446	java/io/EOFException
    //   204	360	446	java/io/EOFException
    //   370	376	446	java/io/EOFException
    //   376	408	446	java/io/EOFException
    //   432	443	446	java/io/EOFException
    //   456	491	446	java/io/EOFException
    //   491	535	446	java/io/EOFException
    //   537	543	446	java/io/EOFException
    //   550	556	446	java/io/EOFException
    //   561	572	446	java/io/EOFException
    //   623	629	446	java/io/EOFException
    //   636	642	446	java/io/EOFException
    //   646	652	446	java/io/EOFException
    //   656	662	446	java/io/EOFException
    //   666	676	446	java/io/EOFException
    //   681	687	446	java/io/EOFException
    //   692	703	446	java/io/EOFException
    //   756	879	446	java/io/EOFException
    //   887	937	446	java/io/EOFException
    //   937	990	446	java/io/EOFException
    //   990	997	446	java/io/EOFException
    //   1138	1144	446	java/io/EOFException
    //   141	185	1000	java/lang/OutOfMemoryError
    //   185	201	1000	java/lang/OutOfMemoryError
    //   201	204	1000	java/lang/OutOfMemoryError
    //   204	360	1000	java/lang/OutOfMemoryError
    //   370	376	1000	java/lang/OutOfMemoryError
    //   376	408	1000	java/lang/OutOfMemoryError
    //   432	443	1000	java/lang/OutOfMemoryError
    //   456	491	1000	java/lang/OutOfMemoryError
    //   491	535	1000	java/lang/OutOfMemoryError
    //   537	543	1000	java/lang/OutOfMemoryError
    //   550	556	1000	java/lang/OutOfMemoryError
    //   561	572	1000	java/lang/OutOfMemoryError
    //   623	629	1000	java/lang/OutOfMemoryError
    //   636	642	1000	java/lang/OutOfMemoryError
    //   646	652	1000	java/lang/OutOfMemoryError
    //   656	662	1000	java/lang/OutOfMemoryError
    //   666	676	1000	java/lang/OutOfMemoryError
    //   681	687	1000	java/lang/OutOfMemoryError
    //   692	703	1000	java/lang/OutOfMemoryError
    //   756	879	1000	java/lang/OutOfMemoryError
    //   887	937	1000	java/lang/OutOfMemoryError
    //   937	990	1000	java/lang/OutOfMemoryError
    //   990	997	1000	java/lang/OutOfMemoryError
    //   1138	1144	1000	java/lang/OutOfMemoryError
    //   141	185	1147	java/lang/Throwable
    //   185	201	1147	java/lang/Throwable
    //   201	204	1147	java/lang/Throwable
    //   204	360	1147	java/lang/Throwable
    //   370	376	1147	java/lang/Throwable
    //   376	408	1147	java/lang/Throwable
    //   432	443	1147	java/lang/Throwable
    //   456	491	1147	java/lang/Throwable
    //   491	535	1147	java/lang/Throwable
    //   537	543	1147	java/lang/Throwable
    //   550	556	1147	java/lang/Throwable
    //   561	572	1147	java/lang/Throwable
    //   623	629	1147	java/lang/Throwable
    //   636	642	1147	java/lang/Throwable
    //   646	652	1147	java/lang/Throwable
    //   656	662	1147	java/lang/Throwable
    //   666	676	1147	java/lang/Throwable
    //   681	687	1147	java/lang/Throwable
    //   692	703	1147	java/lang/Throwable
    //   756	879	1147	java/lang/Throwable
    //   887	937	1147	java/lang/Throwable
    //   937	990	1147	java/lang/Throwable
    //   990	997	1147	java/lang/Throwable
    //   1138	1144	1147	java/lang/Throwable
  }
  
  final boolean s()
  {
    try
    {
      boolean bool = this.J.a();
      return bool;
    }
    finally
    {
      localObject = finally;
      throw localObject;
    }
  }
  
  bi t()
  {
    return this.D;
  }
}


/* Location:           F:\四个案例的jar\欧朋浏览器\classes-dex2jar.jar
 * Qualified Name:     ab
 * JD-Core Version:    0.7.0-SNAPSHOT-20130630
 */