package com.example.lw.appweb;

import java.io.DataInputStream;
import java.util.Hashtable;

final class ao
  implements Runnable
{
  private static Hashtable B = new Hashtable();
  private bc C;
  private String Code;
  private String I;
  private String J;
  private int Z;
  private ak a;
  private int b = 0;
  private int c = -1;
  private int d = 0;
  private boolean e = false;
  private boolean f = false;
  private boolean g;
  private boolean h;
  private boolean i;
  private Thread[] j = new Thread[2];
  
  ao(String paramString1, String paramString2, int paramInt, String paramString3, boolean paramBoolean)
  {
    this.Code = paramString1;
    this.I = paramString2;
    B.put(new Integer(paramInt), this);
    this.Z = paramInt;
    this.J = paramString3;
    if (!paramBoolean)
    {
      paramBoolean = true;
      this.e = paramBoolean;
      if (b.p) {
        break label114;
      }
    }
    label114:
    for (paramBoolean = bool;; paramBoolean = false)
    {
      this.g = paramBoolean;
      return;
      paramBoolean = false;
      break;
    }
  }
  
  private int Code(DataInputStream paramDataInputStream)
  {
    int k = 4;
    byte[] arrayOfByte = new byte[4];
    while ((paramDataInputStream != null) && (!this.i) && (k > 0)) {
      k -= paramDataInputStream.read(arrayOfByte, 4 - k, k);
    }
    return az.J(arrayOfByte, 0);
  }
  
  public static ao Code(int paramInt)
  {
    return (ao)B.get(new Integer(paramInt));
  }
  
  private static boolean I(int paramInt)
  {
    if (paramInt >= 0) {}
    while ((0xFFFF & paramInt) != 0) {
      return false;
    }
    return true;
  }
  
  private void Z(int paramInt)
  {
    try
    {
      g.I.B();
      g.Z.c(this.Z);
      g.Z.c(paramInt);
      g.I.Code(33);
      b.J();
      return;
    }
    catch (Throwable localThrowable) {}
  }
  
  private void c()
  {
    synchronized (this.j)
    {
      this.j[0] = this.j[1];
      this.j[1] = null;
      return;
    }
  }
  
  private void d()
  {
    b.Code(new Runnable()
    {
      public final void run()
      {
        ao.Code(ao.this);
      }
    });
  }
  
  private void e()
  {
    switch (this.b)
    {
    default: 
      return;
    case 1: 
      Z(1);
      return;
    case 2: 
    case 3: 
      Z(3);
      return;
    }
    if (this.d == this.c)
    {
      Z(2);
      return;
    }
    Z(0);
  }
  
  private void f()
  {
    this.d = 0;
    this.b = 3;
    g();
  }
  
  private void g()
  {
    this.h = true;
    this.i = true;
    h();
  }
  
  private void h()
  {
    if (this.C != null)
    {
      b.Code(this.C);
      this.C = null;
    }
    if (this.a != null) {}
    try
    {
      this.a.Z();
      label33:
      this.a = null;
      return;
    }
    catch (Throwable localThrowable)
    {
      break label33;
    }
  }
  
  public final void B()
  {
    this.f = false;
    if ((this.e) && (g.c.Z(this.J))) {
      this.e = false;
    }
  }
  
  public final boolean C()
  {
    return this.e;
  }
  
  public final void Code()
  {
    this.h = false;
    synchronized (this.j)
    {
      if (this.j[0] == null)
      {
        this.j[0] = new Thread(this);
        this.j[0].start();
      }
      while (this.j[1] != null) {
        return;
      }
      this.j[1] = new Thread(this);
      this.j[1].start();
    }
  }
  
  public final void I()
  {
    if (this.g) {
      f();
    }
    for (;;)
    {
      d();
      return;
      this.b = 1;
      g();
    }
  }
  
  public final void J()
  {
    this.d = 0;
    this.b = 2;
    g();
    d();
  }
  
  public final void Z()
  {
    this.b = 4;
    Code();
    d();
  }
  
  public final int a()
  {
    return this.d;
  }
  
  public final boolean b()
  {
    return !this.g;
  }
  
  /* Error */
  public final void run()
  {
    // Byte code:
    //   0: aload_0
    //   1: monitorenter
    //   2: aconst_null
    //   3: astore 13
    //   5: aconst_null
    //   6: astore 11
    //   8: aconst_null
    //   9: astore 9
    //   11: aconst_null
    //   12: astore 12
    //   14: aconst_null
    //   15: astore 8
    //   17: aload_0
    //   18: getfield 131	ao:h	Z
    //   21: istore 7
    //   23: iload 7
    //   25: ifeq +37 -> 62
    //   28: aload_0
    //   29: invokespecial 99	ao:e	()V
    //   32: aconst_null
    //   33: invokestatic 169	b:Code	(Ljava/io/OutputStream;)V
    //   36: aconst_null
    //   37: invokestatic 138	b:Code	(Ljava/io/InputStream;)V
    //   40: aload_0
    //   41: invokespecial 133	ao:h	()V
    //   44: aload_0
    //   45: getfield 50	ao:f	Z
    //   48: ifne +7 -> 55
    //   51: aload_0
    //   52: invokevirtual 170	ao:B	()V
    //   55: aload_0
    //   56: invokespecial 172	ao:c	()V
    //   59: aload_0
    //   60: monitorexit
    //   61: return
    //   62: aload_0
    //   63: iconst_0
    //   64: putfield 80	ao:i	Z
    //   67: aload_0
    //   68: iconst_1
    //   69: putfield 50	ao:f	Z
    //   72: getstatic 147	g:c	Lad;
    //   75: astore 10
    //   77: aload_0
    //   78: getfield 71	ao:J	Ljava/lang/String;
    //   81: astore 14
    //   83: aload_0
    //   84: getfield 48	ao:e	Z
    //   87: ifne +1145 -> 1232
    //   90: iconst_1
    //   91: istore 7
    //   93: aload 10
    //   95: aload 14
    //   97: iload 7
    //   99: iconst_3
    //   100: invokevirtual 175	ad:Code	(Ljava/lang/String;ZI)Lbu;
    //   103: astore 10
    //   105: aload_0
    //   106: aload 10
    //   108: invokeinterface 179 1 0
    //   113: putfield 48	ao:e	Z
    //   116: aload_0
    //   117: aload 10
    //   119: invokeinterface 182 1 0
    //   124: putfield 71	ao:J	Ljava/lang/String;
    //   127: iconst_0
    //   128: istore_1
    //   129: aload_0
    //   130: iconst_0
    //   131: putfield 46	ao:d	I
    //   134: iload_1
    //   135: istore 5
    //   137: aload_0
    //   138: getfield 42	ao:b	I
    //   141: iconst_4
    //   142: if_icmpne +33 -> 175
    //   145: iload_1
    //   146: istore 5
    //   148: aload_0
    //   149: getfield 77	ao:g	Z
    //   152: ifne +23 -> 175
    //   155: aload 10
    //   157: invokeinterface 185 1 0
    //   162: l2i
    //   163: istore 5
    //   165: aload_0
    //   166: iload 5
    //   168: putfield 46	ao:d	I
    //   171: aload_0
    //   172: invokespecial 99	ao:e	()V
    //   175: aload 10
    //   177: iload 5
    //   179: i2l
    //   180: invokeinterface 188 3 0
    //   185: astore 13
    //   187: aload 13
    //   189: astore 11
    //   191: aload 12
    //   193: astore 9
    //   195: aload_0
    //   196: iconst_4
    //   197: putfield 42	ao:b	I
    //   200: aload 12
    //   202: astore 9
    //   204: aload_0
    //   205: invokespecial 99	ao:e	()V
    //   208: iconst_m1
    //   209: istore_2
    //   210: iconst_0
    //   211: istore_1
    //   212: iconst_1
    //   213: istore 4
    //   215: aload 8
    //   217: astore 12
    //   219: aload 8
    //   221: astore 9
    //   223: aload_0
    //   224: getfield 80	ao:i	Z
    //   227: ifne +417 -> 644
    //   230: iconst_0
    //   231: istore_3
    //   232: aload 8
    //   234: astore 12
    //   236: aload 8
    //   238: astore 9
    //   240: aload_0
    //   241: invokespecial 133	ao:h	()V
    //   244: aload 8
    //   246: astore 12
    //   248: aload 8
    //   250: astore 9
    //   252: aload_0
    //   253: getfield 77	ao:g	Z
    //   256: ifeq +127 -> 383
    //   259: aload 8
    //   261: astore 12
    //   263: aload 8
    //   265: astore 9
    //   267: aload_0
    //   268: getstatic 191	g:Code	Le;
    //   271: aload_0
    //   272: getfield 56	ao:Code	Ljava/lang/String;
    //   275: invokestatic 194	b:Code	(Ljava/lang/String;)Ljava/lang/String;
    //   278: aconst_null
    //   279: ldc 196
    //   281: invokeinterface 200 4 0
    //   286: putfield 140	ao:a	Lak;
    //   289: aload 8
    //   291: astore 12
    //   293: aload 8
    //   295: astore 9
    //   297: aload_0
    //   298: getfield 140	ao:a	Lak;
    //   301: invokevirtual 203	ak:I	()Ljava/io/DataInputStream;
    //   304: astore 8
    //   306: aload_0
    //   307: getfield 140	ao:a	Lak;
    //   310: invokevirtual 205	ak:B	()J
    //   313: l2i
    //   314: istore 6
    //   316: aload_0
    //   317: getfield 140	ao:a	Lak;
    //   320: invokevirtual 207	ak:J	()I
    //   323: istore_2
    //   324: iload_2
    //   325: sipush 200
    //   328: if_icmpeq +910 -> 1238
    //   331: iconst_1
    //   332: istore_2
    //   333: iload_2
    //   334: istore_3
    //   335: iload 6
    //   337: istore_2
    //   338: iload_3
    //   339: ifeq +877 -> 1216
    //   342: aload 8
    //   344: astore 12
    //   346: aload 8
    //   348: astore 9
    //   350: aload_0
    //   351: getfield 56	ao:Code	Ljava/lang/String;
    //   354: aload_0
    //   355: getfield 58	ao:I	Ljava/lang/String;
    //   358: invokevirtual 213	java/lang/String:equals	(Ljava/lang/Object;)Z
    //   361: ifne +216 -> 577
    //   364: aload 8
    //   366: astore 12
    //   368: aload 8
    //   370: astore 9
    //   372: aload_0
    //   373: aload_0
    //   374: getfield 58	ao:I	Ljava/lang/String;
    //   377: putfield 56	ao:Code	Ljava/lang/String;
    //   380: goto -165 -> 215
    //   383: aload 8
    //   385: astore 12
    //   387: aload 8
    //   389: astore 9
    //   391: bipush 110
    //   393: anewarray 4	java/lang/Object
    //   396: astore 13
    //   398: aload 8
    //   400: astore 12
    //   402: aload 8
    //   404: astore 9
    //   406: bipush 110
    //   408: newarray int
    //   410: astore 14
    //   412: aload 14
    //   414: bipush 29
    //   416: iconst_2
    //   417: iastore
    //   418: aload 14
    //   420: bipush 37
    //   422: iload 5
    //   424: iastore
    //   425: aload 14
    //   427: bipush 43
    //   429: aload 14
    //   431: bipush 43
    //   433: iaload
    //   434: ldc 214
    //   436: ior
    //   437: iastore
    //   438: aload 8
    //   440: astore 12
    //   442: aload 8
    //   444: astore 9
    //   446: aload 13
    //   448: bipush 53
    //   450: aload_0
    //   451: getfield 56	ao:Code	Ljava/lang/String;
    //   454: aastore
    //   455: aload 8
    //   457: astore 12
    //   459: aload 8
    //   461: astore 9
    //   463: invokestatic 215	b:B	()V
    //   466: aload 8
    //   468: astore 12
    //   470: aload 8
    //   472: astore 9
    //   474: aload_0
    //   475: aload 13
    //   477: aload 14
    //   479: aload_0
    //   480: getfield 58	ao:I	Ljava/lang/String;
    //   483: aconst_null
    //   484: invokestatic 220	ba:Code	(Ljava/lang/String;Ljava/lang/String;)I
    //   487: iconst_1
    //   488: invokestatic 225	ap:Code	([Ljava/lang/Object;[IIZ)Lbc;
    //   491: putfield 135	ao:C	Lbc;
    //   494: aload 8
    //   496: astore 12
    //   498: aload 8
    //   500: astore 9
    //   502: new 82	java/io/DataInputStream
    //   505: dup
    //   506: aload_0
    //   507: getfield 135	ao:C	Lbc;
    //   510: invokespecial 227	java/io/DataInputStream:<init>	(Ljava/io/InputStream;)V
    //   513: astore 8
    //   515: aload_0
    //   516: aload 8
    //   518: invokespecial 229	ao:Code	(Ljava/io/DataInputStream;)I
    //   521: istore_2
    //   522: iload_2
    //   523: ifgt +706 -> 1229
    //   526: iload_2
    //   527: invokestatic 231	ao:I	(I)Z
    //   530: ifeq +38 -> 568
    //   533: ldc 214
    //   535: iload_2
    //   536: iand
    //   537: ifne +706 -> 1243
    //   540: ldc 232
    //   542: iload_2
    //   543: iand
    //   544: ifne +704 -> 1248
    //   547: goto +696 -> 1243
    //   550: aload_0
    //   551: aload 8
    //   553: invokespecial 229	ao:Code	(Ljava/io/DataInputStream;)I
    //   556: istore_2
    //   557: iconst_1
    //   558: istore_1
    //   559: goto -221 -> 338
    //   562: iconst_0
    //   563: istore 4
    //   565: goto -15 -> 550
    //   568: iload_2
    //   569: ifge +660 -> 1229
    //   572: iconst_1
    //   573: istore_3
    //   574: goto -236 -> 338
    //   577: aload 8
    //   579: astore 12
    //   581: aload 8
    //   583: astore 9
    //   585: aload_0
    //   586: invokespecial 160	ao:f	()V
    //   589: aload_0
    //   590: invokespecial 99	ao:e	()V
    //   593: aload 11
    //   595: invokestatic 169	b:Code	(Ljava/io/OutputStream;)V
    //   598: aload 8
    //   600: invokestatic 138	b:Code	(Ljava/io/InputStream;)V
    //   603: aload 10
    //   605: ifnull +10 -> 615
    //   608: aload 10
    //   610: invokeinterface 234 1 0
    //   615: aload_0
    //   616: invokespecial 133	ao:h	()V
    //   619: aload_0
    //   620: getfield 50	ao:f	Z
    //   623: ifne +7 -> 630
    //   626: aload_0
    //   627: invokevirtual 170	ao:B	()V
    //   630: aload_0
    //   631: invokespecial 172	ao:c	()V
    //   634: goto -575 -> 59
    //   637: astore 8
    //   639: aload_0
    //   640: monitorexit
    //   641: aload 8
    //   643: athrow
    //   644: iload_1
    //   645: istore 5
    //   647: iload 4
    //   649: istore_1
    //   650: aload 8
    //   652: astore 9
    //   654: iload 5
    //   656: ifne +23 -> 679
    //   659: aload_0
    //   660: getfield 44	ao:c	I
    //   663: iconst_m1
    //   664: if_icmpeq +162 -> 826
    //   667: iload_2
    //   668: aload_0
    //   669: getfield 44	ao:c	I
    //   672: if_icmpeq +154 -> 826
    //   675: aload_0
    //   676: invokespecial 160	ao:f	()V
    //   679: getstatic 237	b:A	I
    //   682: newarray byte
    //   684: astore 8
    //   686: aload_0
    //   687: invokespecial 99	ao:e	()V
    //   690: aload_0
    //   691: getfield 80	ao:i	Z
    //   694: ifne +79 -> 773
    //   697: iload_2
    //   698: istore_3
    //   699: iload_2
    //   700: ifle +566 -> 1266
    //   703: aload 9
    //   705: aload 8
    //   707: iconst_0
    //   708: iload_2
    //   709: getstatic 237	b:A	I
    //   712: invokestatic 243	java/lang/Math:min	(II)I
    //   715: invokevirtual 86	java/io/DataInputStream:read	([BII)I
    //   718: istore_3
    //   719: aload 11
    //   721: aload 8
    //   723: iconst_0
    //   724: iload_3
    //   725: invokevirtual 249	java/io/OutputStream:write	([BII)V
    //   728: aload_0
    //   729: aload_0
    //   730: getfield 46	ao:d	I
    //   733: iload_3
    //   734: iadd
    //   735: putfield 46	ao:d	I
    //   738: lconst_0
    //   739: iload_3
    //   740: i2l
    //   741: iload_3
    //   742: i2l
    //   743: invokestatic 252	b:Code	(JJJ)V
    //   746: iload 5
    //   748: ifne +514 -> 1262
    //   751: aload_0
    //   752: getfield 46	ao:d	I
    //   755: aload_0
    //   756: getfield 44	ao:c	I
    //   759: if_icmpeq +14 -> 773
    //   762: goto +500 -> 1262
    //   765: aload_0
    //   766: aload_0
    //   767: getfield 46	ao:d	I
    //   770: putfield 44	ao:c	I
    //   773: aload 11
    //   775: invokevirtual 255	java/io/OutputStream:flush	()V
    //   778: aload_0
    //   779: invokespecial 99	ao:e	()V
    //   782: aload 11
    //   784: invokestatic 169	b:Code	(Ljava/io/OutputStream;)V
    //   787: aload 9
    //   789: invokestatic 138	b:Code	(Ljava/io/InputStream;)V
    //   792: aload 10
    //   794: ifnull +10 -> 804
    //   797: aload 10
    //   799: invokeinterface 234 1 0
    //   804: aload_0
    //   805: invokespecial 133	ao:h	()V
    //   808: aload_0
    //   809: getfield 50	ao:f	Z
    //   812: ifne +7 -> 819
    //   815: aload_0
    //   816: invokevirtual 170	ao:B	()V
    //   819: aload_0
    //   820: invokespecial 172	ao:c	()V
    //   823: goto -764 -> 59
    //   826: aload_0
    //   827: iload_2
    //   828: putfield 44	ao:c	I
    //   831: goto -152 -> 679
    //   834: astore 8
    //   836: aload 10
    //   838: astore 8
    //   840: aload 11
    //   842: astore 10
    //   844: aload_0
    //   845: getfield 42	ao:b	I
    //   848: iconst_1
    //   849: if_icmpeq +22 -> 871
    //   852: aload_0
    //   853: getfield 42	ao:b	I
    //   856: iconst_2
    //   857: if_icmpeq +14 -> 871
    //   860: aload_0
    //   861: getfield 80	ao:i	Z
    //   864: ifne +7 -> 871
    //   867: aload_0
    //   868: invokespecial 160	ao:f	()V
    //   871: aload_0
    //   872: aload 8
    //   874: invokeinterface 179 1 0
    //   879: putfield 48	ao:e	Z
    //   882: aload_0
    //   883: invokespecial 99	ao:e	()V
    //   886: aload 10
    //   888: invokestatic 169	b:Code	(Ljava/io/OutputStream;)V
    //   891: aload 9
    //   893: invokestatic 138	b:Code	(Ljava/io/InputStream;)V
    //   896: aload 8
    //   898: ifnull +10 -> 908
    //   901: aload 8
    //   903: invokeinterface 234 1 0
    //   908: aload_0
    //   909: invokespecial 133	ao:h	()V
    //   912: aload_0
    //   913: getfield 50	ao:f	Z
    //   916: ifne +7 -> 923
    //   919: aload_0
    //   920: invokevirtual 170	ao:B	()V
    //   923: aload_0
    //   924: invokespecial 172	ao:c	()V
    //   927: goto -868 -> 59
    //   930: aload_0
    //   931: aload 9
    //   933: invokespecial 229	ao:Code	(Ljava/io/DataInputStream;)I
    //   936: istore_1
    //   937: iload_1
    //   938: invokestatic 231	ao:I	(I)Z
    //   941: ifeq +18 -> 959
    //   944: ldc_w 256
    //   947: iload_1
    //   948: iand
    //   949: ifeq +10 -> 959
    //   952: ldc 214
    //   954: iload_1
    //   955: iand
    //   956: ifeq +60 -> 1016
    //   959: aload_0
    //   960: invokespecial 160	ao:f	()V
    //   963: goto -190 -> 773
    //   966: astore 8
    //   968: aload_0
    //   969: invokespecial 99	ao:e	()V
    //   972: aload 11
    //   974: invokestatic 169	b:Code	(Ljava/io/OutputStream;)V
    //   977: aload 9
    //   979: invokestatic 138	b:Code	(Ljava/io/InputStream;)V
    //   982: aload 10
    //   984: ifnull +10 -> 994
    //   987: aload 10
    //   989: invokeinterface 234 1 0
    //   994: aload_0
    //   995: invokespecial 133	ao:h	()V
    //   998: aload_0
    //   999: getfield 50	ao:f	Z
    //   1002: ifne +7 -> 1009
    //   1005: aload_0
    //   1006: invokevirtual 170	ao:B	()V
    //   1009: aload_0
    //   1010: invokespecial 172	ao:c	()V
    //   1013: aload 8
    //   1015: athrow
    //   1016: iload_1
    //   1017: ldc_w 257
    //   1020: iand
    //   1021: ifeq +18 -> 1039
    //   1024: iconst_1
    //   1025: istore_1
    //   1026: aload_0
    //   1027: aload 9
    //   1029: invokespecial 229	ao:Code	(Ljava/io/DataInputStream;)I
    //   1032: istore_2
    //   1033: invokestatic 260	java/lang/Thread:yield	()V
    //   1036: goto -346 -> 690
    //   1039: iconst_0
    //   1040: istore_1
    //   1041: goto -15 -> 1026
    //   1044: astore 8
    //   1046: aconst_null
    //   1047: astore 9
    //   1049: aconst_null
    //   1050: astore 11
    //   1052: aconst_null
    //   1053: astore 10
    //   1055: goto -87 -> 968
    //   1058: astore 8
    //   1060: aconst_null
    //   1061: astore 9
    //   1063: aconst_null
    //   1064: astore 11
    //   1066: goto -98 -> 968
    //   1069: astore 8
    //   1071: aconst_null
    //   1072: astore 9
    //   1074: goto -106 -> 968
    //   1077: astore 12
    //   1079: aload 8
    //   1081: astore 9
    //   1083: aload 12
    //   1085: astore 8
    //   1087: goto -119 -> 968
    //   1090: astore 12
    //   1092: aload 8
    //   1094: astore 9
    //   1096: aload 12
    //   1098: astore 8
    //   1100: goto -132 -> 968
    //   1103: astore 8
    //   1105: aload 12
    //   1107: astore 9
    //   1109: goto -141 -> 968
    //   1112: astore 11
    //   1114: aload 8
    //   1116: astore 12
    //   1118: aload 11
    //   1120: astore 8
    //   1122: aload 10
    //   1124: astore 11
    //   1126: aload 12
    //   1128: astore 10
    //   1130: goto -162 -> 968
    //   1133: astore 11
    //   1135: goto -253 -> 882
    //   1138: astore 8
    //   1140: aload 11
    //   1142: astore 10
    //   1144: aload 13
    //   1146: astore 8
    //   1148: goto -304 -> 844
    //   1151: astore 8
    //   1153: aload 10
    //   1155: astore 8
    //   1157: aload 11
    //   1159: astore 10
    //   1161: goto -317 -> 844
    //   1164: astore 8
    //   1166: aload 10
    //   1168: astore 8
    //   1170: aload 11
    //   1172: astore 10
    //   1174: goto -330 -> 844
    //   1177: astore 9
    //   1179: aload 8
    //   1181: astore 9
    //   1183: aload 10
    //   1185: astore 8
    //   1187: aload 11
    //   1189: astore 10
    //   1191: goto -347 -> 844
    //   1194: astore 9
    //   1196: aload 8
    //   1198: astore 9
    //   1200: aload 10
    //   1202: astore 8
    //   1204: aload 11
    //   1206: astore 10
    //   1208: goto -364 -> 844
    //   1211: iload_3
    //   1212: istore_2
    //   1213: goto -180 -> 1033
    //   1216: iload_1
    //   1217: istore 5
    //   1219: aload 8
    //   1221: astore 9
    //   1223: iload 4
    //   1225: istore_1
    //   1226: goto -572 -> 654
    //   1229: goto -891 -> 338
    //   1232: iconst_0
    //   1233: istore 7
    //   1235: goto -1142 -> 93
    //   1238: iconst_0
    //   1239: istore_2
    //   1240: goto -907 -> 333
    //   1243: iconst_1
    //   1244: istore_3
    //   1245: goto -907 -> 338
    //   1248: ldc_w 257
    //   1251: iload_2
    //   1252: iand
    //   1253: ifeq -691 -> 562
    //   1256: iconst_1
    //   1257: istore 4
    //   1259: goto -709 -> 550
    //   1262: iload_2
    //   1263: iload_3
    //   1264: isub
    //   1265: istore_3
    //   1266: iload_3
    //   1267: ifne -56 -> 1211
    //   1270: iload_1
    //   1271: ifne -506 -> 765
    //   1274: iload 5
    //   1276: ifne -346 -> 930
    //   1279: goto -514 -> 765
    // Local variable table:
    //   start	length	slot	name	signature
    //   0	1282	0	this	ao
    //   128	1143	1	k	int
    //   209	1056	2	m	int
    //   231	1036	3	n	int
    //   213	1045	4	i1	int
    //   135	1140	5	i2	int
    //   314	22	6	i3	int
    //   21	1213	7	bool	boolean
    //   15	584	8	localDataInputStream	DataInputStream
    //   637	14	8	localObject1	Object
    //   684	38	8	arrayOfByte	byte[]
    //   834	1	8	localThrowable1	Throwable
    //   838	64	8	localObject2	Object
    //   966	48	8	localObject3	Object
    //   1044	1	8	localObject4	Object
    //   1058	1	8	localObject5	Object
    //   1069	11	8	localObject6	Object
    //   1085	14	8	localObject7	Object
    //   1103	12	8	localObject8	Object
    //   1120	1	8	localObject9	Object
    //   1138	1	8	localThrowable2	Throwable
    //   1146	1	8	localObject10	Object
    //   1151	1	8	localThrowable3	Throwable
    //   1155	1	8	localObject11	Object
    //   1164	1	8	localThrowable4	Throwable
    //   1168	52	8	localObject12	Object
    //   9	1099	9	localObject13	Object
    //   1177	1	9	localThrowable5	Throwable
    //   1181	1	9	localObject14	Object
    //   1194	1	9	localThrowable6	Throwable
    //   1198	24	9	localObject15	Object
    //   75	1132	10	localObject16	Object
    //   6	1059	11	localObject17	Object
    //   1112	7	11	localObject18	Object
    //   1124	1	11	localObject19	Object
    //   1133	72	11	localThrowable7	Throwable
    //   12	568	12	localObject20	Object
    //   1077	7	12	localObject21	Object
    //   1090	16	12	localObject22	Object
    //   1116	11	12	localObject23	Object
    //   3	1142	13	localObject24	Object
    //   81	397	14	localObject25	Object
    // Exception table:
    //   from	to	target	type
    //   28	55	637	finally
    //   55	59	637	finally
    //   589	603	637	finally
    //   608	615	637	finally
    //   615	630	637	finally
    //   630	634	637	finally
    //   778	792	637	finally
    //   797	804	637	finally
    //   804	819	637	finally
    //   819	823	637	finally
    //   882	896	637	finally
    //   901	908	637	finally
    //   908	923	637	finally
    //   923	927	637	finally
    //   968	982	637	finally
    //   987	994	637	finally
    //   994	1009	637	finally
    //   1009	1016	637	finally
    //   659	679	834	java/lang/Throwable
    //   679	690	834	java/lang/Throwable
    //   690	697	834	java/lang/Throwable
    //   703	746	834	java/lang/Throwable
    //   751	762	834	java/lang/Throwable
    //   765	773	834	java/lang/Throwable
    //   773	778	834	java/lang/Throwable
    //   826	831	834	java/lang/Throwable
    //   930	944	834	java/lang/Throwable
    //   959	963	834	java/lang/Throwable
    //   1026	1033	834	java/lang/Throwable
    //   1033	1036	834	java/lang/Throwable
    //   659	679	966	finally
    //   679	690	966	finally
    //   690	697	966	finally
    //   703	746	966	finally
    //   751	762	966	finally
    //   765	773	966	finally
    //   773	778	966	finally
    //   826	831	966	finally
    //   930	944	966	finally
    //   959	963	966	finally
    //   1026	1033	966	finally
    //   1033	1036	966	finally
    //   17	23	1044	finally
    //   62	90	1044	finally
    //   93	105	1044	finally
    //   105	127	1058	finally
    //   129	134	1058	finally
    //   137	145	1058	finally
    //   148	175	1058	finally
    //   175	187	1058	finally
    //   195	200	1069	finally
    //   204	208	1069	finally
    //   306	324	1077	finally
    //   515	522	1090	finally
    //   526	533	1090	finally
    //   550	557	1090	finally
    //   223	230	1103	finally
    //   240	244	1103	finally
    //   252	259	1103	finally
    //   267	289	1103	finally
    //   297	306	1103	finally
    //   350	364	1103	finally
    //   372	380	1103	finally
    //   391	398	1103	finally
    //   406	412	1103	finally
    //   446	455	1103	finally
    //   463	466	1103	finally
    //   474	494	1103	finally
    //   502	515	1103	finally
    //   585	589	1103	finally
    //   844	871	1112	finally
    //   871	882	1112	finally
    //   871	882	1133	java/lang/Throwable
    //   17	23	1138	java/lang/Throwable
    //   62	90	1138	java/lang/Throwable
    //   93	105	1138	java/lang/Throwable
    //   105	127	1151	java/lang/Throwable
    //   129	134	1151	java/lang/Throwable
    //   137	145	1151	java/lang/Throwable
    //   148	175	1151	java/lang/Throwable
    //   175	187	1151	java/lang/Throwable
    //   195	200	1164	java/lang/Throwable
    //   204	208	1164	java/lang/Throwable
    //   223	230	1164	java/lang/Throwable
    //   240	244	1164	java/lang/Throwable
    //   252	259	1164	java/lang/Throwable
    //   267	289	1164	java/lang/Throwable
    //   297	306	1164	java/lang/Throwable
    //   350	364	1164	java/lang/Throwable
    //   372	380	1164	java/lang/Throwable
    //   391	398	1164	java/lang/Throwable
    //   406	412	1164	java/lang/Throwable
    //   446	455	1164	java/lang/Throwable
    //   463	466	1164	java/lang/Throwable
    //   474	494	1164	java/lang/Throwable
    //   502	515	1164	java/lang/Throwable
    //   585	589	1164	java/lang/Throwable
    //   306	324	1177	java/lang/Throwable
    //   515	522	1194	java/lang/Throwable
    //   526	533	1194	java/lang/Throwable
    //   550	557	1194	java/lang/Throwable
  }
}


/* Location:           F:\四个案例的jar\欧朋浏览器\classes-dex2jar.jar
 * Qualified Name:     ao
 * JD-Core Version:    0.7.0-SNAPSHOT-20130630
 */