package com.example.lw.appweb;

import java.io.ByteArrayInputStream;
import java.io.ByteArrayOutputStream;
import java.io.DataInputStream;
import java.io.DataOutputStream;
import java.io.IOException;
import java.io.InputStream;
import java.io.OutputStream;
import java.util.Calendar;
import java.util.Hashtable;
import java.util.Iterator;
import java.util.TimeZone;
import java.util.Vector;

public class g
  implements am, Runnable
{
  public static e Code;
  private static r D;
  private static byte[] E;
  private static byte[] F;
  private static String G;
  private static Hashtable H;
  public static g I;
  private static Hashtable K;
  private static int[] L = new int[32];
  private static int[] M = new int[32];
  private static Vector N = new Vector();
  private static ay O;
  private static int P;
  private static int Q;
  private static byte[] R;
  private static byte[] S;
  private static byte[] T;
  private static byte[] U;
  private static boolean V;
  private static boolean W;
  private static int X;
  private static boolean Y;
  public static aw Z;
  private static int aa = 2147483647;
  private static boolean af;
  public static int b = 1;
  public static ad c;
  static byte[] d;
  public static boolean e;
  private static int w = -1;
  private boolean A = true;
  protected ab B;
  public boolean C;
  protected Vector J = new Vector();
  public int a;
  private int ab;
  private int ac;
  private int ad;
  private int ae;
  protected q f;
  private boolean g = true;
  private boolean h;
  private boolean i;
  private int j = -1;
  private int k;
  private long l;
  private boolean m;
  private boolean n;
  private boolean o;
  private final Vector p = new Vector();
  private int q;
  private boolean r;
  private int s;
  private int t;
  private int u;
  private int v;
  private boolean x;
  private boolean y;
  private boolean z;
  
  public g(e parame)
  {
    I = this;
    Code = parame;
  }
  
  private void A()
  {
    try
    {
      this.i = true;
      this.j = 51;
      notifyAll();
      return;
    }
    finally
    {
      localObject = finally;
      throw localObject;
    }
  }
  
  private static String B(String paramString)
  {
    return paramString.substring(paramString.indexOf('-') + 1);
  }
  
  private static String C(String paramString)
  {
    if (H == null)
    {
      H = new Hashtable();
      String str1 = new String(a("/resources")).trim();
      int i2;
      for (int i1 = 0; i1 < str1.length(); i1 = i2 + 1)
      {
        int i4 = str1.indexOf('=', i1);
        int i3 = str1.indexOf('\n', i4 + 1);
        i2 = i3;
        if (i3 < 0) {
          i2 = str1.length();
        }
        String str2 = str1.substring(i1, i4).trim();
        String str3 = str1.substring(i4 + 1, i2).trim();
        H.put(str2, str3);
      }
    }
    return (String)H.get(paramString);
  }
  
  private static int Code(br parambr)
  {
    if (parambr != null)
    {
      if (parambr.Code == 0) {
        parambr.Code = Z.Code(42, 1, parambr);
      }
      return parambr.Code;
    }
    return Z.Code(42, 1, null);
  }
  
  private static int Code(k paramk, int paramInt)
  {
    int i1;
    if (paramk.B())
    {
      i1 = paramk.o();
      if (i1 > paramInt) {}
    }
    int i2;
    do
    {
      return i1;
      paramk.I(false);
      i2 = paramk.o();
      i1 = i2;
    } while (i2 <= paramInt);
    paramk.I(true);
    return paramk.o();
  }
  
  public static int Code(byte[] paramArrayOfByte)
  {
    return paramArrayOfByte.length - 5 - az.I(paramArrayOfByte, paramArrayOfByte.length - 5);
  }
  
  public static e Code()
  {
    return Code;
  }
  
  public static String Code(int paramInt, String paramString)
  {
    return (char)(paramInt + 33) + paramString;
  }
  
  public static String Code(String paramString)
  {
    return (String)H().get(paramString);
  }
  
  public static String Code(byte[] paramArrayOfByte, int paramInt)
  {
    return az.Code(paramArrayOfByte, paramInt);
  }
  
  /* Error */
  private void Code(int paramInt1, int paramInt2, int paramInt3, int paramInt4)
  {
    // Byte code:
    //   0: aload_0
    //   1: monitorenter
    //   2: iload_3
    //   3: ifle +137 -> 140
    //   6: iload 4
    //   8: ifle +132 -> 140
    //   11: iload_1
    //   12: iload_3
    //   13: iadd
    //   14: ifle +126 -> 140
    //   17: iload_2
    //   18: iload 4
    //   20: iadd
    //   21: ifle +119 -> 140
    //   24: iload_1
    //   25: getstatic 119	g:Code	Le;
    //   28: invokeinterface 223 1 0
    //   33: if_icmpge +107 -> 140
    //   36: iload_2
    //   37: getstatic 119	g:Code	Le;
    //   40: invokeinterface 225 1 0
    //   45: if_icmpge +95 -> 140
    //   48: aload_0
    //   49: getfield 227	g:u	I
    //   52: ifle +91 -> 143
    //   55: aload_0
    //   56: getfield 229	g:s	I
    //   59: istore 5
    //   61: aload_0
    //   62: getfield 227	g:u	I
    //   65: istore 6
    //   67: aload_0
    //   68: aload_0
    //   69: getfield 229	g:s	I
    //   72: iload_1
    //   73: invokestatic 234	java/lang/Math:min	(II)I
    //   76: putfield 229	g:s	I
    //   79: aload_0
    //   80: iload_1
    //   81: iload_3
    //   82: iadd
    //   83: iload 5
    //   85: iload 6
    //   87: iadd
    //   88: invokestatic 237	java/lang/Math:max	(II)I
    //   91: aload_0
    //   92: getfield 229	g:s	I
    //   95: isub
    //   96: putfield 227	g:u	I
    //   99: aload_0
    //   100: getfield 239	g:t	I
    //   103: istore_1
    //   104: aload_0
    //   105: getfield 241	g:v	I
    //   108: istore_3
    //   109: aload_0
    //   110: aload_0
    //   111: getfield 239	g:t	I
    //   114: iload_2
    //   115: invokestatic 234	java/lang/Math:min	(II)I
    //   118: putfield 239	g:t	I
    //   121: aload_0
    //   122: iload_2
    //   123: iload 4
    //   125: iadd
    //   126: iload_1
    //   127: iload_3
    //   128: iadd
    //   129: invokestatic 237	java/lang/Math:max	(II)I
    //   132: aload_0
    //   133: getfield 239	g:t	I
    //   136: isub
    //   137: putfield 241	g:v	I
    //   140: aload_0
    //   141: monitorexit
    //   142: return
    //   143: aload_0
    //   144: iload_1
    //   145: putfield 229	g:s	I
    //   148: aload_0
    //   149: iload_2
    //   150: putfield 239	g:t	I
    //   153: aload_0
    //   154: iload_3
    //   155: putfield 227	g:u	I
    //   158: aload_0
    //   159: iload 4
    //   161: putfield 241	g:v	I
    //   164: goto -24 -> 140
    //   167: astore 7
    //   169: aload_0
    //   170: monitorexit
    //   171: aload 7
    //   173: athrow
    // Local variable table:
    //   start	length	slot	name	signature
    //   0	174	0	this	g
    //   0	174	1	paramInt1	int
    //   0	174	2	paramInt2	int
    //   0	174	3	paramInt3	int
    //   0	174	4	paramInt4	int
    //   59	29	5	i1	int
    //   65	23	6	i2	int
    //   167	5	7	localObject	Object
    // Exception table:
    //   from	to	target	type
    //   24	140	167	finally
    //   143	164	167	finally
  }
  
  private void Code(Vector paramVector)
  {
    int[] arrayOfInt = new int[paramVector.size()];
    int i1 = 0;
    int i3;
    for (int i2 = 0; i1 < arrayOfInt.length; i2 = i3)
    {
      br localbr = (br)paramVector.elementAt(i1);
      i3 = i2;
      if (localbr.Code != 0)
      {
        arrayOfInt[i2] = localbr.Code;
        i3 = i2 + 1;
      }
      i1 += 1;
    }
    if (i2 > 0)
    {
      paramVector = new int[i2];
      i1 = 0;
      while (i1 < i2)
      {
        int i6 = arrayOfInt[i1];
        int i4 = i1;
        i3 = 0;
        while (i3 < i4)
        {
          int i5 = (i3 + i4) / 2;
          if (i6 < paramVector[i5]) {
            i4 = i5;
          } else {
            i3 = i5 + 1;
          }
        }
        System.arraycopy(paramVector, i3, paramVector, i3 + 1, i1 - i3);
        paramVector[i3] = i6;
        i1 += 1;
      }
      Z.Code(paramVector);
      Code(67);
      return;
    }
    C();
  }
  
  public static void Code(t paramt)
  {
    N.addElement(paramt);
  }
  
  static void Code(char[] paramArrayOfChar, int paramInt1, int paramInt2)
  {
    Z.m(Z.Code(paramArrayOfChar, paramInt1, paramInt2 - paramInt1));
  }
  
  public static byte[] Code(String paramString, byte[] paramArrayOfByte, int paramInt)
  {
    int i1 = az.Code(paramString) + 2;
    byte[] arrayOfByte = new byte[paramInt + i1 + 5];
    az.Code(paramString, arrayOfByte, paramInt);
    int i2 = paramInt + i1;
    az.I(i1, arrayOfByte, i2);
    i1 = i2 + 2;
    arrayOfByte[i1] = 1;
    az.I(32528, arrayOfByte, i1 + 1);
    System.arraycopy(paramArrayOfByte, 0, arrayOfByte, 0, paramInt);
    return arrayOfByte;
  }
  
  private static String D()
  {
    String str = C("server-url");
    if ((str != null) && (!str.equals(""))) {
      return str;
    }
    return "http://mini5resource.opera-mini.net";
  }
  
  private static String E()
  {
    int i1 = Math.min(Code.C(), Code.a());
    if ((i1 < 210) || (b.k)) {
      return "hqvga";
    }
    if (i1 < 300) {
      return "qvga";
    }
    if (i1 < 440) {
      return "hvga";
    }
    if (i1 < 600) {
      return "vga";
    }
    return "svga";
  }
  
  private static String F()
  {
    if (Code.d()) {
      return "hvga-tablet";
    }
    if (b.Code)
    {
      int i1 = Math.min(Code.C(), Code.a());
      if ((i1 < 210) || (b.k)) {
        return "qvga-touch";
      }
      if ((i1 >= 600) && (Code.c() > 380)) {
        return "svga-touch-xhdpi";
      }
    }
    StringBuilder localStringBuilder = new StringBuilder().append(E()).append("-");
    String str;
    if (Code.d()) {
      str = "tablet";
    }
    for (;;)
    {
      return str;
      if (b.Code) {
        str = "touch";
      } else {
        str = "keypad";
      }
    }
  }
  
  private static String G()
  {
    return C(F());
  }
  
  /* Error */
  private static Hashtable H()
  {
    // Byte code:
    //   0: bipush 10
    //   2: istore_0
    //   3: iconst_0
    //   4: istore_1
    //   5: getstatic 341	g:K	Ljava/util/Hashtable;
    //   8: ifnonnull +164 -> 172
    //   11: new 139	java/util/Hashtable
    //   14: dup
    //   15: invokespecial 140	java/util/Hashtable:<init>	()V
    //   18: putstatic 341	g:K	Ljava/util/Hashtable;
    //   21: new 343	java/io/ByteArrayInputStream
    //   24: dup
    //   25: invokestatic 346	g:d	()[B
    //   28: invokespecial 347	java/io/ByteArrayInputStream:<init>	([B)V
    //   31: astore_3
    //   32: new 349	java/io/DataInputStream
    //   35: dup
    //   36: aload_3
    //   37: invokespecial 352	java/io/DataInputStream:<init>	(Ljava/io/InputStream;)V
    //   40: invokevirtual 355	java/io/DataInputStream:readUTF	()Ljava/lang/String;
    //   43: astore 7
    //   45: aload 7
    //   47: bipush 10
    //   49: invokevirtual 131	java/lang/String:indexOf	(I)I
    //   52: iflt +165 -> 217
    //   55: iload_1
    //   56: aload 7
    //   58: invokevirtual 156	java/lang/String:length	()I
    //   61: if_icmpge +107 -> 168
    //   64: aload 7
    //   66: iload_0
    //   67: iload_1
    //   68: invokevirtual 159	java/lang/String:indexOf	(II)I
    //   71: istore_2
    //   72: iload_2
    //   73: ifge +134 -> 207
    //   76: aload 7
    //   78: invokevirtual 156	java/lang/String:length	()I
    //   81: istore_2
    //   82: aload 7
    //   84: iload_1
    //   85: iload_2
    //   86: invokevirtual 162	java/lang/String:substring	(II)Ljava/lang/String;
    //   89: invokevirtual 152	java/lang/String:trim	()Ljava/lang/String;
    //   92: astore 6
    //   94: aload 6
    //   96: ldc_w 290
    //   99: invokevirtual 294	java/lang/String:equals	(Ljava/lang/Object;)Z
    //   102: ifne +108 -> 210
    //   105: aload 6
    //   107: bipush 61
    //   109: invokevirtual 131	java/lang/String:indexOf	(I)I
    //   112: istore_1
    //   113: iload_1
    //   114: iflt +42 -> 156
    //   117: aload 6
    //   119: iconst_0
    //   120: iload_1
    //   121: invokevirtual 162	java/lang/String:substring	(II)Ljava/lang/String;
    //   124: invokevirtual 152	java/lang/String:trim	()Ljava/lang/String;
    //   127: astore 4
    //   129: aload 6
    //   131: iload_1
    //   132: iconst_1
    //   133: iadd
    //   134: invokevirtual 135	java/lang/String:substring	(I)Ljava/lang/String;
    //   137: invokevirtual 152	java/lang/String:trim	()Ljava/lang/String;
    //   140: astore 5
    //   142: getstatic 341	g:K	Ljava/util/Hashtable;
    //   145: aload 4
    //   147: aload 5
    //   149: invokevirtual 166	java/util/Hashtable:put	(Ljava/lang/Object;Ljava/lang/Object;)Ljava/lang/Object;
    //   152: pop
    //   153: goto +57 -> 210
    //   156: ldc_w 357
    //   159: astore 5
    //   161: aload 6
    //   163: astore 4
    //   165: goto -23 -> 142
    //   168: aload_3
    //   169: invokestatic 359	b:Code	(Ljava/io/InputStream;)V
    //   172: getstatic 341	g:K	Ljava/util/Hashtable;
    //   175: areturn
    //   176: astore_3
    //   177: aconst_null
    //   178: astore_3
    //   179: aload_3
    //   180: invokestatic 359	b:Code	(Ljava/io/InputStream;)V
    //   183: goto -11 -> 172
    //   186: astore 4
    //   188: aconst_null
    //   189: astore_3
    //   190: aload_3
    //   191: invokestatic 359	b:Code	(Ljava/io/InputStream;)V
    //   194: aload 4
    //   196: athrow
    //   197: astore 4
    //   199: goto -9 -> 190
    //   202: astore 4
    //   204: goto -25 -> 179
    //   207: goto -125 -> 82
    //   210: iload_2
    //   211: iconst_1
    //   212: iadd
    //   213: istore_1
    //   214: goto -159 -> 55
    //   217: bipush 38
    //   219: istore_0
    //   220: goto -165 -> 55
    // Local variable table:
    //   start	length	slot	name	signature
    //   2	218	0	i1	int
    //   4	210	1	i2	int
    //   71	142	2	i3	int
    //   31	138	3	localByteArrayInputStream	ByteArrayInputStream
    //   176	1	3	localIOException1	IOException
    //   178	13	3	localInputStream	InputStream
    //   127	37	4	str1	String
    //   186	9	4	localObject1	Object
    //   197	1	4	localObject2	Object
    //   202	1	4	localIOException2	IOException
    //   140	20	5	str2	String
    //   92	70	6	str3	String
    //   43	40	7	str4	String
    // Exception table:
    //   from	to	target	type
    //   21	32	176	java/io/IOException
    //   21	32	186	finally
    //   32	55	197	finally
    //   55	72	197	finally
    //   76	82	197	finally
    //   82	113	197	finally
    //   117	142	197	finally
    //   142	153	197	finally
    //   32	55	202	java/io/IOException
    //   55	72	202	java/io/IOException
    //   76	82	202	java/io/IOException
    //   82	113	202	java/io/IOException
    //   117	142	202	java/io/IOException
    //   142	153	202	java/io/IOException
  }
  
  public static int I(int paramInt)
  {
    for (;;)
    {
      if (paramInt == 0) {
        return 0;
      }
      int i1 = 1;
      while (i1 < L.length)
      {
        if (L[i1] == paramInt)
        {
          arrayOfInt = M;
          arrayOfInt[i1] += 1;
          return i1;
        }
        i1 += 1;
      }
      i1 = 1;
      while (i1 < L.length)
      {
        if (L[i1] == 0)
        {
          arrayOfInt = M;
          arrayOfInt[i1] += 1;
          L[i1] = paramInt;
          return i1;
        }
        i1 += 1;
      }
      int[] arrayOfInt = new int[L.length + 32];
      System.arraycopy(L, 0, arrayOfInt, 0, L.length);
      L = arrayOfInt;
      arrayOfInt = new int[M.length + 32];
      System.arraycopy(M, 0, arrayOfInt, 0, M.length);
      M = arrayOfInt;
    }
  }
  
  public static int I(String paramString)
  {
    return paramString.charAt(0) - '!';
  }
  
  private native void I(ab paramab);
  
  public static void I(t paramt)
  {
    N.removeElement(paramt);
  }
  
  public static boolean I(byte[] paramArrayOfByte)
  {
    return (paramArrayOfByte != null) && (paramArrayOfByte.length >= 3) && (az.I(paramArrayOfByte, paramArrayOfByte.length - 2) == 32528) && (paramArrayOfByte[(paramArrayOfByte.length - 3)] == 1);
  }
  
  public static int J(int paramInt)
  {
    int i1;
    if ((paramInt <= 0) || (paramInt >= L.length)) {
      i1 = 0;
    }
    int i2;
    int i3;
    do
    {
      return i1;
      i2 = L[paramInt];
      int[] arrayOfInt = M;
      i3 = arrayOfInt[paramInt] - 1;
      arrayOfInt[paramInt] = i3;
      i1 = i2;
    } while (i3 != 0);
    L[paramInt] = 0;
    return i2;
  }
  
  private static byte[] K()
  {
    try
    {
      Object localObject1 = j.Code.I("resource");
      Object localObject2;
      int i1;
      Object localObject3;
      return localIOException1;
    }
    catch (IOException localIOException1)
    {
      try
      {
        localObject2 = j.Code.Code("resource", 4);
        if (localObject2 != null)
        {
          i1 = localObject2.length;
          if (i1 != 0) {}
        }
        else
        {
          return localObject1;
        }
        localObject1 = new ByteArrayInputStream((byte[])localObject1);
        localObject3 = new ByteArrayInputStream((byte[])localObject2);
        localObject2 = new aa();
        ((aa)localObject2).Code((InputStream)localObject3);
        localObject3 = new ByteArrayOutputStream();
        bg.Code((InputStream)localObject1, (OutputStream)localObject3, (aa)localObject2);
        localObject1 = ((ByteArrayOutputStream)localObject3).toByteArray();
        return localObject1;
      }
      catch (IOException localIOException2) {}
      localIOException1 = localIOException1;
      return a("/v");
    }
  }
  
  private native void L();
  
  private void M()
  {
    try
    {
      Iterator localIterator = this.J.iterator();
      while (localIterator.hasNext()) {
        ((ab)localIterator.next()).m();
      }
    }
    finally {}
  }
  
  public static int Z(int paramInt)
  {
    if ((paramInt <= 0) || (paramInt >= L.length)) {
      return 0;
    }
    return L[paramInt];
  }
  
  private native void Z(ab paramab);
  
  public static String a(int paramInt)
  {
    return "b_" + paramInt;
  }
  
  /* Error */
  private static byte[] a(String paramString)
  {
    // Byte code:
    //   0: aload_0
    //   1: invokestatic 421	b:J	(Ljava/lang/String;)Ljava/io/InputStream;
    //   4: astore_0
    //   5: new 384	java/io/ByteArrayOutputStream
    //   8: dup
    //   9: invokespecial 385	java/io/ByteArrayOutputStream:<init>	()V
    //   12: astore_2
    //   13: sipush 1024
    //   16: newarray byte
    //   18: astore_3
    //   19: aload_0
    //   20: aload_3
    //   21: invokevirtual 426	java/io/InputStream:read	([B)I
    //   24: istore_1
    //   25: iload_1
    //   26: iflt +20 -> 46
    //   29: aload_2
    //   30: aload_3
    //   31: iconst_0
    //   32: iload_1
    //   33: invokevirtual 430	java/io/ByteArrayOutputStream:write	([BII)V
    //   36: goto -17 -> 19
    //   39: astore_2
    //   40: aload_0
    //   41: invokestatic 359	b:Code	(Ljava/io/InputStream;)V
    //   44: aconst_null
    //   45: areturn
    //   46: aload_0
    //   47: invokestatic 359	b:Code	(Ljava/io/InputStream;)V
    //   50: aload_2
    //   51: invokevirtual 393	java/io/ByteArrayOutputStream:toByteArray	()[B
    //   54: areturn
    //   55: astore_2
    //   56: aload_0
    //   57: invokestatic 359	b:Code	(Ljava/io/InputStream;)V
    //   60: aload_2
    //   61: athrow
    // Local variable table:
    //   start	length	slot	name	signature
    //   0	62	0	paramString	String
    //   24	9	1	i1	int
    //   12	18	2	localByteArrayOutputStream	ByteArrayOutputStream
    //   39	12	2	localException	java.lang.Exception
    //   55	6	2	localObject	Object
    //   18	13	3	arrayOfByte	byte[]
    // Exception table:
    //   from	to	target	type
    //   13	19	39	java/lang/Exception
    //   19	25	39	java/lang/Exception
    //   29	36	39	java/lang/Exception
    //   13	19	55	finally
    //   19	25	55	finally
    //   29	36	55	finally
  }
  
  public static r c()
  {
    if ((D != null) && (D.Z)) {
      return D;
    }
    DataInputStream localDataInputStream = new DataInputStream(new ByteArrayInputStream(d()));
    try
    {
      r localr = new r();
      D = localr;
      localr.Code(localDataInputStream);
      return D;
    }
    catch (IOException localIOException) {}
    return null;
  }
  
  private void d(int paramInt)
  {
    ??? = null;
    boolean bool1 = true;
    int i14 = 1;
    int i15 = 1;
    int i16 = 1;
    int i17 = 1;
    int i18 = 1;
    int i19 = 1;
    int i20 = 1;
    int i10 = 1;
    int i21 = 1;
    int i22 = 1;
    int i23 = 1;
    int i24 = 1;
    int i11 = 1;
    int i7 = 1;
    int i25 = 1;
    int i26 = 1;
    int i27 = 1;
    int i28 = 1;
    int i29 = 1;
    int i30 = 1;
    int i31 = 1;
    boolean bool2 = true;
    int i6 = 1;
    boolean bool3 = false;
    boolean bool4 = false;
    boolean bool5 = false;
    boolean bool6 = false;
    boolean bool7 = false;
    int i32 = 0;
    int i1 = 0;
    int i8 = 0;
    int i2 = 0;
    int i3 = 0;
    int i4 = 0;
    int i9 = 0;
    int i5 = 0;
    int i33 = 0;
    int i12 = 0;
    int i34 = 0;
    int i35 = 0;
    int i36 = 0;
    int i13 = 0;
    k localk;
    Object localObject9;
    label1798:
    Object localObject10;
    switch (paramInt)
    {
    case -315: 
    case -314: 
    case -313: 
    case -312: 
    case -311: 
    case -310: 
    case -309: 
    case -308: 
    case -307: 
    case -306: 
    case -305: 
    case -304: 
    case -303: 
    case -302: 
    case -301: 
    case -281: 
    case -280: 
    case -279: 
    case -278: 
    case -277: 
    case -276: 
    case -275: 
    case -274: 
    case -271: 
    case -269: 
    case -259: 
    case -258: 
    case -257: 
    case -256: 
    case -255: 
    case -254: 
    case -253: 
    case -252: 
    case -251: 
    case -250: 
    case -249: 
    case -248: 
    case -246: 
    case -245: 
    case -244: 
    case -243: 
    case -242: 
    case -241: 
    case -240: 
    case -239: 
    case -238: 
    case -237: 
    case -236: 
    case -235: 
    case -234: 
    case -233: 
    case -232: 
    case -231: 
    case -230: 
    case -229: 
    case -228: 
    case -227: 
    case -226: 
    case -219: 
    case -218: 
    case -215: 
    case -212: 
    case -211: 
    case -210: 
    case -209: 
    case -208: 
    case -207: 
    case -205: 
    case -204: 
    case -203: 
    case -200: 
    case -197: 
    case -196: 
    case -195: 
    case -194: 
    case -193: 
    case -192: 
    case -191: 
    case -190: 
    case -189: 
    case -188: 
    case -187: 
    case -186: 
    case -185: 
    case -184: 
    case -183: 
    case -182: 
    case -181: 
    case -180: 
    case -174: 
    case -164: 
    case -163: 
    case -162: 
    case -161: 
    case -160: 
    case -148: 
    case -147: 
    case -146: 
    case -145: 
    case -144: 
    case -143: 
    case -142: 
    case -141: 
    case -140: 
    case -139: 
    case -138: 
    case -137: 
    case -136: 
    case -135: 
    case -134: 
    case -133: 
    case -132: 
    case -131: 
    case -130: 
    case -126: 
    case -120: 
    case -117: 
    case -97: 
    case -92: 
    case -91: 
    case -90: 
    case -89: 
    case -85: 
    case -84: 
    case -82: 
    case -81: 
    case -80: 
    case -79: 
    case -78: 
    case -77: 
    case -76: 
    case -75: 
    case -74: 
    case -73: 
    case -72: 
    case -71: 
    case -70: 
    case -68: 
    case -67: 
    default: 
      if (Z("vm_error")) {
        throw new RuntimeException("Invalid function: " + paramInt);
      }
    case -206: 
      Z.h();
      i1 = ((ab)Z.v(Z.f())).d();
      paramInt = i1;
      if (i1 >= b.V) {
        paramInt = 0;
      }
      Z.b(Z.Code(43, 1, b.X[paramInt]));
    case -65: 
      return;
    case -198: 
      ((ab)Z.v(Z.f())).b().Z(Z.h(), Z.h(), Z.f());
      return;
    case -199: 
      ((ab)Z.v(Z.f())).b().I(Z.h(), Z.h(), Z.f(), Z.h());
      return;
    case -213: 
      ((ab)Z.v(Z.f())).b().b(Z.f());
      return;
    case -214: 
      ??? = ((ab)Z.v(Z.f())).b().c(Z.h());
      if (??? != null)
      {
        Z.b(Z.Code((String)???));
        return;
      }
      Z.b(0);
      return;
    case -201: 
      ((ab)Z.v(Z.f())).n();
      return;
    case -202: 
      ??? = ((ab)Z.v(Z.f())).b().k(Z.h());
      Z.b(Z.Code(71, 1, ???));
      return;
    case -291: 
      ??? = Z.v(Z.f());
      localk = k.Code(???);
      Z.b(localk.Code(???, Z.h()));
      return;
    case -294: 
      ??? = Z.v(Z.f());
      localk = k.Code(???);
      localObject9 = Z;
      paramInt = i13;
      if (localk.I(???, Z.h())) {
        paramInt = 1;
      }
      ((aw)localObject9).c(paramInt);
      return;
    case -290: 
      ??? = Z.v(Z.f());
      localk = k.Code(???);
      Z.c(localk.I(???));
      return;
    case -292: 
      ??? = Z.v(Z.f());
      k.Code(???).Z(???, Z.h());
      return;
    case -289: 
      ??? = Z.v(Z.f());
      k.Code(???).Z(???);
      return;
    case -293: 
      ??? = Z.v(Z.f());
      localk = k.Code(???);
      localObject9 = (ax)Z.v(Z.f());
      Z.c(localk.Code(???, (ax)localObject9, Z.h()));
      return;
    case -216: 
      i1 = Z.h();
      ??? = Z.f(Z.f());
      if ("cookies".equals(???))
      {
        bool1 = bool3;
        if (i1 == 0) {
          bool1 = true;
        }
        b.H = bool1;
        paramInt = i6;
      }
      for (;;)
      {
        Z.c(paramInt);
        return;
        if ("protocol".equals(???))
        {
          bool1 = bool4;
          if (i1 == 0) {
            bool1 = true;
          }
          ap.Code(bool1);
          paramInt = i6;
        }
        else if ("landscape".equals(???))
        {
          paramInt = i6;
          if (i1 != w)
          {
            w = i1;
            ??? = Code;
            bool1 = bool5;
            if (i1 == 1) {
              bool1 = true;
            }
            ((e)???).Z(bool1);
            this.x = true;
            paramInt = i6;
          }
        }
        else if ("imagequality".equals(???))
        {
          b.t = i1;
          paramInt = i6;
        }
        else if (((b.z) && ("statusbar".equals(???))) || ((!b.z) && ("fullscreen".equals(???))))
        {
          bool1 = bool6;
          if (i1 == 0) {
            bool1 = true;
          }
          Code.I(bool1);
          paramInt = i6;
        }
        else
        {
          if (!"eula_agreed".equals(???)) {
            break;
          }
          bool1 = bool7;
          if (i1 != 0) {
            bool1 = true;
          }
          b.D = bool1;
          paramInt = i6;
          if (bool1)
          {
            if (b.K[3] != null) {
              b.C("md");
            }
            ap.Z();
            for (;;)
            {
              synchronized (this.p)
              {
                if (this.p.size() <= 0) {
                  break;
                }
                localObject9 = (String)this.p.firstElement();
                if ((localObject9 == null) || (((String)localObject9).length() == 0)) {
                  this.p.removeElementAt(0);
                }
              }
              synchronized (this.p)
              {
                if (!b.D) {
                  this.p.addElement(localObject9);
                }
              }
              new Thread()
              {
                public final void run()
                {
                  g.this.B();
                  g.Z.b(g.Z.Code(str4));
                  g.this.Code(5);
                }
              }.start();
            }
            paramInt = i6;
          }
        }
      }
    case -217: 
      paramInt = Z.h();
      i1 = Z.h();
      Z.b(Z.Code(68, 1, ((ab)Z.v(Z.f())).b().J(i1, paramInt, Z.f())));
      return;
    case -267: 
      ((ab)Z.v(Z.f())).b().C(Z.f());
      return;
    case -268: 
      ??? = ((ab)Z.v(Z.f())).b();
      paramInt = Z.f();
      if (Z.h() != 0) {}
      for (;;)
      {
        ((k)???).Code(paramInt, bool1);
        return;
        bool1 = false;
      }
    case -263: 
      Z.b(((ab)Z.v(Z.f())).b().p());
      return;
    case -265: 
      Z.b(((ab)Z.v(Z.f())).b().q());
      return;
    case -266: 
      ((ab)Z.v(Z.f())).b().B(Z.h(), Z.f());
      return;
    case -264: 
      ??? = Z;
      ??? = ((ab)Z.v(Z.f())).b();
      paramInt = Z.h();
      Z.f();
      ((aw)???).b(((k)???).p(paramInt));
      return;
    case -270: 
      Z.b(((ab)Z.v(Z.f())).b().I(Z.f(), Z.f()));
      return;
    case -165: 
      Z.c(((I)Z.v(Z.f())).Code());
      return;
    case -166: 
      Z.c(((I)Z.v(Z.f())).I());
      return;
    case -167: 
      ??? = Z;
      if (((I)Z.v(Z.f())).Z()) {}
      for (paramInt = i14;; paramInt = 0)
      {
        ((aw)???).c(paramInt);
        return;
      }
    case -168: 
      Z.b(Z.Code(((I)Z.v(Z.f())).J()));
      return;
    case -169: 
      ??? = Z;
      Z.v(Z.f());
      ((aw)???).c(0);
      return;
    case -170: 
      ??? = Z;
      if (((I)Z.v(Z.f())).B()) {}
      for (paramInt = i15;; paramInt = 0)
      {
        ((aw)???).c(paramInt);
        return;
      }
    case -171: 
      Z.b(Z.Code(((I)Z.v(Z.f())).C()));
      return;
    case -172: 
      ??? = Z;
      if (((I)Z.v(Z.f())).a()) {}
      for (paramInt = i16;; paramInt = 0)
      {
        ((aw)???).c(paramInt);
        return;
      }
    case -173: 
      ??? = Z;
      if (((I)Z.v(Z.f())).b()) {}
      for (paramInt = i17;; paramInt = 0)
      {
        ((aw)???).c(paramInt);
        return;
      }
    case -175: 
      ??? = Z;
      Z.v(Z.f());
      ((aw)???).c(0);
      return;
    case -176: 
      ??? = Z;
      if (((I)Z.v(Z.f())).c()) {}
      for (paramInt = i18;; paramInt = 0)
      {
        ((aw)???).c(paramInt);
        return;
      }
    case -177: 
      ??? = Z;
      if (((I)Z.v(Z.f())).d()) {}
      for (paramInt = i19;; paramInt = 0)
      {
        ((aw)???).c(paramInt);
        return;
      }
    case -178: 
      ??? = Z;
      if (((I)Z.v(Z.f())).e()) {}
      for (paramInt = i20;; paramInt = 0)
      {
        ((aw)???).c(paramInt);
        return;
      }
    case -179: 
      ((I)Z.v(Z.f())).Code(Z.h());
      return;
    case -220: 
      paramInt = i10;
      switch (((ab)Z.v(Z.f())).b().f())
      {
      default: 
        paramInt = i10;
      }
      for (;;)
      {
        Z.c(paramInt);
        return;
        paramInt = 2;
        continue;
        paramInt = 4;
      }
    case -221: 
      paramInt = i32;
      switch (((ab)Z.v(Z.f())).b().h())
      {
      default: 
        paramInt = 2;
      }
      Z.c(paramInt);
      return;
    case -222: 
      ??? = ((ab)Z.v(Z.f())).b();
      Z.c(((k)???).i());
      return;
    case -223: 
      ??? = ((ab)Z.v(Z.f())).b();
      Z.c(((k)???).j());
      return;
    case -224: 
      ??? = ((ab)Z.v(Z.f())).b();
      Z.c(((k)???).k());
      return;
    case -225: 
      ??? = ((ab)Z.v(Z.f())).b();
      Z.c(((k)???).l());
      return;
    case -295: 
      Z.b(Z.Code(72, 1, new bi()));
      return;
    case -296: 
      ??? = (bi)Z.v(Z.f());
      ((ab)Z.v(Z.f())).Code((bi)???, Z.h());
      return;
    case -297: 
      ??? = (bi)Z.v(Z.f());
      ((ab)Z.v(Z.f())).Code((bi)???);
      return;
    case -69: 
      Z.z(0);
      Code.y();
      return;
    case -64: 
      e();
      throw Z.u();
    case -66: 
      Code.z();
      return;
    case -86: 
      ??? = Z.f(Z.f());
      ??? = Z.f(Z.f());
      Code.Z((String)???, (String)???);
      return;
    case -87: 
      ??? = Z.f(Z.f());
      Code.B((String)???);
      return;
    case -88: 
      Code.W();
      return;
    case -153: 
      paramInt = Z.f();
      i1 = Z.h();
      ??? = Z.f(Z.f());
      i2 = Z.r(paramInt);
      Z.I(paramInt, 0, i2, true);
      ??? = a(i1);
      ??? = Code(i1, (String)???);
      try
      {
        j.Code.Code((String)???, (String)???, Z.Code, i2);
        return;
      }
      catch (Throwable localThrowable1)
      {
        return;
      }
    case -149: 
      paramInt = Z.h();
      String str5 = Z.f(Z.f());
      localObject2 = Z;
      ??? = Z;
      localObject10 = a(paramInt);
      str5 = Code(paramInt, str5);
      ((aw)localObject2).b(((aw)???).Code(61, 1, j.Code.J((String)localObject10, str5)));
      return;
    case -150: 
      paramInt = Z.h();
      ??? = Z.f(Z.f());
      localObject2 = a(paramInt);
      ??? = Code(paramInt, (String)???);
    }
    try
    {
      localObject2 = j.Code.Z((String)localObject2, (String)???);
      paramInt = i1;
      if (localObject2 != null)
      {
        paramInt = Code((byte[])localObject2);
        paramInt = Z.I((byte[])localObject2, 0, paramInt);
      }
      Z.b(paramInt);
      return;
    }
    catch (Throwable localThrowable9)
    {
      for (;;)
      {
        String str1;
        String str2;
        Object localObject3;
        paramInt = i1;
        continue;
        paramInt = 0;
        continue;
        paramInt = 0;
        continue;
        paramInt = 0;
      }
    }
    I(Z.f());
    Z.f(Z.f());
    Z.h();
    Z.c(0);
    return;
    paramInt = Z.h();
    Object localObject2 = Z.f(Z.f());
    Z.b(Z.Code(62, 1, m.Code(paramInt, (String)localObject2)));
    return;
    paramInt = Z.h();
    ??? = Z.f(Z.f());
    localObject2 = a(paramInt);
    ??? = Code(paramInt, (String)???);
    try
    {
      if (j.Code.Code((String)localObject2, (String)???))
      {
        Z.c(1);
        return;
      }
    }
    catch (Throwable localThrowable2)
    {
      Z.c(0);
      return;
    }
    paramInt = Z.h();
    ??? = Z.f(Z.f());
    str1 = a(paramInt);
    ??? = Code(paramInt, (String)???);
    try
    {
      j.Code.I(str1, (String)???);
      return;
    }
    catch (Throwable localThrowable3)
    {
      return;
    }
    paramInt = Z.h();
    str2 = a(paramInt);
    try
    {
      j.Code.I(str2, paramInt);
      return;
    }
    catch (Throwable localThrowable4)
    {
      return;
    }
    Z.b(Z.Code(F));
    F = null;
    return;
    localObject3 = Z;
    if (F != null) {}
    for (paramInt = i21;; paramInt = 0)
    {
      ((aw)localObject3).c(paramInt);
      return;
    }
    F = Z.q(Z.f());
    return;
    localObject3 = Z;
    if (Code.k()) {}
    for (paramInt = i22;; paramInt = 0)
    {
      ((aw)localObject3).c(paramInt);
      return;
    }
    paramInt = Z.f();
    Code.w().Code(Z.f(paramInt));
    return;
    Z.b(Z.Code(Code.w().Code()));
    return;
    localObject3 = Z;
    if (Code.w().I()) {}
    for (paramInt = i23;; paramInt = 0)
    {
      ((aw)localObject3).c(paramInt);
      return;
    }
    if (Code.F())
    {
      Z.c(4);
      return;
    }
    Z.c(1);
    return;
    paramInt = "http://nada:4711".indexOf("://") + 3;
    i1 = "http://nada:4711".indexOf(':', paramInt);
    if ((paramInt >= 3) && (i1 >= 0))
    {
      localObject3 = "http://nada:4711".substring(paramInt, i1);
      ??? = new StringBuffer();
      ((StringBuffer)???).append("http://").append((String)localObject3).append("/hrandom/connected?l=").append(o.Code()).append("&b=").append(Code.V());
      if (b.q == 2) {
        ((StringBuffer)???).append("&showlink");
      }
      Z.b(Z.Code(((StringBuffer)???).toString()));
      localObject3 = ap.a();
      ??? = Z;
      if (localObject3 != null) {
        break label4254;
      }
    }
    label4254:
    for (paramInt = i8;; paramInt = Z.Code((String)localObject3))
    {
      ((aw)???).b(paramInt);
      return;
      Z.b(0);
      break;
    }
    localObject3 = Z;
    if (Code.J(Z.h())) {}
    for (paramInt = i24;; paramInt = 0)
    {
      ((aw)localObject3).c(paramInt);
      return;
    }
    Code.B(Z.h());
    return;
    localObject3 = Code.Z(Z.h());
    i.Code = (Vector)localObject3;
    if (localObject3 == null)
    {
      Z.c(0);
      return;
    }
    Z.c(i.Code.size());
    return;
    Z.Code(Z.f());
    if ((i.Code != null) && (i.Code.size() > 0))
    {
      i.Code.elementAt(0);
      i.Code.removeElementAt(0);
      paramInt = Z.Code(null);
      Z.J(Z.Code(), 0, paramInt);
      paramInt = Z.Code(null);
      Z.J(Z.Code(), 1, paramInt);
      paramInt = Z.Code(null);
      Z.J(Z.Code(), 2, paramInt);
      Z.B(Z.Code(), 3, 0);
      if (i.Code.size() > 0)
      {
        Z.Code(0);
        Z.c(1);
        return;
      }
    }
    i.Code = null;
    Z.Code(0);
    Z.c(0);
    return;
    Code.A();
    return;
    if (Code.D())
    {
      Z.Z(-3, Z.Code(d.Code));
      Z.Z(-2, Z.Code(d.I));
      Z.Z(-4, Z.Code(d.Z));
      Z.c(1);
      return;
    }
    d.I = null;
    d.Code = null;
    d.Z = null;
    Z.c(0);
    return;
    Z.h();
    localObject3 = ((ab)Z.v(Z.f())).b();
    try
    {
      i1 = ((k)localObject3).n();
      paramInt = i2;
      if (i1 != 0)
      {
        Z.I = new int[2];
        Z.I[0] = i1;
        Z.I[1] = 16;
        paramInt = Z.n();
      }
      Z.b(paramInt);
      return;
    }
    catch (Throwable localThrowable8)
    {
      for (;;)
      {
        paramInt = i2;
      }
    }
    paramInt = Z.h();
    localObject3 = Z;
    if (paramInt == 16) {}
    for (paramInt = i11;; paramInt = 0)
    {
      ((aw)localObject3).c(paramInt);
      return;
    }
    paramInt = Z.h();
    i1 = Z.h();
    localObject3 = Z;
    if (k.J(i1, paramInt)) {}
    for (paramInt = i7;; paramInt = 0)
    {
      ((aw)localObject3).c(paramInt);
      return;
    }
    paramInt = Z.h();
    i1 = Z.h();
    if (Code.m())
    {
      localObject3 = c.Code(i1, paramInt);
      label4821:
      if ((localObject3 != null) && (!"".equals(localObject3)))
      {
        ??? = localObject3;
        if (((String)localObject3).startsWith("file://")) {}
      }
      for (??? = "file://" + (String)localObject3;; ??? = "")
      {
        Z.b(Z.Code((String)???));
        return;
      }
      i1 = Z.h();
      i2 = Z.h();
      paramInt = i3;
      if (Code.m())
      {
        localObject3 = c.I(i2, i1);
        paramInt = i3;
        if (localObject3 != null) {
          paramInt = Z.Code((String)localObject3);
        }
      }
      Z.b(paramInt);
      return;
      i1 = Z.h();
      i2 = Z.h();
      paramInt = i4;
      if (Code.m())
      {
        localObject3 = c.Z(i2, i1);
        paramInt = i4;
        if (localObject3 != null) {
          paramInt = Z.Code((String)localObject3);
        }
      }
      Z.b(paramInt);
      return;
      i1 = Z.h();
      i2 = Z.h();
      paramInt = i9;
      if (Code.m()) {
        paramInt = Z.Code(c.J(i2, i1));
      }
      Z.b(paramInt);
      return;
      if (!Code.m()) {}
    }
    for (;;)
    {
      try
      {
        localObject3 = c.J();
        if (localObject3 != null)
        {
          Z.I = new int[localObject3.length];
          i1 = 0;
          paramInt = 0;
          if (i1 < localObject3.length)
          {
            if (localObject3[i1] == 0) {
              break label6952;
            }
            ??? = Z.I;
            i2 = paramInt + 1;
            ???[paramInt] = localObject3[i1];
            paramInt = i2;
            break label6966;
          }
          Z.b(Z.n());
          return;
        }
      }
      catch (Throwable localThrowable5) {}
      Z.b(0);
      return;
      paramInt = Z.f();
      if (paramInt == 0) {}
      for (String str3 = null;; str3 = Z.f(paramInt))
      {
        paramInt = i5;
        if (Code.m()) {}
        try
        {
          str3 = c.a(str3);
          paramInt = i5;
          if (str3 != null) {
            paramInt = Z.Code(str3);
          }
          Z.b(paramInt);
          return;
        }
        catch (Throwable localThrowable7)
        {
          for (;;)
          {
            paramInt = i5;
          }
        }
      }
      Code.m();
      Z.c(0);
      return;
      paramInt = i33;
      if (Code.m()) {
        paramInt = Z.Code(58, 1, c);
      }
      Z.b(paramInt);
      return;
      if (Code.m())
      {
        paramInt = i25;
        Z.c(paramInt);
        return;
        if (Code.J(Z.f(Z.f()).toLowerCase()))
        {
          paramInt = i26;
          Z.c(paramInt);
          return;
          str3 = Z.f(Z.f());
          try
          {
            bool1 = Code.I(str3);
            if (!bool1) {
              break label6937;
            }
            paramInt = i27;
            Z.c(paramInt);
            return;
          }
          catch (IOException localIOException)
          {
            for (;;)
            {
              paramInt = 2;
            }
          }
          Z.c(Code.P());
          return;
          Z.c(Code.Q());
          return;
          if (((ad)Z.v(Z.f())).B(Z.f(Z.f())))
          {
            Z.c(1);
            return;
          }
          Z.c(0);
          return;
          ??? = (ad)Z.v(Z.f());
          ??? = Z.f(Z.f());
          localObject10 = Z;
          if (((ad)???).Z((String)???)) {}
          for (paramInt = i28;; paramInt = 0)
          {
            ((aw)localObject10).c(paramInt);
            return;
          }
          ??? = (ad)Z.v(Z.f());
          ??? = Z.f(Z.f());
          localObject10 = Z;
          if (((ad)???).J((String)???)) {}
          for (paramInt = i29;; paramInt = 0)
          {
            ((aw)localObject10).c(paramInt);
            return;
          }
          try
          {
            Z.v(Z.f());
            ??? = Z.f(Z.f());
            ??? = Z.f(Z.f());
            ??? = new l(c, (String)???, (String)???);
            paramInt = Z.Code(59, 1, ???);
            Z.b(paramInt);
            return;
          }
          catch (Throwable localThrowable6)
          {
            for (;;)
            {
              paramInt = i12;
            }
          }
          ??? = (l)Z.v(Z.f());
          Z.Z(Z.f());
          if (!((l)???).Code())
          {
            Z.c(0);
            Z.Z(0);
            Z.Code(0);
            Z.I(0);
            return;
          }
          if (!((l)???).Code()) {
            label5763:
            if ((((Integer)???[1]).intValue() & 0x4) != 0) {
              break label5943;
            }
          }
          label5943:
          for (paramInt = 0;; paramInt = 1)
          {
            Z.Code(Z.Code((String)???[2]));
            Z.I(Z.Code((String)???[0]));
            Z.B(Z.Z(), 2, paramInt);
            Z.J(Z.Z(), 0, Z.Code());
            Z.J(Z.Z(), 1, Z.I());
            Z.B(Z.Z(), 3, 0);
            Z.B(Z.Z(), 4, 0);
            Z.c(1);
            break;
            ??? = ((l)???).Code;
            paramInt = ((l)???).I;
            ((l)???).I = (paramInt + 1);
            ??? = (Object[])((Vector)???).elementAt(paramInt);
            break label5763;
          }
          paramInt = Z.f();
          if (paramInt == 0) {
            break;
          }
          ((l)Z.v(paramInt)).Code = null;
          return;
          Z.v(Z.f());
          ??? = Z.f(Z.f());
          ??? = Z.f(Z.f());
          Z.c(Code.I((String)???, (String)???));
          return;
          Z.v(Z.f());
          Z.f();
          Z.h();
          Z.f(Z.f());
          Z.f(Z.f());
          Z.b(0);
          return;
          ??? = ((ad)Z.v(Z.f())).Z();
          Z.l(???.length);
          paramInt = i34;
          while (paramInt < ???.length)
          {
            if (???[paramInt] != null) {
              Z.m(Z.Code(57, 1, ???[paramInt]));
            }
            paramInt += 1;
          }
          Z.b(Z.l());
          return;
          Z.v(Z.f());
          Z.b(0);
          return;
          Z.v(Z.f());
          Z.b(Z.Code("/"));
          return;
          ??? = (ad)Z.v(Z.f());
          ??? = Z.f(Z.f());
          Z.b(Z.Code(((ad)???).e((String)???)));
          return;
          ??? = ((ag)Z.v(Z.f())).Code();
          if (??? != null)
          {
            Z.b(Z.Code((String)???));
            return;
          }
          Z.b(0);
          return;
          ??? = ((ag)Z.v(Z.f())).I();
          if (??? != null)
          {
            Z.b(Z.Code((String)???));
            return;
          }
          Z.b(0);
          return;
          ??? = (ag)Z.v(Z.f());
          ??? = Z;
          if (((ag)???).Z()) {}
          for (paramInt = i30;; paramInt = 0)
          {
            ((aw)???).c(paramInt);
            return;
          }
          Z.v(Z.f());
          Z.c(1);
          return;
          ??? = (ag)Z.v(Z.f());
          ??? = Z;
          if (((ag)???).J()) {}
          for (paramInt = i31;; paramInt = 0)
          {
            ((aw)???).c(paramInt);
            return;
          }
          Z.v(Z.f());
          Z.h();
          ??? = c.I();
          if (??? != null)
          {
            Z.b(Z.Code((String)???));
            return;
          }
          Z.b(0);
          return;
          Z.v(Z.f());
          Z.f(Z.f());
          Z.b(0);
          return;
          R = Z.q(Z.f());
          u();
          return;
          ??? = Z.q(Z.f());
          S = (byte[])???;
          if (???.length != 0) {
            break;
          }
          S = null;
          return;
          if (U == null)
          {
            ??? = Z.q(Z.f());
            T = (byte[])???;
            if (???.length == 0) {
              T = null;
            }
          }
          for (;;)
          {
            e = true;
            return;
            paramInt = Z.f();
            i1 = Z.r(paramInt);
            Z.I(paramInt, 0, i1, true);
            T = new byte[U.length + i1];
            System.arraycopy(Z.Code, 0, T, 0, i1);
            System.arraycopy(U, 0, T, i1, U.length);
            T[0] = ((byte)((T.length - 1) / 4));
          }
          if ((!b.O) || (b.S == null))
          {
            Z.b(0);
            return;
          }
          synchronized (b.R)
          {
            Z.Code = new byte[b.S.length / 3];
            paramInt = i35;
            while (paramInt < b.S.length)
            {
              Z.Code[(paramInt / 3 + 0)] = b.S[paramInt];
              paramInt += 3;
            }
            Z.b(Z.p());
            return;
          }
          ??? = Z;
          paramInt = i36;
          if (b.O) {
            paramInt = b.d();
          }
          ((aw)???).b(paramInt);
          return;
          if (!b.O) {
            break;
          }
          if (Z.h() != 0) {}
          for (bool1 = bool2;; bool1 = false)
          {
            b.P = bool1;
            return;
          }
        }
      }
      label6937:
      label6952:
      break label6966;
      Object localObject5 = null;
      break label4821;
      paramInt = 0;
      break label1798;
      label6966:
      i1 += 1;
    }
  }
  
  public static byte[] d()
  {
    if (E != null) {
      return E;
    }
    D = null;
    byte[] arrayOfByte = K();
    E = arrayOfByte;
    return arrayOfByte;
  }
  
  public static boolean g()
  {
    return (V) || (W);
  }
  
  public static boolean n()
  {
    return I.s() - aa > 3000;
  }
  
  static void u()
  {
    int i1 = 0;
    if (R != null) {
      i1 = R[0];
    }
    for (;;)
    {
      ByteArrayOutputStream localByteArrayOutputStream = new ByteArrayOutputStream((i1 + 3) * 5 + 1);
      DataOutputStream localDataOutputStream = new DataOutputStream(localByteArrayOutputStream);
      try
      {
        localDataOutputStream.writeByte(i1 + 3);
        if (R != null) {
          localDataOutputStream.write(R, 1, R.length - 1);
        }
        localDataOutputStream.writeByte(3);
        localDataOutputStream.writeInt(bj.Code);
        localDataOutputStream.writeByte(4);
        localDataOutputStream.writeInt(b.M);
        localDataOutputStream.writeByte(17);
        localDataOutputStream.writeInt(ba.Code);
        label102:
        d = localByteArrayOutputStream.toByteArray();
        return;
      }
      catch (IOException localIOException)
      {
        break label102;
      }
      if (d != null) {
        i1 = d[0] - 3;
      }
    }
  }
  
  private void y()
  {
    if (this.u > 0)
    {
      if ((!this.n) || (this.s < this.ab) || (this.t < this.ac) || (this.s + this.u > this.ab + this.ad) || (this.t + this.v > this.ac + this.ae)) {
        Code.Code(this.s, this.t, this.u, this.v);
      }
      this.u = 0;
    }
  }
  
  private void z()
  {
    try
    {
      if (!this.g) {
        notifyAll();
      }
      return;
    }
    finally
    {
      localObject = finally;
      throw localObject;
    }
  }
  
  public final void B()
  {
    for (;;)
    {
      try
      {
        if (this.g) {
          if (f())
          {
            this.h = false;
            throw new RuntimeException();
          }
        }
      }
      catch (InterruptedException localInterruptedException)
      {
        return;
        this.h = true;
        wait();
        continue;
      }
      finally {}
      this.h = false;
      this.g = true;
      Z.C();
    }
  }
  
  public void B(int paramInt)
  {
    if (!this.C) {
      bj.Code(paramInt);
    }
  }
  
  public final void C()
  {
    try
    {
      this.g = false;
      notifyAll();
      return;
    }
    finally
    {
      localObject = finally;
      throw localObject;
    }
  }
  
  public void C(int paramInt)
  {
    int i1;
    int i2;
    Object localObject1;
    Object localObject7;
    Object localObject10;
    boolean bool1;
    Object localObject9;
    label1788:
    int i3;
    label1798:
    label1815:
    Object localObject2;
    switch (paramInt)
    {
    case -319: 
    case -318: 
    case -317: 
    case -316: 
    case -300: 
    case -299: 
    case -298: 
    case -297: 
    case -296: 
    case -295: 
    case -294: 
    case -293: 
    case -292: 
    case -291: 
    case -290: 
    case -289: 
    case -288: 
    case -287: 
    case -286: 
    case -285: 
    case -284: 
    case -283: 
    case -282: 
    case -279: 
    case -278: 
    case -275: 
    case -274: 
    case -273: 
    case -272: 
    case -270: 
    case -268: 
    case -267: 
    case -266: 
    case -265: 
    case -264: 
    case -263: 
    case -262: 
    case -261: 
    case -260: 
    case -247: 
    case -225: 
    case -224: 
    case -223: 
    case -222: 
    case -221: 
    case -220: 
    case -217: 
    case -216: 
    case -214: 
    case -213: 
    case -212: 
    case -211: 
    case -210: 
    case -209: 
    case -206: 
    case -202: 
    case -201: 
    case -199: 
    case -198: 
    case -191: 
    case -179: 
    case -178: 
    case -177: 
    case -176: 
    case -175: 
    case -174: 
    case -173: 
    case -172: 
    case -171: 
    case -170: 
    case -169: 
    case -168: 
    case -167: 
    case -166: 
    case -165: 
    case -159: 
    case -158: 
    case -157: 
    case -156: 
    case -155: 
    case -154: 
    case -153: 
    case -152: 
    case -151: 
    case -150: 
    case -149: 
    case -129: 
    case -128: 
    case -127: 
    case -126: 
    case -125: 
    case -124: 
    case -123: 
    case -122: 
    case -121: 
    case -120: 
    case -119: 
    case -118: 
    case -117: 
    case -116: 
    case -115: 
    case -114: 
    case -113: 
    case -112: 
    case -111: 
    case -110: 
    case -109: 
    case -108: 
    case -107: 
    case -106: 
    case -105: 
    case -104: 
    case -103: 
    case -102: 
    case -101: 
    case -100: 
    case -99: 
    case -98: 
    case -96: 
    case -95: 
    case -94: 
    case -93: 
    case -88: 
    case -87: 
    case -86: 
    case -83: 
    case -74: 
    case -73: 
    case -72: 
    case -69: 
    case -68: 
    case -67: 
    case -66: 
    case -65: 
    case -64: 
    default: 
      d(paramInt);
    case -320: 
    case -321: 
      do
      {
        do
        {
          do
          {
            return;
          } while (this.C);
          paramInt = Z.h();
          i1 = Z.h();
          i2 = Z.f();
          bj.Code(i1, paramInt);
        } while (i2 == 0);
        bj.Code(Z.f(i2));
        return;
      } while (this.C);
      bj.Code(Z.h());
      return;
    case -323: 
      bj.J();
      Code(0, 0, Code.J(), Code.B());
      return;
    case -322: 
      this.x = true;
      this.r = true;
      return;
    case -324: 
      w();
      return;
    case -325: 
      E = null;
      if (V)
      {
        V = false;
        localObject1 = new ay(D(), G());
        O = (ay)localObject1;
        ((ay)localObject1).start();
        Z.c(X);
        return;
      }
      if (W)
      {
        W = false;
        localObject1 = new ay(D(), G);
        O = (ay)localObject1;
        ((ay)localObject1).start();
        Z.c(X);
        return;
      }
      Z.c(0);
      return;
    case -326: 
      if (P >= 4)
      {
        Z.c(-1);
        return;
      }
      if (O != null)
      {
        paramInt = O.J;
        String str;
        if (paramInt != -1)
        {
          if (paramInt == 0)
          {
            Z.c(0);
            return;
          }
          paramInt = Math.min(O.B * 100 / paramInt, 99);
          localObject7 = O.a;
          if (localObject7 == null)
          {
            Z.c(paramInt);
            return;
          }
          str = F();
          if (G != null)
          {
            localObject1 = G;
            if (!b.Code((byte[])localObject7).equals(localObject1)) {
              break label1788;
            }
          }
        }
        for (;;)
        {
          try
          {
            if (G == null)
            {
              localObject10 = new byte[0];
              j.Code.Code("resource", (byte[])localObject7);
              j.Code.Code("resource", str.getBytes());
              j.Code.Code("resource", ((String)localObject1).getBytes());
              j.Code.Code("resource", (byte[])localObject10);
              j.Code.Code("resource", (byte[])localObject10);
              localObject1 = O.C;
              G = (String)localObject1;
              if (localObject1 != null)
              {
                bool1 = true;
                W = bool1;
                E = null;
                paramInt = 0;
                if (paramInt == 0) {
                  break label1815;
                }
                j.Code.Z("resource");
                paramInt = P + 1;
                P = paramInt;
                if (paramInt >= 4) {
                  break label1798;
                }
                localObject1 = new ay(D(), G());
                O = (ay)localObject1;
                ((ay)localObject1).start();
                Z.c(0);
                return;
                localObject1 = C(str);
                break;
              }
              bool1 = false;
              continue;
            }
            try
            {
              if (new String(j.Code.Code("resource", 5)).equals(G))
              {
                G = null;
                E = null;
                O = null;
                Z.c(0);
                return;
              }
            }
            catch (IOException localIOException2)
            {
              localObject9 = new byte[0];
              j.Code.Code("resource", (byte[])localObject9);
              j.Code.Code("resource", (byte[])localObject9);
              j.Code.Code("resource", 4, (byte[])localObject7);
              j.Code.Code("resource", 5, ((String)localObject1).getBytes());
              E = null;
              paramInt = 0;
            }
            continue;
            paramInt = 1;
          }
          catch (IOException localIOException1)
          {
            Q = -3;
            O = null;
            Z.c(-1);
            return;
          }
          continue;
          paramInt = 1;
        }
        Q = -2;
        O = null;
        Z.c(-1);
        return;
        O = null;
      }
      Z.c(100);
      return;
    case -327: 
      Z.c(Q);
      return;
    case -160: 
      i1 = Z.h();
      i2 = Z.f();
      if (Z.h() != 0)
      {
        bool1 = true;
        paramInt = Z.h();
        i3 = Z.f();
        if (i3 == 0) {
          break label1974;
        }
        localObject2 = Z.f(i3);
        i3 = Z.f();
        localObject7 = Z.f(Z.f());
        if (paramInt != 1) {
          break label1980;
        }
      }
      for (paramInt = 1;; paramInt = 0)
      {
        localObject2 = new av((String)localObject7, i2, i3, (String)localObject2, bool1, i1, paramInt);
        ((t)localObject2).start();
        Z.b(Z.Code(65, 1, localObject2));
        return;
        bool1 = false;
        break;
        localObject2 = null;
        break label1895;
      }
    case -164: 
    case -161: 
      ((t)Z.v(Z.f())).Code();
      return;
    case -276: 
      ap.J();
      return;
    case -162: 
      paramInt = Z.f();
      i1 = Z.f();
      localObject2 = new ai(Z.f(Z.f()), paramInt, i1);
      ((ai)localObject2).start();
      Z.b(Z.Code(66, 1, localObject2));
      return;
    case -163: 
      ((ai)Z.v(Z.f())).Z();
      return;
    case -47: 
      Code(Z.h(), Z.h(), Z.h(), Z.h());
      return;
    case -48: 
      this.q = Z.f();
      return;
    case -49: 
      Z.b(Code(Code.q().Code(Z.h(), Z.h())));
      return;
    case -50: 
      label1895:
      Z.Z(Z.f());
      label1974:
      label1980:
      i1 = Z.h();
      i2 = Z.h();
      if (Z.h() != 0)
      {
        bool1 = true;
        label2199:
        paramInt = 0;
        if (paramInt > b) {
          break label10081;
        }
      }
      break;
    }
    label2323:
    label5282:
    label7757:
    label7889:
    label8789:
    for (;;)
    {
      try
      {
        Z.I(Z.Z(), i1, i2, true);
        localObject2 = Code.q().Code(Z.Code, 0, i2, 256, null, bool1);
        Z.Z(0);
        localObject7 = Z;
        if (localObject2 == null) {
          break label2323;
        }
        paramInt = Code((br)localObject2);
        ((aw)localObject7).b(paramInt);
        return;
      }
      catch (Throwable localThrowable1)
      {
        if (paramInt == b) {
          break label10081;
        }
      }
      bool1 = false;
      break label2199;
      if (paramInt > 0) {}
      for (boolean bool2 = true;; bool2 = false)
      {
        Code(bool2);
        paramInt += 1;
        break;
      }
      paramInt = 0;
      continue;
      Z.c(((br)Z.v(Z.f())).Code());
      return;
      Z.c(((br)Z.v(Z.f())).I());
      return;
      Z.c(((br)Z.v(Z.f())).Z());
      return;
      if (Z.h() != 0) {}
      int i4;
      int i5;
      int i6;
      int i7;
      int i8;
      int i9;
      int i10;
      for (bool1 = true;; bool1 = false)
      {
        paramInt = Z.h();
        i1 = Z.h();
        i2 = Z.h();
        i3 = Z.h();
        i4 = Z.h();
        i5 = Z.h();
        i6 = Z.h();
        i7 = Z.h();
        i8 = Z.h();
        i9 = Z.h();
        i10 = Z.h();
        Z.b(Code(((br)Z.v(Z.f())).Code(i10, i9, i8, i7, i6, i5, i4, i3, i2, i1, paramInt, bool1)));
        return;
      }
      paramInt = Z.h();
      i1 = Z.h();
      i2 = Z.h();
      Z.b(Z.Code(43, 1, Code.s().Code(paramInt, i1, i2)));
      return;
      Code.s();
      Z.h();
      Z.h();
      Z.h();
      Z.h();
      return;
      Z.c(((ax)Z.v(Z.f())).c());
      return;
      Z.c(((ax)Z.v(Z.f())).Code(Z.f(Z.f())));
      return;
      Z.c(((ax)Z.v(Z.f())).Code(Z.Code(Z.f(), Z.h(), Z.h())));
      return;
      localObject7 = (ax)Z.v(Z.f());
      paramInt = 0;
      Object localObject3 = "";
      i1 = Z.f();
      if (i1 != 0)
      {
        localObject3 = Z.f(i1);
        paramInt = ((ax)localObject7).Code((String)localObject3);
      }
      i1 = Z.f();
      localObject9 = Z.g(i1);
      if (Z.h() == 0) {}
      for (bool1 = true;; bool1 = false)
      {
        paramInt = b.Code((char[])localObject9, bool1, Z.h(), paramInt, (ax)localObject7);
        if ((!bool1) || (paramInt >= localObject9.length)) {
          break;
        }
        Z.b(Z.Code(new String((char[])localObject9, 0, paramInt) + (String)localObject3));
        return;
      }
      if ((!bool1) && (paramInt > 0))
      {
        Z.b(Z.Code((String)localObject3 + new String((char[])localObject9, paramInt, localObject9.length - paramInt)));
        return;
      }
      Z.b(i1);
      return;
      localObject3 = (ax)Z.v(Z.f());
      Z.f();
      paramInt = Z.h();
      Z.h();
      i1 = Z.h();
      localObject7 = Z.g(Z.f());
      Z.l(0);
      x.Code((char[])localObject7, i1, paramInt, 0, (ax)localObject3, null);
      Z.b(Z.l());
      return;
      Z.Z(Z.f());
      localObject7 = (ax)Z.v(Z.Z());
      localObject3 = null;
      paramInt = Z.f();
      if (paramInt != 0) {
        localObject3 = Z.f(paramInt);
      }
      paramInt = Z.h();
      i1 = Z.h();
      i2 = Z.h();
      localObject9 = new B(Z.g(Z.f()), i2, i1, paramInt, (String)localObject3, (ax)localObject7);
      Z.l(0);
      paramInt = 0;
      if (paramInt < ((B)localObject9).Code())
      {
        Z.J(Z.I(9, 44));
        if (((B)localObject9).c(paramInt)) {
          Z.B(Z.J(), 4, ((ax)localObject7).Code((String)localObject3));
        }
        for (i1 = Z.Code((String)localObject3);; i1 = Z.Code(((B)localObject9).I(), ((B)localObject9).Z(paramInt), ((B)localObject9).J(paramInt)))
        {
          Z.J(Z.J(), 0, i1);
          Z.B(Z.J(), 2, ((B)localObject9).a(paramInt));
          Z.J(Z.J(), 1, Z.Z());
          Z.B(Z.J(), 3, ((B)localObject9).I(paramInt));
          Z.B(Z.J(), 5, ((ax)localObject7).c());
          Z.B(Z.J(), 6, ((B)localObject9).B(paramInt));
          Z.B(Z.J(), 8, ((B)localObject9).C(paramInt));
          Z.m(Z.J());
          paramInt += 1;
          break;
          Z.B(Z.J(), 4, ((B)localObject9).b(paramInt));
        }
      }
      i1 = Z.I(2, 45);
      Z.J(i1, 0, Z.l());
      localObject3 = Z;
      if (((B)localObject9).Z()) {}
      for (paramInt = 1;; paramInt = 0)
      {
        ((aw)localObject3).B(i1, 1, paramInt);
        Z.b(i1);
        Z.Z(0);
        Z.J(0);
        return;
      }
      b.Z(Z.h() | 0x8000);
      Z.b(Z.p());
      return;
      localObject3 = (m)Z.v(Z.f());
      i1 = Z.f();
      i2 = Z.h();
      i3 = Z.h();
      paramInt = 0;
      try
      {
        Z.I(i1, i3, i2, true);
        ((m)localObject3).write(Z.Code, 0, i2);
        return;
      }
      catch (Throwable localThrowable5)
      {
        if (paramInt == b) {
          throw localThrowable5;
        }
        Z.B(i1);
        if (paramInt > 0) {}
        for (bool1 = true;; bool1 = false)
        {
          Code(bool1);
          i1 = Z.B();
          Z.B(0);
          paramInt += 1;
          break;
        }
      }
      b.Code((m)Z.v(Z.f()));
      return;
      ((m)Z.v(Z.f())).Code(Z.h());
      return;
      ((m)Z.v(Z.f())).I(Z.h());
      return;
      ((m)Z.v(Z.f())).Z(Z.h());
      return;
      ((m)Z.v(Z.f())).Code(Z.h(Z.f()));
      return;
      localObject3 = (m)Z.v(Z.f());
      paramInt = Z.f();
      Z.j(paramInt);
      paramInt = Z.k(paramInt);
      ((m)localObject3).I(paramInt);
      ((m)localObject3).write(Z.Code, 0, paramInt);
      return;
      i1 = Z.h();
      if (Z.h() != 0) {}
      for (bool1 = true;; bool1 = false)
      {
        paramInt = 0;
        try
        {
          localObject3 = b.Code(i1 | 0x8000, bool1);
          Z.b(Code((br)localObject3));
          return;
        }
        catch (Throwable localThrowable2)
        {
          if (paramInt != b) {
            break;
          }
          throw Z.e(22);
          if (paramInt <= 0) {
            break label3953;
          }
          for (bool2 = true;; bool2 = false)
          {
            Code(bool2);
            paramInt += 1;
            break;
          }
        }
      }
      label3953:
      Object localObject4 = (bd)Z.v(Z.f());
      paramInt = Z.f();
      i1 = Z.h();
      Z.I(paramInt, Z.h(), i1, false);
      Z.c(((bd)localObject4).read(Z.Code, 0, i1));
      Z.p(Z.g());
      return;
      Z.c(((bd)Z.v(Z.f())).I(Z.h()));
      return;
      b.Code((bd)Z.v(Z.f()));
      return;
      Z.c(((bd)Z.v(Z.f())).Code());
      return;
      Z.c(((bd)Z.v(Z.f())).I());
      return;
      Z.c(((bd)Z.v(Z.f())).Z());
      return;
      Z.b(Z.Code(((bd)Z.v(Z.f())).J()));
      return;
      localObject4 = (bd)Z.v(Z.f());
      paramInt = ((bd)localObject4).I();
      if (paramInt < 0)
      {
        Z.b(0);
        return;
      }
      if (paramInt == 0)
      {
        Z.b(Z.i());
        return;
      }
      Z.i(paramInt);
      ((bd)localObject4).read(Z.Code, 0, paramInt);
      if (!az.I(Z.Code, 0, paramInt)) {
        throw Z.e(25);
      }
      Z.b(Z.j());
      return;
      Z.b(Z.Code(61, 1, bd.Code(Z.h())));
      return;
      localObject4 = Z.f(Z.f());
      for (;;)
      {
        try
        {
          localObject8 = c;
          if (!c.B((String)localObject4))
          {
            bool1 = true;
            localObject4 = ((ad)localObject8).Code((String)localObject4, bool1, 3);
            if (!((bu)localObject4).B()) {
              break;
            }
            localObject4 = m.Code(((bu)localObject4).Code(0L));
            Z.b(Z.Code(62, 1, localObject4));
            return;
          }
        }
        catch (Throwable localThrowable3)
        {
          Z.b(0);
          return;
        }
        bool1 = false;
      }
      Z.b(0);
      return;
      for (Object localObject5 = Z.f(Z.f());; localObject6 = null) {
        try
        {
          if (c.B((String)localObject5))
          {
            localObject5 = c.Code((String)localObject5, false, 3);
            if (localObject5 == null) {
              break;
            }
            localObject5 = bd.Code(((bu)localObject5).Code(), (int)((bu)localObject5).Z());
            Z.b(Z.Code(61, 1, localObject5));
            return;
          }
        }
        catch (Throwable localThrowable4)
        {
          Z.b(0);
          return;
        }
      }
      Z.b(0);
      return;
      paramInt = Z.f();
      i2 = Z.n(paramInt);
      Object localObject6 = new String[i2];
      Z.Code(paramInt, i2);
      paramInt = 0;
      while (paramInt < i2)
      {
        localObject6[paramInt] = Z.f(Z.I[(paramInt + 0)]);
        paramInt += 1;
      }
      paramInt = Z.f();
      Object localObject8 = new String[i2];
      Z.Code(paramInt, i2);
      paramInt = 0;
      while (paramInt < i2)
      {
        localObject8[paramInt] = Z.f(Z.I[(paramInt + 0)]);
        paramInt += 1;
      }
      localObject9 = Z.f(Z.f());
      localObject10 = new StringBuffer(((String)localObject9).length());
      paramInt = 0;
      label4696:
      if (paramInt < ((String)localObject9).length())
      {
        i1 = 0;
        label4707:
        if (i1 >= i2) {
          break label10076;
        }
        if (((String)localObject9).startsWith(localObject8[i1], paramInt))
        {
          ((StringBuffer)localObject10).append(localObject6[i1]);
          paramInt = localObject8[i1].length() + paramInt;
        }
      }
      label7769:
      label8795:
      label10076:
      for (i1 = 1;; i1 = 0)
      {
        if (i1 == 0)
        {
          i1 = paramInt + 1;
          ((StringBuffer)localObject10).append(((String)localObject9).charAt(paramInt));
          paramInt = i1;
          break label4696;
          i1 += 1;
          break label4707;
          Z.b(Z.Code(((StringBuffer)localObject10).toString()));
          return;
          paramInt = Z.f();
          i1 = Z.h();
          Z.I(paramInt, Z.h(), i1, true);
          Z.b(Z.Code(af.Code(Z.Code, i1)));
          return;
          Z.b(Z.Code(af.Code(Z.f(Z.f()))));
          return;
          paramInt = Z.f();
          i1 = Z.h();
          i2 = Z.h();
          i3 = Z.f();
          i4 = Z.h();
          i5 = Z.h();
          Z.I(i3, i5, i4, true);
          localObject6 = new bq(Z.Code, 0, i4);
          Z.I(paramInt, i2, i1, true);
          ((bq)localObject6).Code(Z.Code, 0, i1);
          localObject8 = new byte[32];
          ((bq)localObject6).I((byte[])localObject8, 0, localObject8.length);
          Z.b(Z.Code((byte[])localObject8));
          return;
          this.k = Z.h();
          this.m = true;
          return;
          Z.b(Z.Code(System.currentTimeMillis()));
          return;
          Z.c(s());
          return;
          localObject6 = TimeZone.getDefault();
          localObject8 = Calendar.getInstance((TimeZone)localObject6);
          Z.b(Z.Code(((TimeZone)localObject6).getOffset(1, ((Calendar)localObject8).get(1), ((Calendar)localObject8).get(2), ((Calendar)localObject8).get(5), ((Calendar)localObject8).get(7), 0)));
          return;
          Z.b(Z.Code(o.Code()));
          return;
          o.Code(Z.f(Z.f()));
          Z.c(1);
          return;
          o.I(Z.f(Z.f()));
          Z.c(1);
          return;
          Z.b(Z.Code(o.I()));
          return;
          paramInt = Z.f();
          i1 = Z.f();
          Code.J(Z.f(i1), Z.f(paramInt));
          return;
          int i11;
          int i12;
          int i13;
          int i14;
          e locale;
          if (Z.h() != 0)
          {
            paramInt = 1;
            i2 = Z.h();
            i3 = Z.h();
            i4 = Z.h();
            i1 = Z.f();
            if (i1 == 0) {
              break label5524;
            }
            localObject6 = Z.v(i1);
            localObject6 = (ax)localObject6;
            i5 = Z.h();
            i6 = Z.h();
            i7 = Z.h();
            i8 = Z.h();
            i9 = Z.h();
            i10 = Z.h();
            i1 = Z.h();
            i11 = Z.h();
            i12 = Z.h();
            i13 = Z.f();
            localObject8 = Z.f(Z.f());
            localObject9 = Z.f(Z.f());
            i14 = Z.h();
            localObject10 = Z.f(Z.f());
            localObject11 = Z.f(Z.f());
            locale = Code;
            if (paramInt == 0) {
              break label5530;
            }
          }
          for (paramInt = -1000;; paramInt = i1)
          {
            localObject6 = locale.Code(i12, i13, (String)localObject8, (String)localObject9, i14, (String)localObject10, (String)localObject11, i11, paramInt, i10, i9, i8, i7, i6, i5, (ax)localObject6, i4, i3, i2);
            paramInt = Z.Code(73, 1, localObject6);
            this.a = I(paramInt);
            Z.b(paramInt);
            return;
            paramInt = 0;
            break;
            localObject6 = null;
            break label5282;
          }
          if (Z.h() != 0) {}
          for (bool1 = true;; bool1 = false)
          {
            Code.J(bool1);
            return;
          }
          localObject6 = Z;
          if (Code.L()) {}
          for (paramInt = 1;; paramInt = 0)
          {
            ((aw)localObject6).c(paramInt);
            return;
          }
          localObject6 = Z;
          if (Code.Code(Z.h())) {}
          for (paramInt = 1;; paramInt = 0)
          {
            ((aw)localObject6).c(paramInt);
            return;
          }
          if (Code.g())
          {
            Z.c(1);
            return;
          }
          if (Code.h() != 0)
          {
            Z.c(-1);
            return;
          }
          Z.c(0);
          return;
          Z.c(b.w);
          return;
          localObject6 = Z.v(Z.f());
          if (Z.h() != 0) {}
          for (bool1 = true;; bool1 = false)
          {
            paramInt = Z.h();
            localObject8 = Z.f(Z.f());
            Code.Code(localObject6, (String)localObject8, paramInt, bool1);
            return;
          }
          localObject6 = Code.I(Z.v(Z.f()));
          if (localObject6 != null)
          {
            Z.b(Z.Code((String)localObject6));
            return;
          }
          Z.b(0);
          return;
          Z.c(-1);
          return;
          Code.Code(Z.v(Z.f()), Z.f(Z.f()));
          return;
          localObject6 = Z.v(Z.f());
          Code.Code(localObject6);
          return;
          localObject6 = Z.v(Z.f());
          if (Z.h() != 0)
          {
            paramInt = 1;
            i2 = Z.h();
            i3 = Z.h();
            i4 = Z.h();
            i5 = Z.h();
            i1 = Z.h();
            i6 = Z.h();
            localObject8 = Code;
            if (paramInt == 0) {
              break label5982;
            }
          }
          label5982:
          for (paramInt = -1000;; paramInt = i1)
          {
            ((e)localObject8).Code(localObject6, i6, paramInt, i5, i4, i3, i2);
            return;
            paramInt = 0;
            break;
          }
          Code.I(Z.h());
          return;
          Code.i();
          return;
          Z.c(Code.j());
          return;
          Z.c(0);
          return;
          Z.c(0);
          return;
          Z.c(b.Y);
          return;
          Z.c(Code.s().I(Z.h()));
          return;
          Code(false);
          return;
          Z.b(Z.Code(Runtime.getRuntime().freeMemory()));
          return;
          ((ab)Z.v(Z.f())).e();
          return;
          this.B = ((ab)Z.v(Z.f()));
          if (b.c > 0) {
            t();
          }
          Code(this.B);
          return;
          ((ab)Z.v(Z.f())).b().Code(Z.h(), Z.h(), Z.h(), Z.h());
          return;
          Z.c(((ab)Z.v(Z.f())).b().Code(Z.f(), Z.f()));
          return;
          localObject6 = Z;
          localObject8 = ((ab)Z.v(Z.f())).b();
          Z.f();
          ((aw)localObject6).b(((k)localObject8).Code(Z.h(), Z.h(), Z.h(), Z.h(), Z.f()));
          return;
          localObject6 = Z;
          if (((ab)Z.v(Z.f())).b().Z()) {}
          for (paramInt = 1;; paramInt = 0)
          {
            ((aw)localObject6).c(paramInt);
            return;
          }
          ((ab)Z.v(Z.f())).b().m();
          return;
          localObject6 = ((ab)Z.v(Z.f())).b();
          Z.Z(Z.f());
          paramInt = Z.f();
          i1 = Z.f();
          localObject8 = Z.f(paramInt);
          localObject9 = new int[4];
          tmp6446_6444 = localObject9;
          tmp6446_6444[0] = 0;
          tmp6450_6446 = tmp6446_6444;
          tmp6450_6446[1] = 0;
          tmp6454_6450 = tmp6450_6446;
          tmp6454_6450[2] = 0;
          tmp6458_6454 = tmp6454_6450;
          tmp6458_6454[3] = 0;
          tmp6458_6454;
          Z.h();
          paramInt = ((k)localObject6).Code((String)localObject8, (int[])localObject9, i1);
          Z.B(Z.Z(), 0, localObject9[0]);
          Z.B(Z.Z(), 1, localObject9[1]);
          Z.B(Z.Z(), 2, localObject9[2]);
          Z.B(Z.Z(), 3, localObject9[3]);
          Z.c(paramInt);
          Z.Z(0);
          return;
          localObject6 = ((ab)Z.v(Z.f())).b().g();
          if (localObject6 == null)
          {
            Z.b(0);
            return;
          }
          Z.Z(Z.I(4, 56));
          Z.B(Z.Z(), 0, localObject6[0]);
          Z.B(Z.Z(), 1, localObject6[1]);
          Z.B(Z.Z(), 2, localObject6[2]);
          Z.B(Z.Z(), 3, localObject6[3]);
          Z.b(Z.Z());
          Z.Z(0);
          return;
          bool1 = b.C();
          if (bool1) {
            b.Code(new Runnable()
            {
              public final void run() {}
            });
          }
          localObject6 = Z;
          if (bool1) {}
          for (paramInt = 0;; paramInt = 1)
          {
            ((aw)localObject6).c(paramInt);
            return;
          }
          localObject6 = Z.f(Z.f());
          paramInt = 0;
          if ((ap.Code == -2) || (ba.Code(ba.Code((String)localObject6, null)).I())) {
            paramInt = 2;
          }
          for (;;)
          {
            Z.c(paramInt);
            return;
            if (ap.Code == 0) {
              paramInt = 1;
            }
          }
          if (Z.h() != 0) {}
          for (bool1 = true;; bool1 = false)
          {
            localObject6 = Z.f(Z.f());
            paramInt = Z.h();
            localObject8 = Z.f(Z.f());
            new ao(Z.f(Z.f()), (String)localObject8, paramInt, (String)localObject6, bool1);
            return;
          }
          Z.c(b.f());
          return;
          localObject6 = ao.Code(Z.h());
          if (localObject6 != null)
          {
            localObject8 = Z;
            if (((ao)localObject6).C()) {}
            for (paramInt = 1;; paramInt = 0)
            {
              ((aw)localObject8).c(paramInt);
              return;
            }
          }
          Z.c(0);
          return;
          localObject6 = ao.Code(Z.h());
          if (localObject6 == null) {
            break;
          }
          ((ao)localObject6).Code();
          return;
          localObject6 = ao.Code(Z.h());
          if (localObject6 == null) {
            break;
          }
          ((ao)localObject6).I();
          return;
          localObject6 = ao.Code(Z.h());
          if (localObject6 == null) {
            break;
          }
          ((ao)localObject6).Z();
          return;
          localObject6 = ao.Code(Z.h());
          if (localObject6 == null) {
            break;
          }
          ((ao)localObject6).J();
          return;
          localObject6 = ao.Code(Z.h());
          if (localObject6 == null) {
            break;
          }
          ((ao)localObject6).B();
          return;
          localObject6 = ao.Code(Z.h());
          localObject8 = Z;
          if ((localObject6 != null) && (((ao)localObject6).b())) {}
          for (paramInt = 1;; paramInt = 0)
          {
            ((aw)localObject8).c(paramInt);
            return;
          }
          localObject6 = ao.Code(Z.h());
          localObject8 = Z;
          if (localObject6 == null) {}
          for (paramInt = 0;; paramInt = ((ao)localObject6).a())
          {
            ((aw)localObject8).c(paramInt);
            return;
          }
          localObject6 = ((ab)Z.v(Z.f())).b();
          localObject8 = Z.f(Z.f());
          ((k)localObject6).Code(Z.f(Z.f()), (String)localObject8);
          return;
          paramInt = Z.h();
          i1 = Z.h();
          if (Z.h() != 0) {}
          for (bool1 = true;; bool1 = false)
          {
            ((ab)Z.v(Z.f())).Code(bool1, i1, paramInt, Z.f());
            return;
          }
          paramInt = Z.h();
          i1 = Z.h();
          ((ab)Z.v(Z.f())).Code(i1, paramInt, Z.f());
          return;
          ((ab)Z.v(Z.f())).Code(Z.f(), Z.f());
          return;
          ((ab)Z.v(Z.f())).I(Z.f(), Z.f());
          return;
          paramInt = Z.h();
          i1 = Z.h();
          ((ab)Z.v(Z.f())).I(i1, paramInt, Z.f());
          return;
          paramInt = Z.h();
          i1 = Z.h();
          ((ab)Z.v(Z.f())).Z(i1, paramInt, Z.f());
          return;
          ((ab)Z.v(Z.f())).p();
          return;
          ((ab)Z.v(Z.f())).q();
          return;
          Z.b(Z.Code(((ab)Z.v(Z.f())).r()));
          return;
          localObject6 = Z;
          if (((ab)Z.v(Z.f())).s()) {}
          for (paramInt = 1;; paramInt = 0)
          {
            ((aw)localObject6).c(paramInt);
            return;
          }
          if (Z.h() != 0) {}
          for (bool1 = true;; bool1 = false)
          {
            paramInt = Z.h();
            ((ab)Z.v(Z.f())).Code(paramInt, bool1);
            return;
          }
          if (Z.h() != 0) {}
          for (bool1 = true;; bool1 = false)
          {
            ((ab)Z.v(Z.f())).Code(bool1);
            return;
          }
          b.L = true;
          b.C("md");
          return;
          Z.m();
          ((ab)Z.v(Z.f())).Code(Z.I);
          Z.b(Z.n());
          return;
          localObject6 = ((ab)Z.v(Z.f())).b();
          Z.b(((k)localObject6).a());
          return;
          localObject10 = new Object[110];
          Object localObject11 = new int[110];
          if (Z.h() != 0)
          {
            paramInt = 1;
            if (Z.h() == 0) {
              break label8745;
            }
            i1 = 1;
            if (Z.h() == 0) {
              break label8750;
            }
            bool1 = true;
            if (Z.h() == 0) {
              break label8756;
            }
            i2 = 1;
            label7781:
            i3 = Z.f();
            if ((b.P) && (paramInt == 0) && (i3 != 0)) {
              localObject10[86] = Z.q(i3);
            }
            i4 = Z.h();
            localObject11[17] = Z.h();
            localObject11[93] = Z.h();
            localObject11[80] = Z.h();
            localObject11[14] = Code.C(Z.h());
            if (Z.h() != 0) {
              break label8762;
            }
            i3 = 1;
            localObject11[23] = i3;
            i5 = localObject11[24];
            if (Z.h() != 1) {
              break label8770;
            }
            i3 = 16;
            label7917:
            localObject11[24] = (i3 | i5);
            i5 = localObject11[24];
            if (Z.h() != 1) {
              break label8776;
            }
            i3 = 1073741824;
            localObject11[24] = (i3 | i5);
            if (Z.h() != 1) {
              break label8782;
            }
            i3 = 115;
            localObject11[21] = i3;
            localObject11[56] = Z.h();
            i3 = Z.f();
            if (i3 != 0)
            {
              localObject6 = Z.f(i3);
              localObject10[27] = localObject6;
              if (((String)localObject6).startsWith("-")) {
                localObject11[17] = 1;
              }
            }
            localObject11[20] = Z.h();
            localObject11[19] = Z.h();
            i3 = Z.f();
            if (i3 != 0) {
              localObject10[42] = Z.f(i3);
            }
            i3 = Z.f();
            if (i3 != 0) {
              localObject10[38] = Z.f(i3);
            }
            localObject10[53] = Z.f(Z.f());
            localObject6 = (String)localObject10[53];
            if ("debug:".equals(localObject6)) {
              Y = true;
            }
            if ((Y) && ("opera:routing".equals(localObject6)))
            {
              if (ap.b) {
                break label8789;
              }
              bool2 = true;
              label8180:
              ap.b = bool2;
            }
            if ((b.P) && (paramInt == 0))
            {
              localObject11[99] = 2;
              localObject10[94] = b.S;
              if (i2 != 0) {
                localObject11[85] |= 2;
              }
              if (i1 != 0) {
                localObject11[85] |= 1;
              }
              i2 = localObject11[85];
              if ((b.Q & 0x2) == 0) {
                break label8795;
              }
              paramInt = 8;
              if ((b.Q & 0x1) == 0) {
                break label8800;
              }
              i1 = 4;
              localObject11[85] = (paramInt | i1 | i2);
            }
            if (d != null) {
              localObject10[77] = d;
            }
            if (S != null) {
              localObject10[73] = S;
            }
            if (T != null)
            {
              localObject10[79] = T;
              e = false;
            }
            localObject8 = b.N;
            if (localObject8 != null)
            {
              localObject6 = localObject8;
              if (!((String)localObject8).equals("")) {}
            }
            else
            {
              localObject6 = Code.Code("OM-Campaign");
            }
            if ((localObject6 != null) && (!((String)localObject6).equals("")) && (!((String)localObject6).equals("debug"))) {
              localObject10[78] = localObject6;
            }
            if (Z.u(37) != 0) {
              localObject11[43] |= 524288;
            }
            if (Code.Y()) {
              localObject11[109] |= 8;
            }
            if (Code.T()) {
              localObject11[43] |= 262144;
            }
            if (!Code.d()) {
              break label8805;
            }
            paramInt = 116;
            localObject11[87] = paramInt;
            localObject11[101] = 115;
            localObject10[103] = "m";
            localObject11[102] = 53;
            localObject6 = E();
            if (!((String)localObject6).equals("hqvga")) {
              break label8811;
            }
            paramInt = 4;
            localObject11[76] = paramInt;
            localObject11[15] = Z.h();
            localObject6 = null;
            paramInt = Z.f();
            if (paramInt == 0) {
              break label10067;
            }
            localObject8 = (ab)Z.v(paramInt);
            if (i4 == 0) {
              break label10061;
            }
            localObject6 = ((ab)localObject8).o();
            localObject9 = ((ab)localObject8).f();
            if (localObject9 != null) {
              localObject11[62] = ((k)localObject9).C();
            }
            localObject10[9] = ((ab)localObject8).a;
            localObject8 = localObject6;
            localObject6 = localObject9;
          }
          for (;;)
          {
            localObject6 = new ab(this, (Object[])localObject10, (int[])localObject11, (k)localObject6, (Hashtable)localObject8, bool1);
            this.J.addElement(localObject6);
            Z.Code(Z.f());
            Z.k();
            ((ab)localObject6).c = Z.Code(69, 9, localObject6);
            Z.C(((ab)localObject6).c, 1, Z.Code());
            Z.Code(0);
            I((ab)localObject6);
            b.Code((Runnable)localObject6);
            Z.b(((ab)localObject6).c);
            return;
            paramInt = 0;
            break;
            i1 = 0;
            break label7757;
            bool1 = false;
            break label7769;
            i2 = 0;
            break label7781;
            i3 = b.t;
            break label7889;
            i3 = 0;
            break label7917;
            i3 = 0;
            break label7949;
            i3 = 100;
            break label7973;
            bool2 = false;
            break label8180;
            paramInt = 0;
            break label8260;
            label8800:
            i1 = 0;
            break label8270;
            label8805:
            paramInt = 109;
            break label8487;
            label8811:
            if (((String)localObject6).equals("qvga"))
            {
              paramInt = 1;
              break label8533;
            }
            if (((String)localObject6).equals("hvga"))
            {
              paramInt = 2;
              break label8533;
            }
            if (((String)localObject6).equals("vga"))
            {
              paramInt = 3;
              break label8533;
            }
            if (((String)localObject6).equals("svga"))
            {
              paramInt = 6;
              break label8533;
            }
            paramInt = 0;
            break label8533;
            localObject6 = (ab)Z.v(Z.f());
            paramInt = Z.h();
            i1 = Z.h();
            i2 = Z.f();
            if (Z.h() != 0)
            {
              bool1 = true;
              if (Z.h() == 0) {
                break label9031;
              }
              bool2 = true;
              label8944:
              if (Z.h() == 0) {
                break label9037;
              }
            }
            for (boolean bool3 = true;; bool3 = false)
            {
              i3 = Z.h();
              i4 = Z.f();
              i5 = Z.h();
              i6 = Z.h();
              i7 = Z.f();
              ((ab)localObject6).b().Code(i7, i6, i5, i4, i3, bool3, bool2, bool1, i2, i1, paramInt);
              return;
              bool1 = false;
              break;
              bool2 = false;
              break label8944;
            }
            localObject6 = Z;
            localObject8 = ((ab)Z.v(Z.f())).b();
            Z.f();
            ((aw)localObject6).b(((k)localObject8).b());
            return;
            localObject6 = (ab)Z.v(Z.f());
            Z.f();
            paramInt = Z.h();
            i1 = Z.h();
            i2 = Z.f();
            if (Z.h() != 0)
            {
              bool1 = true;
              if (Z.h() == 0) {
                break label9257;
              }
              bool2 = true;
              if (Z.h() == 0) {
                break label9263;
              }
            }
            for (bool3 = true;; bool3 = false)
            {
              i3 = Z.h();
              i4 = Z.f();
              i5 = Z.h();
              i6 = Z.h();
              i7 = Z.f();
              ((ab)localObject6).b().Code(i7, i6, i5, i4, i3, bool3, bool2, bool1, i2, i1, paramInt);
              Z.b(((ab)localObject6).b().b());
              return;
              bool1 = false;
              break;
              bool2 = false;
              break label9156;
            }
            localObject6 = Z;
            if (Code.f()) {}
            for (paramInt = 1;; paramInt = 0)
            {
              ((aw)localObject6).c(paramInt);
              return;
            }
            localObject6 = Z;
            if (((ab)Z.v(Z.f())).B()) {}
            for (paramInt = 1;; paramInt = 0)
            {
              ((aw)localObject6).c(paramInt);
              return;
            }
            ((ab)Z.v(Z.f())).g();
            return;
            localObject6 = Z;
            if (((ab)Z.v(Z.f())).b().C(Z.f(), Z.f())) {}
            for (paramInt = 1;; paramInt = 0)
            {
              ((aw)localObject6).c(paramInt);
              return;
            }
            ((ab)Z.v(Z.f())).m();
            return;
            localObject6 = ((ab)Z.v(Z.f())).b();
            if (Z.h() != 0) {}
            for (bool1 = true;; bool1 = false)
            {
              ((k)localObject6).I(bool1);
              return;
            }
            char c1 = (char)Z.h();
            paramInt = Z.h();
            localObject6 = Z;
            localObject8 = ((ab)Z.v(Z.f())).b();
            Z.f();
            ((aw)localObject6).b(((k)localObject8).Code(paramInt, c1));
            return;
            Z.c(((ab)Z.v(Z.f())).b().d(Z.h()));
            return;
            Z.b(((ab)Z.v(Z.f())).b().e(Z.h()));
            return;
            Z.c(((ab)Z.v(Z.f())).b().f(Z.h()));
            return;
            Z.c(((ab)Z.v(Z.f())).b().g(Z.h()));
            return;
            Z.c(((ab)Z.v(Z.f())).b().h(Z.h()));
            return;
            Z.c(((ab)Z.v(Z.f())).b().d());
            return;
            Z.c(((ab)Z.v(Z.f())).b().e());
            return;
            Z.b(((ab)Z.v(Z.f())).b().i(Z.h()));
            return;
            Z.c(((ab)Z.v(Z.f())).b().j(Z.h()));
            return;
            localObject8 = (ab)Z.v(Z.f());
            paramInt = Z.f();
            if (paramInt != 0) {}
            for (localObject6 = Z.f(paramInt);; localObject6 = null)
            {
              ((ab)localObject8).Code((String)localObject6, Z.h(), Z.f(Z.f()));
              return;
            }
            Z.b(Z.Code(((ab)Z.v(Z.f())).b().l(Z.h())));
            return;
            Z.b(Z.Code(((ab)Z.v(Z.f())).b().m(Z.h())));
            return;
            Z.b(Z.Code(((ab)Z.v(Z.f())).b().n(Z.h())));
            return;
            Z.b(((ab)Z.v(Z.f())).b().Z(Z.h(), Z.f()));
            return;
            localObject6 = null;
            break label8588;
            localObject8 = null;
          }
        }
        break label4696;
      }
      label8533:
      label10081:
      localObject6 = null;
    }
  }
  
  /* Error */
  public final void Code(int paramInt)
  {
    // Byte code:
    //   0: aload_0
    //   1: monitorenter
    //   2: aload_0
    //   3: invokevirtual 929	g:f	()Z
    //   6: istore_2
    //   7: iload_2
    //   8: ifeq +6 -> 14
    //   11: aload_0
    //   12: monitorexit
    //   13: return
    //   14: aload_0
    //   15: iconst_1
    //   16: putfield 121	g:i	Z
    //   19: aload_0
    //   20: iload_1
    //   21: putfield 109	g:j	I
    //   24: aload_0
    //   25: invokevirtual 124	java/lang/Object:notifyAll	()V
    //   28: aload_0
    //   29: getfield 121	g:i	Z
    //   32: ifeq -21 -> 11
    //   35: aload_0
    //   36: invokevirtual 935	java/lang/Object:wait	()V
    //   39: goto -11 -> 28
    //   42: astore_3
    //   43: goto -32 -> 11
    //   46: astore_3
    //   47: aload_0
    //   48: monitorexit
    //   49: aload_3
    //   50: athrow
    // Local variable table:
    //   start	length	slot	name	signature
    //   0	51	0	this	g
    //   0	51	1	paramInt	int
    //   6	2	2	bool	boolean
    //   42	1	3	localInterruptedException	InterruptedException
    //   46	4	3	localObject	Object
    // Exception table:
    //   from	to	target	type
    //   2	7	42	java/lang/InterruptedException
    //   14	28	42	java/lang/InterruptedException
    //   28	39	42	java/lang/InterruptedException
    //   2	7	46	finally
    //   14	28	46	finally
    //   28	39	46	finally
  }
  
  public final void Code(int paramInt1, int paramInt2)
  {
    try
    {
      Z.b(paramInt1);
      Code(paramInt2);
      return;
    }
    finally
    {
      localObject = finally;
      throw localObject;
    }
  }
  
  void Code(ab paramab) {}
  
  public void Code(Object paramObject)
  {
    if ((paramObject instanceof k)) {
      ((k)paramObject).c();
    }
    for (;;)
    {
      Code.Z(paramObject);
      return;
      if ((paramObject instanceof ab))
      {
        ab localab = (ab)paramObject;
        localab.e();
        this.J.removeElement(paramObject);
        Z(localab);
        if (paramObject == this.B) {
          this.B = null;
        }
      }
      else if ((paramObject instanceof br))
      {
        ((br)paramObject).Code = 0;
      }
    }
  }
  
  /* Error */
  public final void Code(q paramq)
  {
    // Byte code:
    //   0: iconst_0
    //   1: istore 4
    //   3: iconst_0
    //   4: istore_2
    //   5: invokestatic 1433	bj:B	()Z
    //   8: ifeq +8 -> 16
    //   11: aload_1
    //   12: invokestatic 1435	bj:Code	(Lq;)V
    //   15: return
    //   16: iload 4
    //   18: istore_3
    //   19: aload_0
    //   20: aload_1
    //   21: putfield 1437	g:f	Lq;
    //   24: iload 4
    //   26: istore_3
    //   27: aload_0
    //   28: aload_0
    //   29: getfield 1437	g:f	Lq;
    //   32: invokeinterface 1439 1 0
    //   37: putfield 917	g:ab	I
    //   40: iload 4
    //   42: istore_3
    //   43: aload_0
    //   44: aload_0
    //   45: getfield 1437	g:f	Lq;
    //   48: invokeinterface 1440 1 0
    //   53: putfield 919	g:ac	I
    //   56: iload 4
    //   58: istore_3
    //   59: aload_0
    //   60: aload_0
    //   61: getfield 1437	g:f	Lq;
    //   64: invokeinterface 1441 1 0
    //   69: putfield 921	g:ad	I
    //   72: iload 4
    //   74: istore_3
    //   75: aload_0
    //   76: aload_0
    //   77: getfield 1437	g:f	Lq;
    //   80: invokeinterface 1442 1 0
    //   85: putfield 923	g:ae	I
    //   88: iload 4
    //   90: istore_3
    //   91: invokestatic 1183	java/lang/System:currentTimeMillis	()J
    //   94: lstore 5
    //   96: iload 4
    //   98: istore_3
    //   99: aload_0
    //   100: monitorenter
    //   101: aload_0
    //   102: getfield 107	g:g	Z
    //   105: ifne +68 -> 173
    //   108: aload_0
    //   109: getfield 931	g:h	Z
    //   112: ifne +61 -> 173
    //   115: aload_0
    //   116: iconst_1
    //   117: putfield 107	g:g	Z
    //   120: aload_0
    //   121: monitorexit
    //   122: getstatic 177	g:Z	Law;
    //   125: invokevirtual 936	aw:C	()V
    //   128: aload_0
    //   129: invokevirtual 889	g:s	()I
    //   132: putstatic 103	g:aa	I
    //   135: aload_0
    //   136: aload_0
    //   137: getfield 1010	g:q	I
    //   140: invokevirtual 1443	g:b	(I)V
    //   143: ldc 101
    //   145: putstatic 103	g:aa	I
    //   148: aload_0
    //   149: invokespecial 1444	g:A	()V
    //   152: iload 4
    //   154: istore_3
    //   155: aload_1
    //   156: invokestatic 1445	ap:Code	(Lq;)V
    //   159: iload_2
    //   160: ifeq +7 -> 167
    //   163: aload_0
    //   164: invokevirtual 263	g:C	()V
    //   167: aload_0
    //   168: aconst_null
    //   169: putfield 1437	g:f	Lq;
    //   172: return
    //   173: aload_0
    //   174: iconst_1
    //   175: putfield 915	g:n	Z
    //   178: aload_0
    //   179: invokevirtual 124	java/lang/Object:notifyAll	()V
    //   182: aload_0
    //   183: getfield 915	g:n	Z
    //   186: ifeq -66 -> 120
    //   189: ldc2_w 1446
    //   192: lload 5
    //   194: ladd
    //   195: invokestatic 1183	java/lang/System:currentTimeMillis	()J
    //   198: lsub
    //   199: l2i
    //   200: istore_3
    //   201: iload_3
    //   202: ifgt +36 -> 238
    //   205: aload_0
    //   206: iconst_0
    //   207: putfield 915	g:n	Z
    //   210: aload_0
    //   211: aload_0
    //   212: getfield 917	g:ab	I
    //   215: aload_0
    //   216: getfield 919	g:ac	I
    //   219: aload_0
    //   220: getfield 921	g:ad	I
    //   223: aload_0
    //   224: getfield 923	g:ae	I
    //   227: invokespecial 947	g:Code	(IIII)V
    //   230: aload_0
    //   231: monitorexit
    //   232: aload_0
    //   233: aconst_null
    //   234: putfield 1437	g:f	Lq;
    //   237: return
    //   238: iload_3
    //   239: i2l
    //   240: lstore 7
    //   242: aload_0
    //   243: lload 7
    //   245: invokevirtual 1449	java/lang/Object:wait	(J)V
    //   248: goto -66 -> 182
    //   251: astore_1
    //   252: aload_0
    //   253: monitorexit
    //   254: iload 4
    //   256: istore_3
    //   257: aload_1
    //   258: athrow
    //   259: astore_1
    //   260: iconst_0
    //   261: istore_2
    //   262: iload_2
    //   263: ifne +76 -> 339
    //   266: aload_0
    //   267: invokevirtual 1450	g:B	()V
    //   270: iconst_1
    //   271: istore_2
    //   272: iload_2
    //   273: istore_3
    //   274: aload_0
    //   275: iconst_0
    //   276: invokevirtual 1024	g:Code	(Z)V
    //   279: iload_2
    //   280: istore_3
    //   281: getstatic 177	g:Z	Law;
    //   284: iconst_0
    //   285: invokevirtual 496	aw:c	(I)V
    //   288: iload_2
    //   289: istore_3
    //   290: getstatic 177	g:Z	Law;
    //   293: bipush 66
    //   295: invokevirtual 1451	aw:C	(I)V
    //   298: goto -139 -> 159
    //   301: astore_1
    //   302: goto -143 -> 159
    //   305: astore_1
    //   306: iload_3
    //   307: ifeq +7 -> 314
    //   310: aload_0
    //   311: invokevirtual 263	g:C	()V
    //   314: aload_0
    //   315: aconst_null
    //   316: putfield 1437	g:f	Lq;
    //   319: aload_1
    //   320: athrow
    //   321: astore_1
    //   322: iconst_1
    //   323: istore_3
    //   324: goto -18 -> 306
    //   327: astore_1
    //   328: iload_2
    //   329: istore_3
    //   330: goto -24 -> 306
    //   333: astore_1
    //   334: iconst_1
    //   335: istore_2
    //   336: goto -74 -> 262
    //   339: goto -67 -> 272
    // Local variable table:
    //   start	length	slot	name	signature
    //   0	342	0	this	g
    //   0	342	1	paramq	q
    //   4	332	2	i1	int
    //   18	312	3	i2	int
    //   1	254	4	i3	int
    //   94	99	5	l1	long
    //   240	4	7	l2	long
    // Exception table:
    //   from	to	target	type
    //   101	120	251	finally
    //   120	122	251	finally
    //   173	182	251	finally
    //   182	201	251	finally
    //   205	232	251	finally
    //   242	248	251	finally
    //   252	254	251	finally
    //   19	24	259	java/lang/Throwable
    //   27	40	259	java/lang/Throwable
    //   43	56	259	java/lang/Throwable
    //   59	72	259	java/lang/Throwable
    //   75	88	259	java/lang/Throwable
    //   91	96	259	java/lang/Throwable
    //   99	101	259	java/lang/Throwable
    //   155	159	259	java/lang/Throwable
    //   257	259	259	java/lang/Throwable
    //   274	279	301	java/lang/Throwable
    //   281	288	301	java/lang/Throwable
    //   290	298	301	java/lang/Throwable
    //   19	24	305	finally
    //   27	40	305	finally
    //   43	56	305	finally
    //   59	72	305	finally
    //   75	88	305	finally
    //   91	96	305	finally
    //   99	101	305	finally
    //   155	159	305	finally
    //   257	259	305	finally
    //   274	279	305	finally
    //   281	288	305	finally
    //   290	298	305	finally
    //   122	152	321	finally
    //   266	270	327	finally
    //   122	152	333	java/lang/Throwable
  }
  
  public void Code(boolean paramBoolean)
  {
    int i2 = 0;
    this.l = System.currentTimeMillis();
    o();
    Object localObject;
    int i1;
    if (b.b)
    {
      localObject = Z;
      i1 = 99;
    }
    for (;;)
    {
      ((aw)localObject).z(i1);
      Code.y();
      if (b.c > 0) {
        t();
      }
      return;
      if ((paramBoolean) || (b < 2))
      {
        paramBoolean = true;
        int i3 = this.J.size();
        i1 = 0;
        label76:
        if (i1 >= i3) {
          break label137;
        }
        localObject = (ab)this.J.elementAt(i1);
        if (localObject == this.B) {
          break label125;
        }
        ((ab)localObject).b().I(paramBoolean);
      }
      for (;;)
      {
        i1 += 1;
        break label76;
        paramBoolean = false;
        break;
        label125:
        ((ab)localObject).b().I(false);
      }
      label137:
      aw localaw = Z;
      localObject = localaw;
      i1 = i2;
      if (paramBoolean)
      {
        i1 = 99;
        localObject = localaw;
      }
    }
  }
  
  public byte[] Code(int paramInt1, int paramInt2, int paramInt3, int paramInt4, int paramInt5)
  {
    return null;
  }
  
  public void I()
  {
    int i3 = 0;
    int i2 = 1;
    x.Code();
    E = a("/v");
    bj.Z();
    Z = new aw(this);
    Code.Code();
    b.I();
    if (Code.m()) {
      c = Code.l();
    }
    if ("debug".equals(Code.Code("OM-Campaign"))) {
      ap.b = true;
    }
    int i1;
    if (D().equals("undefined"))
    {
      j.Code.Z("resource");
      if (!V) {
        break label255;
      }
      i1 = 1;
      label116:
      if (!W) {
        break label260;
      }
    }
    for (;;)
    {
      for (;;)
      {
        i2 = i1 + i2;
        i1 = i3;
        if (i2 > 0) {
          i1 = 50 / i2;
        }
        X = i1;
        ba.Code();
        u();
        new Thread(this).start();
        return;
        if (j.Code.Code("resource")) {}
        label260:
        try
        {
          String str1 = new String(j.Code.Code("resource", 2));
          String str2 = F();
          if ((new String(j.Code.Code("resource", 3)).equals(C(str1))) && (B(str2).equals(B(str1)))) {
            break;
          }
          j.Code.Z("resource");
          label248:
          V = true;
        }
        catch (IOException localIOException)
        {
          label255:
          break label248;
        }
      }
      i1 = 0;
      break label116;
      i2 = 0;
    }
  }
  
  public void I(int paramInt1, int paramInt2)
  {
    Object localObject = Z.v(paramInt1);
    if ((localObject instanceof k)) {
      ((k)localObject).J = paramInt2;
    }
    do
    {
      return;
      if ((localObject instanceof ab))
      {
        ((ab)localObject).c = paramInt2;
        return;
      }
    } while (!(localObject instanceof br));
    ((br)localObject).Code = paramInt2;
  }
  
  public final void I(boolean paramBoolean)
  {
    try
    {
      this.z = paramBoolean;
      notifyAll();
      return;
    }
    finally
    {
      localObject = finally;
      throw localObject;
    }
  }
  
  public InputStream J(String paramString)
  {
    return null;
  }
  
  public final void J()
  {
    this.A = false;
  }
  
  public void Z() {}
  
  public boolean Z(String paramString)
  {
    return false;
  }
  
  final void a()
  {
    try
    {
      if (this.C)
      {
        this.o = true;
        z();
      }
      return;
    }
    finally
    {
      localObject = finally;
      throw localObject;
    }
  }
  
  protected void b(int paramInt)
  {
    if (paramInt == 0)
    {
      Z("paintnode");
      return;
    }
    throw new RuntimeException("TODO");
  }
  
  protected boolean b()
  {
    return false;
  }
  
  /* Error */
  final void c(int paramInt)
  {
    // Byte code:
    //   0: iconst_0
    //   1: istore_2
    //   2: iconst_0
    //   3: istore_3
    //   4: aload_0
    //   5: monitorenter
    //   6: getstatic 865	g:U	[B
    //   9: ifnonnull +124 -> 133
    //   12: iconst_4
    //   13: newarray byte
    //   15: putstatic 865	g:U	[B
    //   18: iload_3
    //   19: istore_2
    //   20: getstatic 865	g:U	[B
    //   23: iload_2
    //   24: ldc_w 1489
    //   27: iload_1
    //   28: iand
    //   29: bipush 24
    //   31: ishr
    //   32: i2b
    //   33: bastore
    //   34: getstatic 865	g:U	[B
    //   37: iload_2
    //   38: iconst_1
    //   39: iadd
    //   40: ldc_w 1490
    //   43: iload_1
    //   44: iand
    //   45: bipush 16
    //   47: ishr
    //   48: i2b
    //   49: bastore
    //   50: getstatic 865	g:U	[B
    //   53: iload_2
    //   54: iconst_2
    //   55: iadd
    //   56: ldc_w 1491
    //   59: iload_1
    //   60: iand
    //   61: bipush 8
    //   63: ishr
    //   64: i2b
    //   65: bastore
    //   66: getstatic 865	g:U	[B
    //   69: iload_2
    //   70: iconst_3
    //   71: iadd
    //   72: iload_1
    //   73: sipush 255
    //   76: iand
    //   77: i2b
    //   78: bastore
    //   79: getstatic 867	g:T	[B
    //   82: ifnonnull +107 -> 189
    //   85: getstatic 865	g:U	[B
    //   88: arraylength
    //   89: iconst_1
    //   90: iadd
    //   91: newarray byte
    //   93: astore 4
    //   95: aload 4
    //   97: putstatic 867	g:T	[B
    //   100: aload 4
    //   102: iconst_0
    //   103: getstatic 865	g:U	[B
    //   106: arraylength
    //   107: iconst_4
    //   108: idiv
    //   109: i2b
    //   110: bastore
    //   111: getstatic 865	g:U	[B
    //   114: iconst_0
    //   115: getstatic 867	g:T	[B
    //   118: iconst_1
    //   119: getstatic 865	g:U	[B
    //   122: arraylength
    //   123: invokestatic 255	java/lang/System:arraycopy	(Ljava/lang/Object;ILjava/lang/Object;II)V
    //   126: iconst_1
    //   127: putstatic 869	g:e	Z
    //   130: aload_0
    //   131: monitorexit
    //   132: return
    //   133: getstatic 865	g:U	[B
    //   136: arraylength
    //   137: istore_3
    //   138: iload_2
    //   139: iload_3
    //   140: if_icmpge +21 -> 161
    //   143: getstatic 865	g:U	[B
    //   146: iload_2
    //   147: invokestatic 1493	az:J	([BI)I
    //   150: iload_1
    //   151: if_icmpeq -21 -> 130
    //   154: iload_2
    //   155: iconst_4
    //   156: iadd
    //   157: istore_2
    //   158: goto -20 -> 138
    //   161: iload_3
    //   162: iconst_4
    //   163: iadd
    //   164: newarray byte
    //   166: astore 4
    //   168: getstatic 865	g:U	[B
    //   171: iconst_0
    //   172: aload 4
    //   174: iconst_0
    //   175: iload_3
    //   176: invokestatic 255	java/lang/System:arraycopy	(Ljava/lang/Object;ILjava/lang/Object;II)V
    //   179: aload 4
    //   181: putstatic 865	g:U	[B
    //   184: iload_3
    //   185: istore_2
    //   186: goto -166 -> 20
    //   189: getstatic 867	g:T	[B
    //   192: arraylength
    //   193: iconst_4
    //   194: iadd
    //   195: newarray byte
    //   197: astore 4
    //   199: getstatic 867	g:T	[B
    //   202: iconst_0
    //   203: aload 4
    //   205: iconst_0
    //   206: getstatic 867	g:T	[B
    //   209: arraylength
    //   210: invokestatic 255	java/lang/System:arraycopy	(Ljava/lang/Object;ILjava/lang/Object;II)V
    //   213: getstatic 865	g:U	[B
    //   216: iload_2
    //   217: aload 4
    //   219: getstatic 867	g:T	[B
    //   222: arraylength
    //   223: iconst_4
    //   224: invokestatic 255	java/lang/System:arraycopy	(Ljava/lang/Object;ILjava/lang/Object;II)V
    //   227: aload 4
    //   229: iconst_0
    //   230: aload 4
    //   232: arraylength
    //   233: iconst_1
    //   234: isub
    //   235: iconst_4
    //   236: idiv
    //   237: i2b
    //   238: bastore
    //   239: aload 4
    //   241: putstatic 867	g:T	[B
    //   244: goto -118 -> 126
    //   247: astore 4
    //   249: aload_0
    //   250: monitorexit
    //   251: aload 4
    //   253: athrow
    // Local variable table:
    //   start	length	slot	name	signature
    //   0	254	0	this	g
    //   0	254	1	paramInt	int
    //   1	216	2	i1	int
    //   3	182	3	i2	int
    //   93	147	4	arrayOfByte	byte[]
    //   247	5	4	localObject	Object
    // Exception table:
    //   from	to	target	type
    //   6	18	247	finally
    //   20	126	247	finally
    //   126	130	247	finally
    //   133	138	247	finally
    //   143	154	247	finally
    //   161	184	247	finally
    //   189	244	247	finally
  }
  
  public void e()
  {
    Code.Code(true);
  }
  
  public boolean f()
  {
    return Code.p();
  }
  
  public void h()
  {
    int i3 = 2;
    int i2 = 1;
    Object localObject = Z;
    label53:
    label83:
    label104:
    label244:
    boolean bool;
    if (b())
    {
      i1 = 1;
      ((aw)localObject).J(0, i1);
      Z.J(1, b.j);
      localObject = Z;
      if (!Code.K()) {
        break label865;
      }
      i1 = 1;
      ((aw)localObject).J(3, i1);
      Z.J(5, b.m);
      localObject = Z;
      if (!b.x) {
        break label870;
      }
      i1 = 1;
      ((aw)localObject).J(12, i1);
      localObject = Z;
      if (!b.Z) {
        break label875;
      }
      i1 = 1;
      ((aw)localObject).J(18, i1);
      localObject = Z;
      if (!Code.X()) {
        break label880;
      }
      i1 = 1;
      label130:
      ((aw)localObject).J(28, i1);
      localObject = Z;
      if (!Code.Y()) {
        break label885;
      }
      i1 = 0;
      label156:
      ((aw)localObject).J(27, i1);
      Z.J(7, 1);
      localObject = Z;
      if (!b.z) {
        break label890;
      }
      i1 = 1;
      label186:
      ((aw)localObject).J(11, i1);
      localObject = Z;
      if (!b.y) {
        break label895;
      }
      i1 = 1;
      label207:
      ((aw)localObject).J(2, i1);
      localObject = Z;
      if ((Code.u() == 0) || (Code.u() >= 4)) {
        break label900;
      }
      i1 = 1;
      ((aw)localObject).J(4, i1);
      if (!b.l)
      {
        String str = Code("resolution");
        localObject = str;
        if ("ri".equals(str)) {
          localObject = E();
        }
        if ("hqvga".equals(localObject)) {
          b.k = true;
        }
        b.l = true;
      }
      localObject = Z;
      if (!b.k) {
        break label905;
      }
      i1 = 1;
      label317:
      ((aw)localObject).J(6, i1);
      localObject = Z;
      if (Code.G() <= 0) {
        break label910;
      }
      i1 = Code.G();
      label350:
      ((aw)localObject).J(8, i1);
      Z.J(9, Code.H());
      Z.J(10, b.u);
      if ((b.e != 0) || (b.Code)) {
        break label916;
      }
      i1 = 3;
      label399:
      Z.J(13, i1);
      localObject = Z;
      if (b.f <= 0) {
        break label929;
      }
      i1 = 1;
      label421:
      ((aw)localObject).J(14, i1);
      localObject = Z;
      if (b.f != 1) {
        break label934;
      }
      i1 = 1;
      label443:
      ((aw)localObject).J(15, i1);
      localObject = Z;
      if (!b.Code) {
        break label939;
      }
      i1 = 1;
      label464:
      ((aw)localObject).J(16, i1);
      localObject = Z;
      if ((!b.Code) || (!b.I)) {
        break label944;
      }
      i1 = 1;
      label491:
      ((aw)localObject).J(17, i1);
      Z.J(19, b.i);
      localObject = Z;
      if ((Code.v() & 0x1) == 0) {
        break label949;
      }
      i1 = 1;
      label530:
      ((aw)localObject).J(20, i1);
      localObject = Z;
      if ((Code.v() & 0x2) == 0) {
        break label954;
      }
      i1 = 1;
      label558:
      ((aw)localObject).J(21, i1);
      localObject = Z;
      if ((Code.v() & 0x4) == 0) {
        break label959;
      }
      i1 = 1;
      label586:
      ((aw)localObject).J(22, i1);
      localObject = Z;
      if ((Code.v() & 0x8) == 0) {
        break label964;
      }
      i1 = 1;
      label615:
      ((aw)localObject).J(23, i1);
      localObject = Z;
      if ((Code.v() & 0x10) == 0) {
        break label969;
      }
      i1 = 1;
      label644:
      ((aw)localObject).J(24, i1);
      localObject = Z;
      if ((Code.v() & 0x20) == 0) {
        break label974;
      }
      i1 = 1;
      label673:
      ((aw)localObject).J(25, i1);
      localObject = Z;
      if ((Code.v() & 0x40) == 0) {
        break label979;
      }
      i1 = 1;
      label702:
      ((aw)localObject).J(26, i1);
      if (b()) {
        break label984;
      }
      bool = true;
      label720:
      b.O = bool;
      localObject = Z;
      if (!b.O) {
        break label990;
      }
      i1 = 1;
      label738:
      ((aw)localObject).J(35, i1);
      b.P = b.O;
      Z.Z(-1, Z.Code(Code.U()));
      localObject = Z;
      if (!Z.Code()) {
        break label995;
      }
      i1 = 1;
      label786:
      ((aw)localObject).J(29, i1);
      localObject = Z;
      if (!Z.I()) {
        break label1000;
      }
    }
    label865:
    label870:
    label1000:
    for (int i1 = i2;; i1 = 0)
    {
      ((aw)localObject).J(30, i1);
      Z.J(31, Z.Z());
      Z.J(32, Z.J());
      Z.J(33, Z.B());
      Z.J(34, Z.C());
      return;
      i1 = 0;
      break;
      i1 = 0;
      break label53;
      i1 = 2;
      break label83;
      label875:
      i1 = 0;
      break label104;
      label880:
      i1 = 0;
      break label130;
      label885:
      i1 = 1;
      break label156;
      label890:
      i1 = 0;
      break label186;
      label895:
      i1 = 0;
      break label207;
      i1 = 0;
      break label244;
      i1 = 0;
      break label317;
      i1 = 7;
      break label350;
      i1 = i3;
      if (b.e != 0) {
        break label399;
      }
      i1 = 1;
      break label399;
      i1 = 0;
      break label421;
      i1 = 0;
      break label443;
      i1 = 0;
      break label464;
      i1 = 0;
      break label491;
      i1 = 0;
      break label530;
      i1 = 0;
      break label558;
      i1 = 0;
      break label586;
      i1 = 0;
      break label615;
      i1 = 0;
      break label644;
      i1 = 0;
      break label673;
      i1 = 0;
      break label702;
      bool = false;
      break label720;
      i1 = 0;
      break label738;
      i1 = 0;
      break label786;
    }
  }
  
  public void i() {}
  
  public void j()
  {
    Z.x(this.q);
    int i1 = 1;
    while (i1 < L.length)
    {
      if (L[i1] != 0) {
        Z.x(L[i1]);
      }
      i1 += 1;
    }
  }
  
  public void k()
  {
    this.q = Z.y(this.q);
    int i1 = 1;
    while (i1 < L.length)
    {
      if (L[i1] != 0) {
        L[i1] = Z.y(L[i1]);
      }
      i1 += 1;
    }
  }
  
  public final void l()
  {
    if (this.l + 5000L < System.currentTimeMillis()) {
      Code(false);
    }
  }
  
  public final void m()
  {
    try
    {
      b.a(Code.J());
      this.x = true;
      notifyAll();
      while (this.x) {
        b.Code(this, 0);
      }
    }
    finally {}
  }
  
  protected final void o()
  {
    if (Z("vm_mem"))
    {
      Object[] arrayOfObject = Z.c();
      int i1 = arrayOfObject.length - 1;
      while (i1 >= 0)
      {
        if ((arrayOfObject[i1] != null) && ((arrayOfObject[i1] instanceof br))) {
          ((br)arrayOfObject[i1]).Z();
        }
        i1 -= 1;
      }
      System.gc();
      Runtime.getRuntime().freeMemory();
    }
  }
  
  public void p()
  {
    Code.n();
  }
  
  public void q() {}
  
  public boolean r()
  {
    return false;
  }
  
  /* Error */
  public void run()
  {
    // Byte code:
    //   0: getstatic 119	g:Code	Le;
    //   3: invokeinterface 1565 1 0
    //   8: iconst_0
    //   9: bipush 20
    //   11: invokestatic 943	bj:Code	(II)V
    //   14: getstatic 177	g:Z	Law;
    //   17: ldc_w 1567
    //   20: invokestatic 421	b:J	(Ljava/lang/String;)Ljava/io/InputStream;
    //   23: invokevirtual 1568	aw:Code	(Ljava/io/InputStream;)V
    //   26: aload_0
    //   27: ldc_w 1570
    //   30: invokevirtual 447	g:Z	(Ljava/lang/String;)Z
    //   33: ifeq +24 -> 57
    //   36: ldc_w 1571
    //   39: invokestatic 421	b:J	(Ljava/lang/String;)Ljava/io/InputStream;
    //   42: astore 8
    //   44: aload 8
    //   46: ldc2_w 1572
    //   49: invokevirtual 1577	java/io/InputStream:skip	(J)J
    //   52: lconst_0
    //   53: lcmp
    //   54: ifgt -10 -> 44
    //   57: getstatic 177	g:Z	Law;
    //   60: invokevirtual 1579	aw:a	()V
    //   63: getstatic 177	g:Z	Law;
    //   66: bipush 47
    //   68: invokevirtual 1580	aw:a	(I)I
    //   71: ifne +180 -> 251
    //   74: aload_0
    //   75: invokevirtual 889	g:s	()I
    //   78: sipush 200
    //   81: iadd
    //   82: istore 4
    //   84: iconst_1
    //   85: istore_1
    //   86: getstatic 119	g:Code	Le;
    //   89: invokeinterface 1581 1 0
    //   94: iconst_0
    //   95: istore_3
    //   96: iconst_0
    //   97: istore 6
    //   99: iconst_1
    //   100: istore 5
    //   102: aload_0
    //   103: invokevirtual 929	g:f	()Z
    //   106: ifne +97 -> 203
    //   109: aload_0
    //   110: monitorenter
    //   111: aload_0
    //   112: iconst_0
    //   113: putfield 107	g:g	Z
    //   116: aload_0
    //   117: iconst_0
    //   118: putfield 121	g:i	Z
    //   121: iload 6
    //   123: istore_2
    //   124: aload_0
    //   125: getfield 915	g:n	Z
    //   128: ifeq +34 -> 162
    //   131: iload 6
    //   133: istore_2
    //   134: getstatic 119	g:Code	Le;
    //   137: invokeinterface 1582 1 0
    //   142: ifne +20 -> 162
    //   145: iload 5
    //   147: ifeq +125 -> 272
    //   150: aload_0
    //   151: iconst_1
    //   152: putfield 107	g:g	Z
    //   155: aload_0
    //   156: iconst_1
    //   157: putfield 121	g:i	Z
    //   160: iconst_1
    //   161: istore_2
    //   162: aload_0
    //   163: invokevirtual 124	java/lang/Object:notifyAll	()V
    //   166: iload_3
    //   167: istore 6
    //   169: iload_2
    //   170: ifne +854 -> 1024
    //   173: aload_0
    //   174: getfield 107	g:g	Z
    //   177: ifeq +111 -> 288
    //   180: aload_0
    //   181: getfield 121	g:i	Z
    //   184: ifne +104 -> 288
    //   187: aload_0
    //   188: invokevirtual 935	java/lang/Object:wait	()V
    //   191: goto -18 -> 173
    //   194: astore 8
    //   196: aload_0
    //   197: monitorexit
    //   198: aload 8
    //   200: athrow
    //   201: astore 8
    //   203: aload_0
    //   204: iconst_1
    //   205: putfield 107	g:g	Z
    //   208: aload_0
    //   209: iconst_0
    //   210: putfield 121	g:i	Z
    //   213: aload_0
    //   214: invokestatic 1583	b:Code	(Ljava/lang/Object;)V
    //   217: getstatic 100	g:N	Ljava/util/Vector;
    //   220: invokevirtual 1587	java/util/Vector:elements	()Ljava/util/Enumeration;
    //   223: astore 8
    //   225: aload 8
    //   227: invokeinterface 1592 1 0
    //   232: ifeq +759 -> 991
    //   235: aload 8
    //   237: invokeinterface 1595 1 0
    //   242: checkcast 998	t
    //   245: invokevirtual 1001	t:Code	()V
    //   248: goto -23 -> 225
    //   251: getstatic 177	g:Z	Law;
    //   254: invokevirtual 1597	aw:b	()V
    //   257: getstatic 177	g:Z	Law;
    //   260: invokevirtual 1599	aw:d	()J
    //   263: pop2
    //   264: iconst_0
    //   265: istore 4
    //   267: iconst_0
    //   268: istore_1
    //   269: goto -183 -> 86
    //   272: aload_0
    //   273: iconst_0
    //   274: putfield 915	g:n	Z
    //   277: aload_0
    //   278: iconst_1
    //   279: putfield 107	g:g	Z
    //   282: iload 6
    //   284: istore_2
    //   285: goto -123 -> 162
    //   288: iload_3
    //   289: istore 6
    //   291: aload_0
    //   292: getfield 109	g:j	I
    //   295: ifge +729 -> 1024
    //   298: iload_3
    //   299: istore 6
    //   301: getstatic 119	g:Code	Le;
    //   304: invokeinterface 1600 1 0
    //   309: ifne +715 -> 1024
    //   312: aload_0
    //   313: getfield 915	g:n	Z
    //   316: ifeq +278 -> 594
    //   319: iload_3
    //   320: istore_2
    //   321: iconst_1
    //   322: istore_3
    //   323: aload_0
    //   324: iconst_1
    //   325: putfield 107	g:g	Z
    //   328: aload_0
    //   329: monitorexit
    //   330: getstatic 177	g:Z	Law;
    //   333: invokevirtual 936	aw:C	()V
    //   336: iload_3
    //   337: ifeq +533 -> 870
    //   340: aload_0
    //   341: getfield 1601	g:y	Z
    //   344: aload_0
    //   345: getfield 1481	g:z	Z
    //   348: if_icmpeq +32 -> 380
    //   351: aload_0
    //   352: aload_0
    //   353: getfield 1481	g:z	Z
    //   356: putfield 1601	g:y	Z
    //   359: getstatic 177	g:Z	Law;
    //   362: astore 8
    //   364: aload_0
    //   365: getfield 1481	g:z	Z
    //   368: ifeq +480 -> 848
    //   371: bipush 52
    //   373: istore_3
    //   374: aload 8
    //   376: iload_3
    //   377: invokevirtual 1451	aw:C	(I)V
    //   380: aload_0
    //   381: getfield 527	g:x	Z
    //   384: ifeq +475 -> 859
    //   387: invokestatic 327	g:E	()Ljava/lang/String;
    //   390: ldc_w 305
    //   393: invokevirtual 294	java/lang/String:equals	(Ljava/lang/Object;)Z
    //   396: ifeq +12 -> 408
    //   399: getstatic 1350	b:Q	B
    //   402: ifne +6 -> 408
    //   405: invokestatic 1602	b:a	()V
    //   408: getstatic 119	g:Code	Le;
    //   411: invokeinterface 223 1 0
    //   416: istore_3
    //   417: getstatic 119	g:Code	Le;
    //   420: invokeinterface 225 1 0
    //   425: istore 5
    //   427: getstatic 119	g:Code	Le;
    //   430: iload_3
    //   431: iload 5
    //   433: invokeinterface 1603 3 0
    //   438: getstatic 119	g:Code	Le;
    //   441: iload_3
    //   442: iload 5
    //   444: invokeinterface 1604 3 0
    //   449: getstatic 177	g:Z	Law;
    //   452: getstatic 1606	b:C	I
    //   455: invokevirtual 496	aw:c	(I)V
    //   458: getstatic 177	g:Z	Law;
    //   461: bipush 65
    //   463: invokevirtual 1451	aw:C	(I)V
    //   466: getstatic 177	g:Z	Law;
    //   469: iload_3
    //   470: invokevirtual 496	aw:c	(I)V
    //   473: getstatic 177	g:Z	Law;
    //   476: iload 5
    //   478: invokevirtual 496	aw:c	(I)V
    //   481: getstatic 177	g:Z	Law;
    //   484: bipush 54
    //   486: invokevirtual 1451	aw:C	(I)V
    //   489: aload_0
    //   490: getfield 115	g:A	Z
    //   493: ifeq +35 -> 528
    //   496: getstatic 177	g:Z	Law;
    //   499: astore 8
    //   501: getstatic 119	g:Code	Le;
    //   504: invokeinterface 1608 1 0
    //   509: ifeq +345 -> 854
    //   512: iconst_1
    //   513: istore_3
    //   514: aload 8
    //   516: iload_3
    //   517: invokevirtual 496	aw:c	(I)V
    //   520: getstatic 177	g:Z	Law;
    //   523: bipush 55
    //   525: invokevirtual 1451	aw:C	(I)V
    //   528: getstatic 177	g:Z	Law;
    //   531: bipush 50
    //   533: invokevirtual 1451	aw:C	(I)V
    //   536: aload_0
    //   537: iconst_0
    //   538: putfield 527	g:x	Z
    //   541: aload_0
    //   542: invokestatic 1583	b:Code	(Ljava/lang/Object;)V
    //   545: aload_0
    //   546: getfield 949	g:r	Z
    //   549: ifeq +15 -> 564
    //   552: aload_0
    //   553: getfield 938	g:C	Z
    //   556: ifne +8 -> 564
    //   559: aload_0
    //   560: iconst_1
    //   561: putfield 938	g:C	Z
    //   564: aload_0
    //   565: invokespecial 1609	g:y	()V
    //   568: iconst_0
    //   569: istore 5
    //   571: iconst_0
    //   572: istore_3
    //   573: aload_0
    //   574: iconst_m1
    //   575: putfield 109	g:j	I
    //   578: iload_3
    //   579: istore 7
    //   581: iload_2
    //   582: istore_3
    //   583: iload 5
    //   585: istore 6
    //   587: iload 7
    //   589: istore 5
    //   591: goto -489 -> 102
    //   594: aload_0
    //   595: getfield 1483	g:o	Z
    //   598: ifeq +50 -> 648
    //   601: aload_0
    //   602: iconst_0
    //   603: putfield 1483	g:o	Z
    //   606: getstatic 177	g:Z	Law;
    //   609: sipush 160
    //   612: invokevirtual 496	aw:c	(I)V
    //   615: getstatic 177	g:Z	Law;
    //   618: getstatic 1611	b:E	I
    //   621: invokevirtual 496	aw:c	(I)V
    //   624: getstatic 177	g:Z	Law;
    //   627: iconst_0
    //   628: invokevirtual 496	aw:c	(I)V
    //   631: aload_0
    //   632: bipush 32
    //   634: putfield 109	g:j	I
    //   637: iload_3
    //   638: istore 5
    //   640: iload_2
    //   641: istore_3
    //   642: iload 5
    //   644: istore_2
    //   645: goto -322 -> 323
    //   648: iload_3
    //   649: istore 6
    //   651: aload_0
    //   652: getfield 931	g:h	Z
    //   655: ifne +121 -> 776
    //   658: aload_0
    //   659: getfield 1180	g:m	Z
    //   662: ifeq +44 -> 706
    //   665: aload_0
    //   666: getfield 1178	g:k	I
    //   669: aload_0
    //   670: invokevirtual 889	g:s	()I
    //   673: isub
    //   674: istore 6
    //   676: iload 6
    //   678: istore_3
    //   679: iload 6
    //   681: ifgt +25 -> 706
    //   684: aload_0
    //   685: iconst_0
    //   686: putfield 1180	g:m	Z
    //   689: aload_0
    //   690: iconst_3
    //   691: putfield 109	g:j	I
    //   694: iload 6
    //   696: istore 5
    //   698: iload_2
    //   699: istore_3
    //   700: iload 5
    //   702: istore_2
    //   703: goto -380 -> 323
    //   706: iload_1
    //   707: ifeq +40 -> 747
    //   710: iload 4
    //   712: aload_0
    //   713: invokevirtual 889	g:s	()I
    //   716: isub
    //   717: istore 6
    //   719: iload 6
    //   721: istore_3
    //   722: iload 6
    //   724: ifgt +23 -> 747
    //   727: aload_0
    //   728: bipush 47
    //   730: putfield 109	g:j	I
    //   733: iload 6
    //   735: istore 5
    //   737: iconst_0
    //   738: istore_1
    //   739: iload_2
    //   740: istore_3
    //   741: iload 5
    //   743: istore_2
    //   744: goto -421 -> 323
    //   747: iload 5
    //   749: ifne +283 -> 1032
    //   752: aload_0
    //   753: getfield 527	g:x	Z
    //   756: ifne +276 -> 1032
    //   759: iload_3
    //   760: istore 6
    //   762: aload_0
    //   763: getfield 1601	g:y	Z
    //   766: aload_0
    //   767: getfield 1481	g:z	Z
    //   770: if_icmpeq +6 -> 776
    //   773: goto +259 -> 1032
    //   776: getstatic 177	g:Z	Law;
    //   779: aload_0
    //   780: invokevirtual 1613	aw:Code	(Ljava/lang/Object;)Z
    //   783: ifeq +24 -> 807
    //   786: iload 6
    //   788: istore_3
    //   789: getstatic 177	g:Z	Law;
    //   792: invokevirtual 1614	aw:s	()Z
    //   795: ifeq -622 -> 173
    //   798: iconst_1
    //   799: istore 5
    //   801: iload 6
    //   803: istore_3
    //   804: goto -631 -> 173
    //   807: aload_0
    //   808: getfield 931	g:h	Z
    //   811: ifne +27 -> 838
    //   814: aload_0
    //   815: getfield 1180	g:m	Z
    //   818: ifne +7 -> 825
    //   821: iload_1
    //   822: ifeq +16 -> 838
    //   825: aload_0
    //   826: iload 6
    //   828: i2l
    //   829: invokevirtual 1449	java/lang/Object:wait	(J)V
    //   832: iload 6
    //   834: istore_3
    //   835: goto -662 -> 173
    //   838: aload_0
    //   839: invokevirtual 935	java/lang/Object:wait	()V
    //   842: iload 6
    //   844: istore_3
    //   845: goto -672 -> 173
    //   848: bipush 53
    //   850: istore_3
    //   851: goto -477 -> 374
    //   854: iconst_0
    //   855: istore_3
    //   856: goto -342 -> 514
    //   859: getstatic 177	g:Z	Law;
    //   862: bipush 50
    //   864: invokevirtual 1451	aw:C	(I)V
    //   867: goto -322 -> 545
    //   870: aload_0
    //   871: invokespecial 1609	g:y	()V
    //   874: aload_0
    //   875: getfield 109	g:j	I
    //   878: bipush 47
    //   880: if_icmpne +89 -> 969
    //   883: getstatic 177	g:Z	Law;
    //   886: aload_0
    //   887: getfield 109	g:j	I
    //   890: invokevirtual 1580	aw:a	(I)I
    //   893: ifne +27 -> 920
    //   896: aload_0
    //   897: invokevirtual 889	g:s	()I
    //   900: sipush 200
    //   903: iadd
    //   904: istore 4
    //   906: iconst_1
    //   907: istore_1
    //   908: iconst_1
    //   909: istore 6
    //   911: iload_3
    //   912: istore 5
    //   914: iload 6
    //   916: istore_3
    //   917: goto -344 -> 573
    //   920: getstatic 177	g:Z	Law;
    //   923: invokevirtual 1597	aw:b	()V
    //   926: getstatic 177	g:Z	Law;
    //   929: invokevirtual 1599	aw:d	()J
    //   932: pop2
    //   933: getstatic 119	g:Code	Le;
    //   936: getstatic 119	g:Code	Le;
    //   939: invokeinterface 223 1 0
    //   944: getstatic 119	g:Code	Le;
    //   947: invokeinterface 225 1 0
    //   952: invokeinterface 1603 3 0
    //   957: iconst_1
    //   958: istore 6
    //   960: iload_3
    //   961: istore 5
    //   963: iload 6
    //   965: istore_3
    //   966: goto -393 -> 573
    //   969: getstatic 177	g:Z	Law;
    //   972: aload_0
    //   973: getfield 109	g:j	I
    //   976: invokevirtual 1451	aw:C	(I)V
    //   979: iconst_1
    //   980: istore 6
    //   982: iload_3
    //   983: istore 5
    //   985: iload 6
    //   987: istore_3
    //   988: goto -415 -> 573
    //   991: getstatic 100	g:N	Ljava/util/Vector;
    //   994: invokevirtual 1617	java/util/Vector:removeAllElements	()V
    //   997: invokestatic 1618	ap:I	()V
    //   1000: aload_0
    //   1001: invokespecial 1620	g:M	()V
    //   1004: invokestatic 1621	ab:Code	()V
    //   1007: getstatic 119	g:Code	Le;
    //   1010: invokeinterface 1623 1 0
    //   1015: getstatic 119	g:Code	Le;
    //   1018: invokeinterface 1624 1 0
    //   1023: return
    //   1024: iload_2
    //   1025: istore_3
    //   1026: iload 6
    //   1028: istore_2
    //   1029: goto -706 -> 323
    //   1032: iload_3
    //   1033: istore_2
    //   1034: iconst_1
    //   1035: istore_3
    //   1036: goto -713 -> 323
    // Local variable table:
    //   start	length	slot	name	signature
    //   0	1039	0	this	g
    //   85	823	1	i1	int
    //   123	911	2	i2	int
    //   95	941	3	i3	int
    //   82	823	4	i4	int
    //   100	884	5	i5	int
    //   97	930	6	i6	int
    //   579	9	7	i7	int
    //   42	3	8	localInputStream	InputStream
    //   194	5	8	localObject1	Object
    //   201	1	8	localThrowable	Throwable
    //   223	292	8	localObject2	Object
    // Exception table:
    //   from	to	target	type
    //   111	121	194	finally
    //   124	131	194	finally
    //   134	145	194	finally
    //   150	160	194	finally
    //   162	166	194	finally
    //   173	191	194	finally
    //   196	198	194	finally
    //   272	282	194	finally
    //   291	298	194	finally
    //   301	319	194	finally
    //   323	330	194	finally
    //   594	637	194	finally
    //   651	658	194	finally
    //   658	676	194	finally
    //   684	694	194	finally
    //   710	719	194	finally
    //   727	733	194	finally
    //   752	759	194	finally
    //   762	773	194	finally
    //   776	786	194	finally
    //   789	798	194	finally
    //   807	821	194	finally
    //   825	832	194	finally
    //   838	842	194	finally
    //   8	44	201	java/lang/Throwable
    //   44	57	201	java/lang/Throwable
    //   57	84	201	java/lang/Throwable
    //   86	94	201	java/lang/Throwable
    //   102	111	201	java/lang/Throwable
    //   198	201	201	java/lang/Throwable
    //   251	264	201	java/lang/Throwable
    //   330	336	201	java/lang/Throwable
    //   340	371	201	java/lang/Throwable
    //   374	380	201	java/lang/Throwable
    //   380	408	201	java/lang/Throwable
    //   408	512	201	java/lang/Throwable
    //   514	528	201	java/lang/Throwable
    //   528	545	201	java/lang/Throwable
    //   545	564	201	java/lang/Throwable
    //   564	568	201	java/lang/Throwable
    //   573	578	201	java/lang/Throwable
    //   859	867	201	java/lang/Throwable
    //   870	906	201	java/lang/Throwable
    //   920	957	201	java/lang/Throwable
    //   969	979	201	java/lang/Throwable
  }
  
  public int s()
  {
    return (int)System.currentTimeMillis();
  }
  
  public final void t()
  {
    if (af) {
      return;
    }
    int i5 = this.J.size();
    int i3;
    int i2;
    int i1;
    label90:
    int i6;
    if (this.B != null)
    {
      i3 = b.c * 1024;
      Object localObject = this.B.b();
      i2 = ((k)localObject).o(i3);
      i1 = i2;
      if (i2 > i3) {
        i1 = Code((k)localObject, i3);
      }
      i2 = i3 - Math.max(i1, b.d * 1024);
      i1 = i2;
      if (i5 > 1) {
        i1 = i2 / (i5 - 1);
      }
      i6 = Math.max(1, i1);
      i2 = 0;
      i1 = 0;
      label101:
      if (i2 >= i5) {
        break label226;
      }
      localObject = (ab)this.J.elementAt(i2);
      if (localObject == this.B) {
        break label244;
      }
      localObject = ((ab)localObject).b();
      int i7 = Math.max(1, i6 + i1);
      int i4 = ((k)localObject).o(i7);
      i3 = i4;
      if (i4 > i7) {
        i3 = Code((k)localObject, i7);
      }
      if (i3 <= i6) {
        break label216;
      }
      i1 -= i3 - i6;
    }
    label216:
    label226:
    label244:
    for (;;)
    {
      i2 += 1;
      break label101;
      i2 = b.c * 1024;
      i1 = i2;
      if (i5 <= 0) {
        break label90;
      }
      i1 = i2 / i5;
      break label90;
      i1 = i6 - i3 + i1;
      continue;
      if (i1 >= 0) {
        break;
      }
      af = true;
      Code(true);
      af = false;
      return;
    }
  }
  
  final void v()
  {
    try
    {
      U = null;
      return;
    }
    finally
    {
      localObject = finally;
      throw localObject;
    }
  }
  
  protected void w() {}
  
  public final void x()
  {
    int i2 = this.J.size();
    int i1 = 0;
    while (i1 < i2)
    {
      ((ab)this.J.elementAt(i1)).b().I(true);
      i1 += 1;
    }
    Object[] arrayOfObject = Z.c();
    Vector localVector = new Vector();
    i1 = 0;
    while (i1 < arrayOfObject.length)
    {
      if ((arrayOfObject[i1] instanceof br)) {
        localVector.addElement(arrayOfObject[i1]);
      }
      i1 += 1;
    }
    Code(localVector);
  }
}


/* Location:           F:\jar\\classes-dex2jar.jar
 * Qualified Name:     g
 * JD-Core Version:    0.7.0-SNAPSHOT-20130630
 */